Workbook
Name sites: [1]Sheet3!$A:$B

Sheet Test
A1: Source | B1: Target
A2: https://serco.sharepoint.com/sites/SA-TECHM365DataMigration

Sheet Pilot-Wave1
A1: SITE NAME | B1: SITE URL (MAIN) | C1: Target URL | D1: Wave | E1: SITE TYPE | F1: SITE OWNERS - EMAIL | G1: SIZE IN GB | H1: BU | I1: Portfolio | J1: Active Site | K1: Action | L1: Site Exist in GCCH? | M1: Teams
A2: CCS_ASG_Team | B2: https://serco.sharepoint.com/sites/CCS_ASG_Team | D2: Wave 1 | E2: SharePoint | F2: Christina.Hall@serco-na.com | G2: 0 | H2: Corporate Services | I2: Technology | J2: Yes | K2: Migrate
A3: =_xlfn.XLOOKUP(B3,'All Sites_20260129180943356'!B:B,'All Sites_20260129180943356'!A:A) -> Cyber Opportunities | B3: https://serco.sharepoint.com/sites/CyberOpportunities | D3: Wave 1 | E3: MS Teams | F3: Tracy.West@serco-na.com | G3: 0 | H3: Corporate Services | I3: Technology | J3: Yes | K3: Migrate
A4: Agile Impact Leadership | B4: https://serco.sharepoint.com/sites/AgileImpactLeadership | D4: Wave 1 | E4: SharePoint | F4: Tracy.West@serco-na.com; Wayne.Borchers@serco-na.com; Timothy.Baker@serco-na.com | G4: 0 | H4: Corporate Services | I4: #N/A | J4: Yes | K4: Migrate
A5: =_xlfn.XLOOKUP(B5,'All Sites_20260129180943356'!B:B,'All Sites_20260129180943356'!A:A) -> Temp Site | B5: https://serco.sharepoint.com/sites/TempSite | D5: Wave 1 | E5: SharePoint | F5: Miles.Olson@serco-na.com | G5: 0.01 | H5: Corporate Services | I5: Technology | J5: Yes | K5: Migrate
A6: =_xlfn.XLOOKUP(B6,'All Sites_20260129180943356'!B:B,'All Sites_20260129180943356'!A:A) -> 30238.T13_N81F_OA Community Inventory Assessment | B6: https://serco.sharepoint.com/sites/30238.T13_N81F_OACommunityInventoryAssessment | D6: Wave 1 | E6: MS Teams | F6: Jason.Heuer@serco-na.com; Kelly.Cormican@serco-na.com | G6: 0.01 | H6: Corporate Services | I6: #N/A | J6: Yes | K6: Migrate
A7: =_xlfn.XLOOKUP(B7,'All Sites_20260129180943356'!B:B,'All Sites_20260129180943356'!A:A) -> AcqMgmt Group | B7: https://serco.sharepoint.com/sites/acqmgmt | D7: Wave 1 | E7: MS Teams | F7: Timothy.Baker@serco-na.com | G7: 0.01 | H7: Corporate Services | I7: Technology | J7: Yes | K7: Migrate
A8: =_xlfn.XLOOKUP(B8,'All Sites_20260129180943356'!B:B,'All Sites_20260129180943356'!A:A) -> Decision Support Laptop Reservation | B8: https://serco.sharepoint.com/sites/DecisionSupportLaptopReservation | D8: Wave 1 | E8: MS Teams | F8: Christopher.Pritchet@serco-na.com; Brock.Magnino@serco-na.com | G8: 0.01 | H8: Corporate Services | I8: #N/A | J8: Yes | K8: Migrate
A9: =_xlfn.XLOOKUP(B9,'All Sites_20260129180943356'!B:B,'All Sites_20260129180943356'!A:A) -> J-Plant Core | B9: https://serco.sharepoint.com/sites/J-PlantCore | D9: Wave 1 | E9: MS Teams | F9: Charles.Dewar@serco-na.com | G9: 0.01 | H9: Corporate Services | I9: Citizens Services | J9: Yes | K9: Migrate
A10: =_xlfn.XLOOKUP(B10,'All Sites_20260129180943356'!B:B,'All Sites_20260129180943356'!A:A) -> MTUAS | B10: https://serco.sharepoint.com/sites/MTUAS | D10: Wave 1 | E10: MS Teams | F10: Brian.Hall@serco-na.com | G10: 0.01 | H10: Corporate Services | I10: Technology | J10: Yes | K10: Migrate
A11: =_xlfn.XLOOKUP(B11,'All Sites_20260129180943356'!B:B,'All Sites_20260129180943356'!A:A) -> N81 Expeditionary Logistics | B11: https://serco.sharepoint.com/sites/N81ExpeditionaryLogistics | D11: Wave 1 | E11: MS Teams | F11: Jason.Heuer@serco-na.com | G11: 0.01 | H11: Corporate Services | I11: Technology | J11: Yes | K11: Migrate
A12: =_xlfn.XLOOKUP(B12,'All Sites_20260129180943356'!B:B,'All Sites_20260129180943356'!A:A) -> N81F_OA Community Inventory Assessment_30238.T13 | B12: https://serco.sharepoint.com/sites/N81F_OACommunityInventoryAssessment_30238.T13 | D12: Wave 1 | E12: MS Teams | F12: Jason.Heuer@serco-na.com; Kelly.Cormican@serco-na.com | G12: 0.01 | H12: Corporate Services | I12: #N/A | J12: Yes | K12: Migrate
A13: =_xlfn.XLOOKUP(B13,'All Sites_20260129180943356'!B:B,'All Sites_20260129180943356'!A:A) -> Sentinal | B13: https://serco.sharepoint.com/sites/Sentinal | D13: Wave 1 | E13: MS Teams | F13: Thomas.Glass@serco-na.com | G13: 0.01 | H13: Corporate Services | I13: Technology | J13: Yes | K13: Migrate | L13: https://gov.teams.microsoft.us/l/channel/19%3Agcch%3A55483ea836994cd18b870e0f2cf7b7b7%40thread.tacv2/22790%20Sentinel%20BCA?groupId=3c8c6446-af58-4ca2-aad4-2b966be48a77&tenantId=fb1f5cc5-be84-4881-b037-2d641aea97fd&ngc=true
A14: =_xlfn.XLOOKUP(B14,'All Sites_20260129180943356'!B:B,'All Sites_20260129180943356'!A:A) -> Serco Human Capital | B14: https://serco.sharepoint.com/sites/SercoHumanCapital | D14: Wave 1 | E14: MS Teams | F14: Timothy.Winand@serco-na.com | G14: 0.01 | H14: Corporate Services | I14: Technology | J14: Yes | K14: Migrate
A15: =_xlfn.XLOOKUP(B15,'All Sites_20260129180943356'!B:B,'All Sites_20260129180943356'!A:A) -> Serco Human Capital Community of Interest | B15: https://serco.sharepoint.com/sites/SercoHumanCapitalCommunityofInterest | D15: Wave 1 | E15: MS Teams | F15: Timothy.Winand@serco-na.com | G15: 0.01 | H15: Corporate Services | I15: Technology | J15: Yes | K15: Migrate
A16: =_xlfn.XLOOKUP(B16,'All Sites_20260129180943356'!B:B,'All Sites_20260129180943356'!A:A) -> Serco Human Capital Consulting | B16: https://serco.sharepoint.com/sites/SercoHumanCapitalConsulting | D16: Wave 1 | E16: MS Teams | F16: Timothy.Winand@serco-na.com | G16: 0.01 | H16: Corporate Services | I16: Technology | J16: Yes | K16: Migrate
A17: =_xlfn.XLOOKUP(B17,'All Sites_20260129180943356'!B:B,'All Sites_20260129180943356'!A:A) -> AFRL RW RFP | B17: https://serco.sharepoint.com/sites/AFRLRWRFP | D17: Wave 1 | E17: MS Teams | F17: Cheryl.Lawrence@serco-na.com; Matthew.Imperial@serco-na.com | G17: 0.01 | H17: Corporate Services | I17: #N/A | J17: Yes | K17: Migrate | L17: Yes | M17: https://teams.cloud.microsoft/l/team/19%3AE-ra82ye9-n1kAiAnOa5OJN6szX3IK-PUvdYBK3c5iE1%40thread.tacv2/conversations?groupId=25f52227-6b74-4d0a-a600-9be8da78c1dc&tenantId=f93616dd-45a6-40c8-9e29-adab2fb5f25c
A18: =_xlfn.XLOOKUP(B18,'All Sites_20260129180943356'!B:B,'All Sites_20260129180943356'!A:A) -> Airbus Training Helicopter Study | B18: https://serco.sharepoint.com/sites/AirbusTrainingHelicopterStudy | D18: Wave 1 | E18: MS Teams | F18: Brian.Stehle@serco-na.com; Timothy.Hope@serco-na.com | G18: 0.01 | H18: Corporate Services | I18: #N/A | J18: Yes | K18: Migrate
A19: =_xlfn.XLOOKUP(B19,'All Sites_20260129180943356'!B:B,'All Sites_20260129180943356'!A:A) -> BAE Development and Support | B19: https://serco.sharepoint.com/sites/BAEDevelopmentandSupport | D19: Wave 1 | E19: MS Teams | F19: Charles.Dewar@serco-na.com | G19: 0.01 | H19: Corporate Services | I19: Citizens Services | J19: Yes | K19: Migrate
A20: =_xlfn.XLOOKUP(B20,'All Sites_20260129180943356'!B:B,'All Sites_20260129180943356'!A:A) -> Bell Flight Special Mission Aircraft Market Assessment | B20: https://serco.sharepoint.com/sites/BellFlightSpecialMissionAircraftMarketAssessment | D20: Wave 1 | E20: MS Teams | F20: Timothy.Hope@serco-na.com | G20: 0.01 | H20: Corporate Services | I20: Technology | J20: Yes | K20: Migrate
A21: =_xlfn.XLOOKUP(B21,'All Sites_20260129180943356'!B:B,'All Sites_20260129180943356'!A:A) -> Bendix Road Office | B21: https://serco.sharepoint.com/sites/BendixRoadOffice | D21: Wave 1 | E21: MS Teams | F21: Matthew.Sharpe@serco-na.com | G21: 0.01 | H21: Corporate Services | I21: Technology | J21: Yes | K21: Migrate
A22: =_xlfn.XLOOKUP(B22,'All Sites_20260129180943356'!B:B,'All Sites_20260129180943356'!A:A) -> Brazilian Antartic Support Ship - NApAnt | B22: https://serco.sharepoint.com/sites/BrazilianAntarticSupportShip-NApAnt | D22: Wave 1 | E22: MS Teams | F22: Daniel.Mattioda@serco-na.com; John.Boehmer@serco-na.com | G22: 0.01 | H22: Corporate Services | I22: #N/A | J22: Yes | K22: Migrate
A23: =_xlfn.XLOOKUP(B23,'All Sites_20260129180943356'!B:B,'All Sites_20260129180943356'!A:A) -> CLS Planning | B23: https://serco.sharepoint.com/sites/CLSPlanning | D23: Wave 1 | E23: MS Teams | F23: Michael.Lee@serco-na.com; Melinda.Grigorian@serco-na.com; Jonathan.Downing@serco-na.com | G23: 0.01 | H23: Corporate Services | I23: #N/A | J23: Yes | K23: Migrate
A24: =_xlfn.XLOOKUP(B24,'All Sites_20260129180943356'!B:B,'All Sites_20260129180943356'!A:A) -> DON HCS OARS | B24: https://serco.sharepoint.com/sites/DONHCSOARS | D24: Wave 1 | E24: MS Teams | F24: Albert.Moseley@serco-na.com | G24: 0.01 | H24: Corporate Services | I24: Technology | J24: Yes | K24: Migrate
A25: =_xlfn.XLOOKUP(B25,'All Sites_20260129180943356'!B:B,'All Sites_20260129180943356'!A:A) -> F35 AVMS Avionics Branch Organizational Assessment | B25: https://serco.sharepoint.com/sites/F35AVMSAvionicsOrganizationalStudy | D25: Wave 1 | E25: MS Teams | F25: Albert.Moseley@serco-na.com | G25: 0.01 | H25: Corporate Services | I25: Technology | J25: Yes | K25: Migrate
A26: =_xlfn.XLOOKUP(B26,'All Sites_20260129180943356'!B:B,'All Sites_20260129180943356'!A:A) -> FFGX-Automation | B26: https://serco.sharepoint.com/sites/FFGX-Automation | D26: Wave 1 | E26: MS Teams | F26: Miles.Olson@serco-na.com; Kyle.Hagen@serco-na.com; Kelly.Cormican@serco-na.com | G26: 0.01 | H26: Corporate Services | I26: #N/A | J26: Yes | K26: Migrate
A27: =_xlfn.XLOOKUP(B27,'All Sites_20260129180943356'!B:B,'All Sites_20260129180943356'!A:A) -> HWW Shared Content | B27: https://serco.sharepoint.com/sites/HWWSharedContent246 | D27: Wave 1 | E27: MS Teams | F27: Timothy.Hope@serco-na.com | G27: 0.01 | H27: Corporate Services | I27: Technology | J27: Yes | K27: Migrate
A28: =_xlfn.XLOOKUP(B28,'All Sites_20260129180943356'!B:B,'All Sites_20260129180943356'!A:A) -> LRSO | B28: https://serco.sharepoint.com/sites/LRSO738 | D28: Wave 1 | E28: MS Teams | F28: Melinda.Grigorian@serco-na.com; Thomas.Glass@serco-na.com | G28: 0.01 | H28: Corporate Services | I28: #N/A | J28: Yes | K28: Migrate | L28: 32008 LRSO PS-BCA | MG-AF/SF Market Projects #2 | Microsoft Teams
A29: =_xlfn.XLOOKUP(B29,'All Sites_20260129180943356'!B:B,'All Sites_20260129180943356'!A:A) -> LSV SOW - (using Vessel Construction Management) | B29: https://serco.sharepoint.com/sites/LSVSOW-usingVesselConstructionManagement | D29: Wave 1 | E29: MS Teams | F29: Brian.Stehle@serco-na.com | G29: 0.01 | H29: Corporate Services | I29: Technology | J29: Yes | K29: Migrate
A30: =_xlfn.XLOOKUP(B30,'All Sites_20260129180943356'!B:B,'All Sites_20260129180943356'!A:A) -> PNT PO (JSSMO) Production Analyses | B30: https://serco.sharepoint.com/sites/PNTPOJSSMOProductionAnalyses | D30: Wave 1 | E30: MS Teams | F30: Christopher.Pritchet@serco-na.com | G30: 0.01 | H30: Corporate Services | I30: Technology | J30: Yes | K30: Migrate
A31: =_xlfn.XLOOKUP(B31,'All Sites_20260129180943356'!B:B,'All Sites_20260129180943356'!A:A) -> SE&V CBA (Unclass) | B31: https://serco.sharepoint.com/sites/SEVCBAUnclass | D31: Wave 1 | E31: MS Teams | F31: Christopher.Pritchet@serco-na.com | G31: 0.01 | H31: Corporate Services | I31: Technology | J31: Yes | K31: Migrate
A32: =_xlfn.XLOOKUP(B32,'All Sites_20260129180943356'!B:B,'All Sites_20260129180943356'!A:A) -> SOCOM MAECE | B32: https://serco.sharepoint.com/sites/SOCOMMAECE | D32: Wave 1 | E32: MS Teams | F32: Christopher.Pritchet@serco-na.com; William.Burnette@serco-na.com; Vincent.Amato@serco-na.com | G32: 0.01 | H32: Corporate Services | I32: #N/A | J32: Yes | K32: Migrate
A33: =_xlfn.XLOOKUP(B33,'All Sites_20260129180943356'!B:B,'All Sites_20260129180943356'!A:A) -> SOCOM PEO RW | B33: https://serco.sharepoint.com/sites/SOCOMPEORW | D33: Wave 1 | E33: MS Teams | F33: Brian.Stehle@serco-na.com | G33: 0.01 | H33: Corporate Services | I33: Technology | J33: Yes | K33: Migrate
A34: =_xlfn.XLOOKUP(B34,'All Sites_20260129180943356'!B:B,'All Sites_20260129180943356'!A:A) -> Training Initiatives | B34: https://serco.sharepoint.com/sites/TrainingInitiatives | D34: Wave 1 | E34: MS Teams | F34: Timothy.Hope@serco-na.com | G34: 0.01 | H34: Corporate Services | I34: Technology | J34: Yes | K34: Migrate
A35: =_xlfn.XLOOKUP(B35,'All Sites_20260129180943356'!B:B,'All Sites_20260129180943356'!A:A) -> AmeriCorps OARS Team | B35: https://serco.sharepoint.com/sites/americorpsoarsteam | D35: Wave 1 | E35: MS Teams | F35: Kelly.Cormican@serco-na.com | G35: 0.02 | H35: Corporate Services | I35: Technology | J35: Yes | K35: Migrate
A36: =_xlfn.XLOOKUP(B36,'All Sites_20260129180943356'!B:B,'All Sites_20260129180943356'!A:A) -> PRO | B36: https://serco.sharepoint.com/sites/pro | D36: Wave 1 | E36: MS Teams | F36: Timothy.Baker@serco-na.com | G36: 0.02 | H36: Corporate Services | I36: Technology | J36: Yes | K36: Migrate
A37: =_xlfn.XLOOKUP(B37,'All Sites_20260129180943356'!B:B,'All Sites_20260129180943356'!A:A) -> F-35 LCSP Development | B37: https://serco.sharepoint.com/sites/F-35LCSPDevelopment | D37: Wave 1 | E37: MS Teams | F37: Wayne.Borchers@serco-na.com | G37: 0.02 | H37: Corporate Services | I37: Technology | J37: Yes | K37: Migrate
A38: =_xlfn.XLOOKUP(B38,'All Sites_20260129180943356'!B:B,'All Sites_20260129180943356'!A:A) -> LRSO ILA | B38: https://serco.sharepoint.com/sites/LRSO | D38: Wave 1 | E38: MS Teams | F38: Whitney.Sessoms@SERCO-NA.COM | G38: 0.02 | H38: Corporate Services | I38: Technology | J38: Yes | K38: Migrate
A39: =_xlfn.XLOOKUP(B39,'All Sites_20260129180943356'!B:B,'All Sites_20260129180943356'!A:A) -> SAMI C5ISR Enterprise Architecture | B39: https://serco.sharepoint.com/sites/SAMIC5ISREnterpriseArchitecture | D39: Wave 1 | E39: MS Teams | F39: Tracy.West@serco-na.com; Albert.Moseley@serco-na.com; Wayne.Borchers@serco-na.com | G39: 0.02 | H39: Corporate Services | I39: #N/A | J39: Yes | K39: Migrate
A40: =_xlfn.XLOOKUP(B40,'All Sites_20260129180943356'!B:B,'All Sites_20260129180943356'!A:A) -> EFR CDD | B40: https://serco.sharepoint.com/sites/EFRCDD | D40: Wave 1 | E40: MS Teams | F40: Vincent.Amato@serco-na.com | G40: 0.03 | H40: Corporate Services | I40: Technology | J40: Yes | K40: Migrate
A41: =_xlfn.XLOOKUP(B41,'All Sites_20260129180943356'!B:B,'All Sites_20260129180943356'!A:A) -> BAE Systems | B41: https://serco.sharepoint.com/sites/BAESystems | D41: Wave 1 | E41: MS Teams | F41: Charles.Dewar@serco-na.com | G41: 0.03 | H41: Corporate Services | I41: Citizens Services | J41: Yes | K41: Migrate
A42: =_xlfn.XLOOKUP(B42,'All Sites_20260129180943356'!B:B,'All Sites_20260129180943356'!A:A) -> NAVSEA HRO Training | B42: https://serco.sharepoint.com/sites/NAVSEAHROTraining | D42: Wave 1 | E42: MS Teams | F42: Albert.Moseley@serco-na.com | G42: 0.03 | H42: Corporate Services | I42: Technology | J42: Yes | K42: Migrate
A43: =_xlfn.XLOOKUP(B43,'All Sites_20260129180943356'!B:B,'All Sites_20260129180943356'!A:A) -> PMA-205 Opportunity Team | B43: https://serco.sharepoint.com/sites/PMA-205OpportunityTeam | D43: Wave 1 | E43: MS Teams | F43: Wayne.Borchers@serco-na.com; Timothy.Baker@serco-na.com | G43: 0.03 | H43: Corporate Services | I43: #N/A | J43: Yes | K43: Migrate
A44: =_xlfn.XLOOKUP(B44,'All Sites_20260129180943356'!B:B,'All Sites_20260129180943356'!A:A) -> IMAC General | B44: https://serco.sharepoint.com/sites/IMACGeneral | D44: Wave 1 | E44: MS Teams | F44: Michael.Mcneill@serco-na.com; Michael.Lee@serco-na.com | G44: 0.04 | H44: Corporate Services | I44: #N/A | J44: Yes | K44: Migrate
A45: =_xlfn.XLOOKUP(B45,'All Sites_20260129180943356'!B:B,'All Sites_20260129180943356'!A:A) -> Armed Overwatch MBSE | B45: https://serco.sharepoint.com/sites/ArmedOverwatchMBSE | D45: Wave 1 | E45: MS Teams | F45: Julie.Tetreault@serco-na.com | G45: 0.04 | H45: Corporate Services | I45: Technology | J45: Yes | K45: Migrate
A46: CanadaF-35Security | B46: https://serco.sharepoint.com/sites/CanadaF-35Security | D46: Wave 1 | E46: SharePoint | F46: Tracy.West@serco-na.com; Albert.Moseley@serco-na.com | G46: 0.04 | H46: Corporate Services | I46: #N/A | J46: Yes | K46: Migrate
A47: =_xlfn.XLOOKUP(B47,'All Sites_20260129180943356'!B:B,'All Sites_20260129180943356'!A:A) -> Complex Cognitive Skills (ARI-PDRI) | B47: https://serco.sharepoint.com/sites/ComplexCognitiveSkillsARI-PDRI | D47: Wave 1 | E47: MS Teams | F47: Christopher.Pritchet@serco-na.com; Timothy.Hope@serco-na.com | G47: 0.04 | H47: Corporate Services | I47: #N/A | J47: Yes | K47: Migrate
A48: =_xlfn.XLOOKUP(B48,'All Sites_20260129180943356'!B:B,'All Sites_20260129180943356'!A:A) -> High Point Aerotechnologies | B48: https://serco.sharepoint.com/sites/HighPointAerotechnologies | D48: Wave 1 | E48: MS Teams | F48: Timothy.Hope@serco-na.com | G48: 0.04 | H48: Corporate Services | I48: Technology | J48: Yes | K48: Migrate
A49: =_xlfn.XLOOKUP(B49,'All Sites_20260129180943356'!B:B,'All Sites_20260129180943356'!A:A) -> UAS Business Development | B49: https://serco.sharepoint.com/sites/UASBusinessDevelopment | D49: Wave 1 | E49: MS Teams | F49: Timothy.Baker@serco-na.com; Vincent.Amato@serco-na.com | G49: 0.04 | H49: Corporate Services | I49: #N/A | J49: Yes | K49: Migrate
A50: USMCUAS | B50: https://serco.sharepoint.com/sites/USMCUAS | D50: Wave 1 | E50: SharePoint | F50: William.Burnette@serco-na.com; Vincent.Amato@serco-na.com | G50: 0.04 | H50: Corporate Services | I50: #N/A | J50: Yes | K50: Migrate
A51: =_xlfn.XLOOKUP(B51,'All Sites_20260129180943356'!B:B,'All Sites_20260129180943356'!A:A) -> AMCAG_TO1 | B51: https://serco.sharepoint.com/sites/AMCAG_TO1 | D51: Wave 1 | E51: SharePoint | F51: Kyle.Hagen@serco-na.com; Kelly.Cormican@serco-na.com | G51: 0.05 | H51: Corporate Services | I51: #N/A | J51: Yes | K51: Migrate
A52: =_xlfn.XLOOKUP(B52,'All Sites_20260129180943356'!B:B,'All Sites_20260129180943356'!A:A) -> F-47 Projects | B52: https://serco.sharepoint.com/sites/F-47Projects | D52: Wave 1 | E52: MS Teams | F52: Thomas.Ober@serco-na.com; Jonathan.Downing@serco-na.com; Richard.Branson@serco-na.com; Wayne.Borchers@serco-na.com | G52: 0.05 | H52: Corporate Services | I52: #N/A | J52: Yes | K52: Migrate
A53: =_xlfn.XLOOKUP(B53,'All Sites_20260129180943356'!B:B,'All Sites_20260129180943356'!A:A) -> FAA Client Share - Leader and Culture Dev | B53: https://serco.sharepoint.com/sites/FAAClientShare-LeaderandCultureDev | D53: Wave 1 | E53: MS Teams | F53: Isma.Zeghmi@serco-na.com; Brock.Magnino@serco-na.com | G53: 0.05 | H53: Corporate Services | I53: #N/A | J53: Yes | K53: Migrate
A54: =_xlfn.XLOOKUP(B54,'All Sites_20260129180943356'!B:B,'All Sites_20260129180943356'!A:A) -> IMCOM G9 ACS Manpower Analysis | B54: https://serco.sharepoint.com/sites/IMCOMG9ACSManpowerAnalysis | D54: Wave 1 | E54: MS Teams | F54: Brian.Stehle@serco-na.com; Albert.Moseley@serco-na.com; Kelly.Cormican@serco-na.com | G54: 0.06 | H54: Corporate Services | I54: #N/A | J54: Yes | K54: Migrate
A55: =_xlfn.XLOOKUP(B55,'All Sites_20260129180943356'!B:B,'All Sites_20260129180943356'!A:A) -> Internal Projects | B55: https://serco.sharepoint.com/sites/InternalProjects | D55: Wave 1 | E55: MS Teams | F55: Tracy.West@serco-na.com; Timothy.Hope@serco-na.com | G55: 0.06 | H55: Corporate Services | I55: #N/A | J55: Yes | K55: Migrate
A56: =_xlfn.XLOOKUP(B56,'All Sites_20260129180943356'!B:B,'All Sites_20260129180943356'!A:A) -> UAE National Training Center | B56: https://serco.sharepoint.com/sites/UAENationalTrainingCenter | D56: Wave 1 | E56: MS Teams | F56: Timothy.Winand@serco-na.com; Tracy.West@serco-na.com; James.Hammond@serco-na.com; William.Burnette@serco-na.com | G56: 0.06 | H56: Corporate Services | I56: #N/A | J56: Yes | K56: Migrate
A57: =_xlfn.XLOOKUP(B57,'All Sites_20260129180943356'!B:B,'All Sites_20260129180943356'!A:A) -> NAVY Support Contract | B57: https://serco.sharepoint.com/sites/NAVYSupportContract | D57: Wave 1 | E57: MS Teams | F57: William.Burnette@serco-na.com; Brian.Beales@serco-na.com | G57: 0.07 | H57: Corporate Services | I57: #N/A | J57: Yes | K57: Migrate
A58: =_xlfn.XLOOKUP(B58,'All Sites_20260129180943356'!B:B,'All Sites_20260129180943356'!A:A) -> T-7 | B58: https://serco.sharepoint.com/sites/T-7 | D58: Wave 1 | E58: MS Teams | F58: Brian.Godfrey@serco-na.com | G58: 0.09 | H58: Corporate Services | I58: Technology | J58: Yes | K58: Migrate
A59: UKHERA | B59: https://serco.sharepoint.com/sites/UKHERA | D59: Wave 1 | E59: SharePoint | F59: Tracy.West@serco-na.com; Wayne.Borchers@serco-na.com | G59: 0.09 | H59: Corporate Services | I59: #N/A | J59: Yes | K59: Migrate
A60: =_xlfn.XLOOKUP(B60,'All Sites_20260129180943356'!B:B,'All Sites_20260129180943356'!A:A) -> Hampton Office | B60: https://serco.sharepoint.com/sites/HamptonOffice | D60: Wave 1 | E60: MS Teams | F60: Christopher.Pritchet@serco-na.com; William.Burnette@serco-na.com | G60: 0.1 | H60: Corporate Services | I60: #N/A | J60: Yes | K60: Migrate
A61: =_xlfn.XLOOKUP(B61,'All Sites_20260129180943356'!B:B,'All Sites_20260129180943356'!A:A) -> Digital Materiel Management (DMM) | B61: https://serco.sharepoint.com/sites/DigitalMaterielManagementDMM | D61: Wave 1 | E61: MS Teams | F61: John.Staudt@serco-na.com; Matthew.Imperial@serco-na.com | G61: 0.12 | H61: Corporate Services | I61: #N/A | J61: Yes | K61: Migrate
A62: =_xlfn.XLOOKUP(B62,'All Sites_20260129180943356'!B:B,'All Sites_20260129180943356'!A:A) -> Belgium Coastal Security | B62: https://serco.sharepoint.com/sites/BelgiumCoastalSecurity | D62: Wave 1 | E62: MS Teams | F62: Tracy.West@serco-na.com; Albert.Moseley@serco-na.com; James.Hammond@serco-na.com; William.Burnette@serco-na.com; Wayne.Borchers@serco-na.com; Timothy.Baker@serco-na.com | G62: 0.13 | H62: Corporate Services | I62: #N/A | J62: Yes | K62: Migrate
A63: =_xlfn.XLOOKUP(B63,'All Sites_20260129180943356'!B:B,'All Sites_20260129180943356'!A:A) -> F-15QA Ferry Support | B63: https://serco.sharepoint.com/sites/F-15QAFerrySupport | D63: Wave 1 | E63: MS Teams | F63: Daniel.Mattioda@serco-na.com | G63: 0.13 | H63: Corporate Services | I63: Technology | J63: Yes | K63: Migrate | L63: https://serconagcch.sharepoint.us/sites/MG-F-15QAFerry/Shared%20Documents/Forms/AllItems.aspx?FolderCTID=0x012000250ECE9B0BF12742A175C1FCC6D17F55&id=%2Fsites%2FMG%2DF%2D15QAFerry%2FShared%20Documents%2FGeneral | M63: Teams Link: https://gov.teams.microsoft.us/l/team/19%3Agcch%3Af5cc9fd2158c4ec39f1afe804d0789e0%40thread.tacv2/conversations?groupId=af34a362-0f04-4de1-8c4c-2106d1abab80&tenantId=fb1f5cc5-be84-4881-b037-2d641aea97fd
A64: =_xlfn.XLOOKUP(B64,'All Sites_20260129180943356'!B:B,'All Sites_20260129180943356'!A:A) -> PMS515 - FFG-62 Risk Management | B64: https://serco.sharepoint.com/sites/PMS515-FFG-62RiskManagement | D64: Wave 1 | E64: MS Teams | F64: Kyle.Hagen@serco-na.com; Brian.Stehle@serco-na.com; Kyle.Hagen@serco-na.com | G64: 0.16 | H64: Corporate Services | I64: #N/A | J64: Yes | K64: Migrate
A65: =_xlfn.XLOOKUP(B65,'All Sites_20260129180943356'!B:B,'All Sites_20260129180943356'!A:A) -> SOF/PR Data | B65: https://serco.sharepoint.com/sites/SOFPRData | D65: Wave 1 | E65: MS Teams | F65: Gayle.Ingram@serco-na.com | G65: 0.17 | H65: Corporate Services | I65: Technology | J65: Yes | K65: Migrate
A66: =_xlfn.XLOOKUP(B66,'All Sites_20260129180943356'!B:B,'All Sites_20260129180943356'!A:A) -> PRC RFP Team | B66: https://serco.sharepoint.com/sites/PRCRFPTeam | D66: Wave 1 | E66: MS Teams | F66: Albert.Moseley@serco-na.com; Luke.Mcdade@serco-na.com | G66: 0.19 | H66: Corporate Services | I66: #N/A | J66: Yes | K66: Migrate
A67: =_xlfn.XLOOKUP(B67,'All Sites_20260129180943356'!B:B,'All Sites_20260129180943356'!A:A) -> PMA251 - EAF Roadmap and MADMS RM | B67: https://serco.sharepoint.com/sites/PMA251-EAFRoadmapandMADMSRM | D67: Wave 1 | E67: MS Teams | F67: Vincent.Amato@serco-na.com | G67: 0.2 | H67: Corporate Services | I67: Technology | J67: Yes | K67: Migrate
A68: =_xlfn.XLOOKUP(B68,'All Sites_20260129180943356'!B:B,'All Sites_20260129180943356'!A:A) -> Agile Impact Waterfall | B68: https://serco.sharepoint.com/sites/AgileImpactWaterfall | D68: Wave 1 | E68: MS Teams | F68: Wayne.Borchers@serco-na.com | G68: 0.22 | H68: Corporate Services | I68: Technology | J68: Yes | K68: Migrate
A69: =_xlfn.XLOOKUP(B69,'All Sites_20260129180943356'!B:B,'All Sites_20260129180943356'!A:A) -> PNT Cyber & Program Protection | B69: https://serco.sharepoint.com/sites/PNTCyberProgramProtection | D69: Wave 1 | E69: MS Teams | F69: Tracy.West@serco-na.com; Bradley.Schlenker@serco-na.com; George.Sanderlin@serco-na.com; Matthew.Imperial@serco-na.com; Blake.Farley@serco-na.com; Gus.Burnette@serco-na.com | G69: 0.22 | H69: Corporate Services | I69: #N/A | J69: Yes | K69: Migrate | L69: General | MG-PNT Cyber & Program Protection | Microsoft Teams
A70: =_xlfn.XLOOKUP(B70,'All Sites_20260129180943356'!B:B,'All Sites_20260129180943356'!A:A) -> KSA Integrated Protection System | B70: https://serco.sharepoint.com/sites/KSAIntegratedProtectionSystem | D70: Wave 1 | E70: MS Teams | F70: Albert.Moseley@serco-na.com; James.Hammond@serco-na.com; Kelly.Cormican@serco-na.com; Wayne.Borchers@serco-na.com; Timothy.Baker@serco-na.com | G70: 0.23 | H70: Corporate Services | I70: #N/A | J70: Yes | K70: Migrate
A71: =_xlfn.XLOOKUP(B71,'All Sites_20260129180943356'!B:B,'All Sites_20260129180943356'!A:A) -> OARS Organizational Design Product | B71: https://serco.sharepoint.com/sites/OARSOrganizationalDesignProduct | D71: Wave 1 | E71: MS Teams | F71: Albert.Moseley@serco-na.com; Kelly.Cormican@serco-na.com | G71: 0.23 | H71: Corporate Services | I71: #N/A | J71: Yes | K71: Migrate
A72: =_xlfn.XLOOKUP(B72,'All Sites_20260129180943356'!B:B,'All Sites_20260129180943356'!A:A) -> Key Bank TRIRIGA Implementation | B72: https://serco.sharepoint.com/sites/KeyBankTRIRIGAImplementation | D72: Wave 1 | E72: MS Teams | F72: Charles.Dewar@serco-na.com | G72: 0.24 | H72: Corporate Services | I72: Citizens Services | J72: Yes | K72: Migrate
A73: =_xlfn.XLOOKUP(B73,'All Sites_20260129180943356'!B:B,'All Sites_20260129180943356'!A:A) -> PMA268 UMCS Support | B73: https://serco.sharepoint.com/sites/PMA268Support | D73: Wave 1 | E73: MS Teams | F73: Christina.Hall@serco-na.com | G73: 0.24 | H73: Corporate Services | I73: Technology | J73: Yes | K73: Migrate
A74: =_xlfn.XLOOKUP(B74,'All Sites_20260129180943356'!B:B,'All Sites_20260129180943356'!A:A) -> Agile Impact | B74: https://serco.sharepoint.com/sites/consultancy | D74: Wave 1 | E74: MS Teams | F74: Tracy.West@serco-na.com; Albert.Moseley@serco-na.com; Wayne.Borchers@serco-na.com; Timothy.Baker@serco-na.com | G74: 0.25 | H74: Corporate Services | I74: #N/A | J74: Yes | K74: Migrate
A75: =_xlfn.XLOOKUP(B75,'All Sites_20260129180943356'!B:B,'All Sites_20260129180943356'!A:A) -> HMAS Stirling Infrastructure Sustainment Contracting Review | B75: https://serco.sharepoint.com/sites/HMASStirlingInfrastructureSustainmentContractingReview | D75: Wave 1 | E75: MS Teams | F75: Timothy.Winand@serco-na.com; Albert.Moseley@serco-na.com | G75: 0.25 | H75: Corporate Services | I75: #N/A | J75: Yes | K75: Migrate
A76: =_xlfn.XLOOKUP(B76,'All Sites_20260129180943356'!B:B,'All Sites_20260129180943356'!A:A) -> USMC Expeditionary Firefighting and Rescue (EFR) | B76: https://serco.sharepoint.com/sites/ExpeditionaryFirefightandRescueEFR | D76: Wave 1 | E76: MS Teams | F76: Timothy.Winand@serco-na.com; Vincent.Amato@serco-na.com | G76: 0.26 | H76: Corporate Services | I76: #N/A | J76: Yes | K76: Migrate
A77: =_xlfn.XLOOKUP(B77,'All Sites_20260129180943356'!B:B,'All Sites_20260129180943356'!A:A) -> N81 Expeditionary Operations | B77: https://serco.sharepoint.com/sites/N81ExpeditionaryOperations | D77: Wave 1 | E77: MS Teams | F77: Jason.Heuer@serco-na.com | G77: 0.29 | H77: Corporate Services | I77: Technology | J77: Yes | K77: Migrate
A78: =_xlfn.XLOOKUP(B78,'All Sites_20260129180943356'!B:B,'All Sites_20260129180943356'!A:A) -> Iron Sharpens Iron | B78: https://serco.sharepoint.com/sites/ironsharpensiron | D78: Wave 1 | E78: MS Teams | F78: Matthew.Sharpe@serco-na.com | G78: 0.31 | H78: Corporate Services | I78: Technology | J78: No | K78: Migrate | N78: 4/22 Rick marked it do no migrate
A79: =_xlfn.XLOOKUP(B79,'All Sites_20260129180943356'!B:B,'All Sites_20260129180943356'!A:A) -> Qiddiya | B79: https://serco.sharepoint.com/sites/Qiddiya | D79: Wave 1 | E79: MS Teams | F79: Charles.Dewar@serco-na.com | G79: 0.37 | H79: Corporate Services | I79: Citizens Services | J79: Yes | K79: Migrate
A80: =_xlfn.XLOOKUP(B80,'All Sites_20260129180943356'!B:B,'All Sites_20260129180943356'!A:A) -> USMC Expeditionary Air Field (EAF) | B80: https://serco.sharepoint.com/sites/USMCExpeditionaryAirFieldEAF | D80: Wave 1 | E80: MS Teams | F80: William.Burnette@serco-na.com; Vincent.Amato@serco-na.com | G80: 0.39 | H80: Corporate Services | I80: #N/A | J80: Yes | K80: Migrate | L80: General | MG-USMC Expeditionary Air Field (EAF) | Microsoft Teams
A81: =_xlfn.XLOOKUP(B81,'All Sites_20260129180943356'!B:B,'All Sites_20260129180943356'!A:A) -> Bell Opportunities | B81: https://serco.sharepoint.com/sites/BellOpportunities | D81: Wave 1 | E81: MS Teams | F81: Brock.Magnino@serco-na.com | G81: 0.43 | H81: Corporate Services | I81: Technology | J81: Yes | K81: Migrate
A82: =_xlfn.XLOOKUP(B82,'All Sites_20260129180943356'!B:B,'All Sites_20260129180943356'!A:A) -> COPA Team Site | B82: https://serco.sharepoint.com/sites/COPATeamSite | D82: Wave 1 | E82: MS Teams | F82: Charles.Dewar@serco-na.com | G82: 0.43 | H82: Corporate Services | I82: Citizens Services | J82: Yes | K82: Migrate
A83: =_xlfn.XLOOKUP(B83,'All Sites_20260129180943356'!B:B,'All Sites_20260129180943356'!A:A) -> N81F OPN8 30238.TO6 | B83: https://serco.sharepoint.com/sites/N81FOPN830238.TO6 | D83: Wave 1 | E83: MS Teams | F83: Kelly.Cormican@serco-na.com | G83: 0.46 | H83: Corporate Services | I83: Technology | J83: Yes | K83: Migrate
A84: PMA-251EAF20262 | B84: https://serco.sharepoint.com/sites/PMA-251EAF20262 | D84: Wave 1 | E84: SharePoint | F84: William.Burnette@serco-na.com; Vincent.Amato@serco-na.com | G84: 0.47 | H84: Corporate Services | I84: #N/A | J84: Yes | K84: Migrate | L84: General | PMA-251 2026 | Microsoft Teams
A85: =_xlfn.XLOOKUP(B85,'All Sites_20260129180943356'!B:B,'All Sites_20260129180943356'!A:A) -> DAF RCO 31589 | B85: https://serco.sharepoint.com/sites/DAFRCO31589 | D85: Wave 1 | E85: MS Teams | F85: Thomas.Glass@serco-na.com | G85: 0.52 | H85: Corporate Services | I85: Technology | J85: Yes | K85: Migrate | L85: 22898 DAF_RCO | MG-AF/SF Market Projects #1 | Microsoft Teams
A86: =_xlfn.XLOOKUP(B86,'All Sites_20260129180943356'!B:B,'All Sites_20260129180943356'!A:A) -> AHFRM Cost Estimates | B86: https://serco.sharepoint.com/sites/AHFRMCostEstimates | D86: Wave 1 | E86: MS Teams | F86: Vanessa.Bauer@SERCO-NA.COM | G86: 0.55 | H86: Corporate Services | I86: Technology | J86: Yes | K86: Migrate
A87: =_xlfn.XLOOKUP(B87,'All Sites_20260129180943356'!B:B,'All Sites_20260129180943356'!A:A) -> WBB-COP Technology Support Services | B87: https://serco.sharepoint.com/sites/SA-M365Team-WBB-COPTSS | D87: Wave 1 | E87: MS Teams | F87: Wayne.Borchers@serco-na.com | G87: 0.7 | H87: Corporate Services | I87: Technology | J87: Yes | K87: Migrate
A88: =_xlfn.XLOOKUP(B88,'All Sites_20260129180943356'!B:B,'All Sites_20260129180943356'!A:A) -> Serco-NA DT DE MBx Musketeers | B88: https://serco.sharepoint.com/sites/ThreeAmigos830 | D88: Wave 1 | E88: MS Teams | F88: Julie.Tetreault@serco-na.com; Deborah.Linton@serco-na.com; Jeffrey.Laugle@serco-na.com | G88: 0.7 | H88: Corporate Services | I88: #N/A | J88: Yes | K88: Migrate
A89: =_xlfn.XLOOKUP(B89,'All Sites_20260129180943356'!B:B,'All Sites_20260129180943356'!A:A) -> NWF - Niceville FL Office | B89: https://serco.sharepoint.com/sites/WBB-BUNWF-SpringFling | D89: Wave 1 | E89: MS Teams | F89: Melinda.Grigorian@serco-na.com | G89: 0.72 | H89: Corporate Services | I89: Technology | J89: Yes | K89: Migrate
A90: =_xlfn.XLOOKUP(B90,'All Sites_20260129180943356'!B:B,'All Sites_20260129180943356'!A:A) -> Sonobuoy | B90: https://serco.sharepoint.com/sites/Sonobuoy | D90: Wave 1 | E90: MS Teams | F90: Brock.Magnino@serco-na.com | G90: 0.77 | H90: Corporate Services | I90: Technology | J90: Yes | K90: Migrate | L90: General | MG-Sonobuoy | Microsoft Teams
A91: =_xlfn.XLOOKUP(B91,'All Sites_20260129180943356'!B:B,'All Sites_20260129180943356'!A:A) -> SEA05 SRB Process | B91: https://serco.sharepoint.com/sites/SEA05SRBProcess | D91: Wave 1 | E91: MS Teams | F91: Kelly.Cormican@serco-na.com | G91: 0.97 | H91: Corporate Services | I91: Technology | J91: Yes | K91: Migrate
A92: =_xlfn.XLOOKUP(B92,'All Sites_20260129180943356'!B:B,'All Sites_20260129180943356'!A:A) -> MTUAS Support | B92: https://serco.sharepoint.com/sites/MTUASSupport | D92: Wave 1 | E92: MS Teams | F92: Thomas.Ober@serco-na.com | G92: 0.98 | H92: Corporate Services | I92: Technology | J92: Yes | K92: Migrate
A93: =_xlfn.XLOOKUP(B93,'All Sites_20260129180943356'!B:B,'All Sites_20260129180943356'!A:A) -> ARC-260 OSA | B93: https://serco.sharepoint.com/sites/ARC-260OSA | D93: Wave 1 | E93: MS Teams | F93: Brian.Godfrey@serco-na.com | G93: 1.08 | H93: Corporate Services | I93: Technology | J93: Yes | K93: Migrate
A94: =_xlfn.XLOOKUP(B94,'All Sites_20260129180943356'!B:B,'All Sites_20260129180943356'!A:A) -> Solution Briefs | B94: https://serco.sharepoint.com/sites/SolutionBriefs | D94: Wave 1 | E94: MS Teams | F94: Charles.Dewar@serco-na.com | G94: 1.11 | H94: Corporate Services | I94: Citizens Services | J94: Yes | K94: Migrate
A95: =_xlfn.XLOOKUP(B95,'All Sites_20260129180943356'!B:B,'All Sites_20260129180943356'!A:A) -> Potential Projects | B95: https://serco.sharepoint.com/sites/PotentialProjects | D95: Wave 1 | E95: MS Teams | F95: Charles.Dewar@serco-na.com | G95: 1.12 | H95: Corporate Services | I95: Citizens Services | J95: Yes | K95: Migrate
A96: =_xlfn.XLOOKUP(B96,'All Sites_20260129180943356'!B:B,'All Sites_20260129180943356'!A:A) -> Business Case Analysis BD Campaign | B96: https://serco.sharepoint.com/sites/BusinessCaseAnalysisBDCampaign | D96: Wave 1 | E96: MS Teams | F96: Thomas.Glass@serco-na.com; Wayne.Borchers@serco-na.com | G96: 1.2 | H96: Corporate Services | I96: #N/A | J96: Yes | K96: Migrate | L96: https://gov.teams.microsoft.us/l/channel/19%3Agcch%3A68db35d951f44f91bf0bf6fe52ac3db0%40thread.tacv2/Product%20Support%20and%20Sustainment?groupId=ba78d508-2db2-4a0f-8235-d0360f0faa59&tenantId=fb1f5cc5-be84-4881-b037-2d641aea97fd
A97: =_xlfn.XLOOKUP(B97,'All Sites_20260129180943356'!B:B,'All Sites_20260129180943356'!A:A) -> ETSS Org Study | B97: https://serco.sharepoint.com/sites/ETSSOrgStudy | D97: Wave 1 | E97: MS Teams | F97: Albert.Moseley@serco-na.com; Luke.Mcdade@serco-na.com; Cassidy.Kuzemka@serco-na.com; Kelly.Cormican@serco-na.com; Albert.Moseley@serco-na.com; Luke.Mcdade@serco-na.com; Cassidy.Kuzemka@serco-na.com; Kelly.Cormican@serco-na.com | G97: 1.21 | H97: Corporate Services | I97: #N/A | J97: Yes | K97: Migrate
A98: =_xlfn.XLOOKUP(B98,'All Sites_20260129180943356'!B:B,'All Sites_20260129180943356'!A:A) -> Cost Reference Info | B98: https://serco.sharepoint.com/sites/CostReferenceInfo | D98: Wave 1 | E98: MS Teams | F98: Katrina.Mims@serco-na.com; Gayle.Ingram@serco-na.com; Vanessa.Bauer@SERCO-NA.COM | G98: 1.23 | H98: Corporate Services | I98: #N/A | J98: Yes | K98: Migrate
A99: =_xlfn.XLOOKUP(B99,'All Sites_20260129180943356'!B:B,'All Sites_20260129180943356'!A:A) -> NAVMAC PF&D Study 30238.TO8 | B99: https://serco.sharepoint.com/sites/NAVMACPFDStudy30238.TO8 | D99: Wave 1 | E99: MS Teams | F99: Brock.Magnino@serco-na.com | G99: 1.25 | H99: Corporate Services | I99: Technology | J99: Yes | K99: Migrate
A100: =_xlfn.XLOOKUP(B100,'All Sites_20260129180943356'!B:B,'All Sites_20260129180943356'!A:A) -> DTIC IAC MAC IDIQ - Pool 2 | B100: https://serco.sharepoint.com/sites/SA-M365Group-WBB-PEOAVNDTICIAC | D100: Wave 1 | E100: MS Teams | F100: Brian.Stehle@serco-na.com | G100: 1.56 | H100: Corporate Services | I100: Technology | J100: Yes | K100: Migrate
...

Sheet Wave1B
A1: SITE Name | B1: SITE URL (MAIN) | C1: SIZE IN GB | D1: SITE OWNERS - EMAIL | E1: BU | F1: Portfolio | G1: Wave | H1: Action | I1: IN PILOT | J1: Site Exist in GCCH? | K1: Teams
A2: AAAA | B2: https://serco.sharepoint.com/sites/aaaa | D2: Michael.J.Harris@serco-na.com | E2: Corporate Services | F2: Technology | G2: Wave 1 | H2: Migrate | I2: =_xlfn.XLOOKUP(B2,'Pilot-Wave1'!B:B,'Pilot-Wave1'!D:D) -> #N/A
A3: AAAAPlanning | B3: https://serco.sharepoint.com/sites/aaaaplanning | D3: Michael.J.Harris@serco-na.com | E3: Corporate Services | F3: Technology | G3: Wave 1 | H3: Migrate | I3: =_xlfn.XLOOKUP(B3,'Pilot-Wave1'!B:B,'Pilot-Wave1'!D:D) -> #N/A
A4: Acquisition Management (AQM) | B4: https://serco.sharepoint.com/sites/AFSFMarketTeam | D4: Raymond.Wier@serco-na.com | E4: Corporate Services | F4: Technology | G4: Wave 1 | H4: Migrate | I4: =_xlfn.XLOOKUP(B4,'Pilot-Wave1'!B:B,'Pilot-Wave1'!D:D) -> #N/A | J4: https://gov.teams.microsoft.us/l/team/19%3Agcch%3Af9f705e178ae4d588e8f42e0406241f8%40thread.tacv2/conversations?groupId=d95aa34f-d2f3-4d7e-a0ab-ed6d7d8c8d22&tenantId=fb1f5cc5-be84-4881-b037-2d641aea97fd
A5: WRO Team | B5: https://serco.sharepoint.com/sites/AFWROSpecialProjects | D5: Raymond.Wier@serco-na.com | E5: Corporate Services | F5: Technology | G5: Wave 1 | H5: Migrate | I5: =_xlfn.XLOOKUP(B5,'Pilot-Wave1'!B:B,'Pilot-Wave1'!D:D) -> #N/A
A6: AHFRM | B6: https://serco.sharepoint.com/sites/ahfrm | D6: Raymond.Wier@serco-na.com | E6: Corporate Services | F6: Technology | G6: Wave 1 | H6: Migrate | I6: =_xlfn.XLOOKUP(B6,'Pilot-Wave1'!B:B,'Pilot-Wave1'!D:D) -> #N/A
A7: AHFRM Rapid Fielding Planning and Support-AHFRM DTIC Management Channel | B7: https://serco.sharepoint.com/sites/AHFRMDTICKICKOFF-AHFRMDTICManagementChannel | D7: Steven.Yelverton@serco-na.com | E7: Corporate Services | F7: Technology | G7: Wave 1 | H7: Migrate | I7: =_xlfn.XLOOKUP(B7,'Pilot-Wave1'!B:B,'Pilot-Wave1'!D:D) -> #N/A
A8: AHFRM Manufacturing Emails | B8: https://serco.sharepoint.com/sites/AHFRMManufacturingEmails | D8: Brian.Townsend@serco-na.com | E8: Corporate Services | F8: Technology | G8: Wave 1 | H8: Migrate | I8: =_xlfn.XLOOKUP(B8,'Pilot-Wave1'!B:B,'Pilot-Wave1'!D:D) -> #N/A
A9: AmeriCorps Workforce Analysis | B9: https://serco.sharepoint.com/sites/AmeriCorpsWorkforceAnalysis | D9: Allison.Gervasio@serco-na.com | E9: Corporate Services | F9: Technology | G9: Wave 1 | H9: Migrate | I9: =_xlfn.XLOOKUP(B9,'Pilot-Wave1'!B:B,'Pilot-Wave1'!D:D) -> #N/A
A10: Angelo B-52 Files | B10: https://serco.sharepoint.com/sites/AngeloFiles | D10: Brian.Townsend@serco-na.com | E10: Corporate Services | F10: Technology | G10: Wave 1 | H10: Migrate | I10: =_xlfn.XLOOKUP(B10,'Pilot-Wave1'!B:B,'Pilot-Wave1'!D:D) -> #N/A
A11: Armed Overwatch | B11: https://serco.sharepoint.com/sites/ArmedOverwatch | D11: Gary.Leavy@serco-na.com | E11: Corporate Services | F11: Technology | G11: Wave 1 | H11: Migrate | I11: =_xlfn.XLOOKUP(B11,'Pilot-Wave1'!B:B,'Pilot-Wave1'!D:D) -> #N/A
A12: Army CONOPS Team | B12: https://serco.sharepoint.com/sites/ArmyCONOPSTeam | D12: Jay.Voorhees@serco-na.com | E12: Corporate Services | F12: Technology | G12: Wave 1 | H12: Migrate | I12: =_xlfn.XLOOKUP(B12,'Pilot-Wave1'!B:B,'Pilot-Wave1'!D:D) -> #N/A
A13: Army Team | B13: https://serco.sharepoint.com/sites/armyteam | D13: Michael.J.Harris@serco-na.com | E13: Corporate Services | F13: Technology | G13: Wave 1 | H13: Migrate | I13: =_xlfn.XLOOKUP(B13,'Pilot-Wave1'!B:B,'Pilot-Wave1'!D:D) -> #N/A
A14: AUSA Group | B14: https://serco.sharepoint.com/sites/AUSAGroup | D14: Michael.J.Harris@serco-na.com | E14: Corporate Services | F14: Technology | G14: Wave 1 | H14: Migrate | I14: =_xlfn.XLOOKUP(B14,'Pilot-Wave1'!B:B,'Pilot-Wave1'!D:D) -> #N/A
A15: B-52 DTIC IAC Team | B15: https://serco.sharepoint.com/sites/B-52DTICIACTeam | D15: Brian.Townsend@serco-na.com | E15: Corporate Services | F15: Technology | G15: Wave 1 | H15: Migrate | I15: =_xlfn.XLOOKUP(B15,'Pilot-Wave1'!B:B,'Pilot-Wave1'!D:D) -> #N/A | J15: https://gov.teams.microsoft.us/l/channel/19%3Agcch%3Ad84581d74cd642a2a5d7289286422301%40thread.tacv2/31688%20B-52%20Analysis%20and%20Modernization?groupId=d63110a1-af9a-4b18-a770-bf272eaafe3b&tenantId=fb1f5cc5-be84-4881-b037-2d641aea97fd&ngc=true
A16: B-52 Legacy TS PWS | B16: https://serco.sharepoint.com/sites/B-52LegacyTSPWS | D16: Brian.Townsend@serco-na.com | E16: Corporate Services | F16: Technology | G16: Wave 1 | H16: Migrate | I16: =_xlfn.XLOOKUP(B16,'Pilot-Wave1'!B:B,'Pilot-Wave1'!D:D) -> #N/A
A17: B-52 Nuc Cert Collaboration | B17: https://serco.sharepoint.com/sites/B-52NucCertCollaboration | D17: Brian.Townsend@serco-na.com | E17: Corporate Services | F17: Technology | G17: Wave 1 | H17: Migrate | I17: =_xlfn.XLOOKUP(B17,'Pilot-Wave1'!B:B,'Pilot-Wave1'!D:D) -> #N/A | J17: https://gov.teams.microsoft.us/l/team/19%3Agcch%3Ac923882e1fae430db5a2a5b92ae4857e%40thread.tacv2/conversations?groupId=6558baf4-9ed8-4d91-95bf-6e8e7a9df34b&tenantId=fb1f5cc5-be84-4881-b037-2d641aea97fd
A18: B-52 TS | B18: https://serco.sharepoint.com/sites/B-52TS | D18: Gary.Leavy@serco-na.com | E18: Corporate Services | F18: Technology | G18: Wave 1 | H18: Migrate | I18: =_xlfn.XLOOKUP(B18,'Pilot-Wave1'!B:B,'Pilot-Wave1'!D:D) -> #N/A
A19: CBP RFI | B19: https://serco.sharepoint.com/sites/CBPRFI | D19: Maggie.Irons@serco-na.com | E19: Corporate Services | F19: Technology | G19: Wave 1 | H19: Migrate | I19: =_xlfn.XLOOKUP(B19,'Pilot-Wave1'!B:B,'Pilot-Wave1'!D:D) -> #N/A
A20: DAF RCO 24-C-0007 | B20: https://serco.sharepoint.com/sites/DAFRCO24-C-0007 | D20: Alexander.Brown@serco-na.com | E20: Corporate Services | F20: Technology | G20: Wave 1 | H20: Migrate | I20: =_xlfn.XLOOKUP(B20,'Pilot-Wave1'!B:B,'Pilot-Wave1'!D:D) -> Wave 1
A21: DAF RCO Bridge | B21: https://serco.sharepoint.com/sites/DAFRCOBridge | D21: Alexander.Brown@serco-na.com | E21: Corporate Services | F21: Technology | G21: Wave 1 | H21: Migrate | I21: =_xlfn.XLOOKUP(B21,'Pilot-Wave1'!B:B,'Pilot-Wave1'!D:D) -> #N/A
A22: Defense Exportability Features - Bell | B22: https://serco.sharepoint.com/sites/DefenseExportabilityFeatures-Bell | D22: Joana.Rivera@serco-na.com | E22: Corporate Services | F22: Technology | G22: Wave 1 | H22: Migrate | I22: =_xlfn.XLOOKUP(B22,'Pilot-Wave1'!B:B,'Pilot-Wave1'!D:D) -> #N/A
A23: DHS FPS Acquisition #32094 | B23: https://serco.sharepoint.com/sites/DHSFPSAcquisition32094 | D23: Leonard.Geshan@serco-na.com | E23: Corporate Services | F23: Technology | G23: Wave 1 | H23: Migrate | I23: =_xlfn.XLOOKUP(B23,'Pilot-Wave1'!B:B,'Pilot-Wave1'!D:D) -> #N/A
A24: Digital Enterprise BD Campaign-DE Consortium 2025 | B24: https://serco.sharepoint.com/sites/DigitalEnterprise-EWAACDEConsortium | D24: Robert.Hoffman@serco-na.com | E24: Corporate Services | F24: Technology | G24: Wave 1 | H24: Migrate | I24: =_xlfn.XLOOKUP(B24,'Pilot-Wave1'!B:B,'Pilot-Wave1'!D:D) -> #N/A
A25: DTIC IAC MAC - Pool One | B25: https://serco.sharepoint.com/sites/DTICIACMAC-PoolOne | D25: Raymond.Wier@serco-na.com | E25: Corporate Services | F25: Technology | G25: Wave 1 | H25: Migrate | I25: =_xlfn.XLOOKUP(B25,'Pilot-Wave1'!B:B,'Pilot-Wave1'!D:D) -> #N/A
A26: DTIC TO # 1 Group | B26: https://serco.sharepoint.com/sites/DTICTO1Group | D26: Robert.Hoffman@serco-na.com | E26: Corporate Services | F26: Technology | G26: Wave 1 | H26: Migrate | I26: =_xlfn.XLOOKUP(B26,'Pilot-Wave1'!B:B,'Pilot-Wave1'!D:D) -> #N/A
A27: Eglin Wide Agile Acquisition Contract (EWAAC) | B27: https://serco.sharepoint.com/sites/EglinWideAgileAcquisitionContractEWAAC | D27: Robert.Hoffman@serco-na.com | E27: Corporate Services | F27: Technology | G27: Wave 1 | H27: Migrate | I27: =_xlfn.XLOOKUP(B27,'Pilot-Wave1'!B:B,'Pilot-Wave1'!D:D) -> #N/A
A28: F-35 FM KBS | B28: https://serco.sharepoint.com/sites/F-35FMKBS | D28: Alex.Stathopoulos@serco-na.com | E28: Corporate Services | F28: Technology | G28: Wave 1 | H28: Migrate | I28: =_xlfn.XLOOKUP(B28,'Pilot-Wave1'!B:B,'Pilot-Wave1'!D:D) -> #N/A
A29: F-35 Logistics KBS | B29: https://serco.sharepoint.com/sites/F-35LogisticsKBS | D29: Alex.Stathopoulos@serco-na.com | E29: Corporate Services | F29: Technology | G29: Wave 1 | H29: Migrate | I29: =_xlfn.XLOOKUP(B29,'Pilot-Wave1'!B:B,'Pilot-Wave1'!D:D) -> #N/A
... A35: JSSMO (PNT PO) - Wright Patterson Client Site Team | B35: https://serco.sharepoint.com/sites/JSSMOPNTPO-WrightPattersonClientSiteTeam | D35: Jeffrey.Braun@serco-na.com | E35: Corporate Services | F35: Technology | G35: Wave 1 | H35: Migrate | I35: =_xlfn.XLOOKUP(B35,'Pilot-Wave1'!B:B,'Pilot-Wave1'!D:D) -> #N/A
A36: KC-135 AW | B36: https://serco.sharepoint.com/sites/KC-135AW | D36: Brian.Townsend@serco-na.com | E36: Corporate Services | F36: Technology | G36: Wave 1 | H36: Migrate | I36: =_xlfn.XLOOKUP(B36,'Pilot-Wave1'!B:B,'Pilot-Wave1'!D:D) -> #N/A | J36: https://gov.teams.microsoft.us/l/team/19%3Agcch%3A5b0526e975a748debd9231e2ddab8b70%40thread.tacv2/conversations?groupId=59010a5f-cd41-429a-9cf5-006a8ffdf72a&tenantId=fb1f5cc5-be84-4881-b037-2d641aea97fd
A37: KC-135 Engineering Support | B37: https://serco.sharepoint.com/sites/KC-135EngineeringSupport | D37: Brian.Townsend@serco-na.com | E37: Corporate Services | F37: Technology | G37: Wave 1 | H37: Migrate | I37: =_xlfn.XLOOKUP(B37,'Pilot-Wave1'!B:B,'Pilot-Wave1'!D:D) -> #N/A | J37: https://gov.teams.microsoft.us/l/team/19%3Agcch%3A5b0526e975a748debd9231e2ddab8b70%40thread.tacv2/conversations?groupId=59010a5f-cd41-429a-9cf5-006a8ffdf72a&tenantId=fb1f5cc5-be84-4881-b037-2d641aea97fd
A38: MDA Threat Systems Engineering -Threat Products and Services | B38: https://serco.sharepoint.com/sites/MDAThreatSystemsEngineering-ThreatProductsandServices | D38: Robert.Hoffman@serco-na.com | E38: Corporate Services | F38: Technology | G38: Wave 1 | H38: Migrate | I38: =_xlfn.XLOOKUP(B38,'Pilot-Wave1'!B:B,'Pilot-Wave1'!D:D) -> #N/A
A39: N81F Combat System Sustainment | B39: https://serco.sharepoint.com/sites/N81FCombatSystemSustainment | D39: Allison.Gervasio@serco-na.com | E39: Corporate Services | F39: Technology | G39: Wave 1 | H39: Migrate | I39: =_xlfn.XLOOKUP(B39,'Pilot-Wave1'!B:B,'Pilot-Wave1'!D:D) -> #N/A
A40: Navigating Business Webinar Series | B40: https://serco.sharepoint.com/sites/NavigatingBusinessWebinarSeries | D40: Allison.Gervasio@serco-na.com | E40: Corporate Services | F40: Technology | G40: Wave 1 | H40: Migrate | I40: =_xlfn.XLOOKUP(B40,'Pilot-Wave1'!B:B,'Pilot-Wave1'!D:D) -> #N/A
A41: NIH NIAID | B41: https://serco.sharepoint.com/sites/NIHNIAID | D41: Allison.Gervasio@serco-na.com | E41: Corporate Services | F41: Technology | G41: Wave 1 | H41: Migrate | I41: =_xlfn.XLOOKUP(B41,'Pilot-Wave1'!B:B,'Pilot-Wave1'!D:D) -> #N/A
A42: PNT - Independent Review Team | B42: https://serco.sharepoint.com/sites/PNT-IndependentReviewTeam | D42: Till.Schanz@serco-na.com | E42: Corporate Services | F42: Technology | G42: Wave 1 | H42: Migrate | I42: =_xlfn.XLOOKUP(B42,'Pilot-Wave1'!B:B,'Pilot-Wave1'!D:D) -> #N/A
A43: AF PNT (JSSMO) Leads | B43: https://serco.sharepoint.com/sites/PNTJSSMOLeads | D43: Till.Schanz@serco-na.com | E43: Corporate Services | F43: Technology | G43: Wave 1 | H43: Migrate | I43: =_xlfn.XLOOKUP(B43,'Pilot-Wave1'!B:B,'Pilot-Wave1'!D:D) -> #N/A
A44: PNT PO Strategic Planning | B44: https://serco.sharepoint.com/sites/PNTPOStrategicPlanning | D44: Till.Schanz@serco-na.com | E44: Corporate Services | F44: Technology | G44: Wave 1 | H44: Migrate | I44: =_xlfn.XLOOKUP(B44,'Pilot-Wave1'!B:B,'Pilot-Wave1'!D:D) -> #N/A
A45: PNT Proposal 2025 | B45: https://serco.sharepoint.com/sites/PNTProposal2025 | D45: Till.Schanz@serco-na.com | E45: Corporate Services | F45: Technology | G45: Wave 1 | H45: Migrate | I45: =_xlfn.XLOOKUP(B45,'Pilot-Wave1'!B:B,'Pilot-Wave1'!D:D) -> #N/A
A46: R-EGI Phase III (Serco) | B46: https://serco.sharepoint.com/sites/R-EGIPhaseIIISerco | D46: Jason.Rusco@serco-na.com | E46: Corporate Services | F46: Technology | G46: Wave 1 | H46: Migrate | I46: =_xlfn.XLOOKUP(B46,'Pilot-Wave1'!B:B,'Pilot-Wave1'!D:D) -> #N/A
A47: R-EGI Phase III (Serco)-R-EGI Leadership Briefings (controlled access) | B47: https://serco.sharepoint.com/sites/R-EGIPhaseIIISerco-R-EGILeadershipBriefingscontrolledaccess | D47: Jason.Rusco@serco-na.com | E47: Corporate Services | F47: Technology | G47: Wave 1 | H47: Migrate | I47: =_xlfn.XLOOKUP(B47,'Pilot-Wave1'!B:B,'Pilot-Wave1'!D:D) -> #N/A
A48: WBB-COP Organizational Development | B48: https://serco.sharepoint.com/sites/SA-M365Team-WBB-COPOD | D48: Allison.Gervasio@serco-na.com | E48: Corporate Services | F48: Technology | G48: Wave 1 | H48: Migrate | I48: =_xlfn.XLOOKUP(B48,'Pilot-Wave1'!B:B,'Pilot-Wave1'!D:D) -> #N/A
A49: Beacon | B49: https://serco.sharepoint.com/sites/SA-WBB-Beacon | D49: Allison.Gervasio@serco-na.com | E49: Corporate Services | F49: Technology | G49: Wave 1 | H49: Migrate | I49: =_xlfn.XLOOKUP(B49,'Pilot-Wave1'!B:B,'Pilot-Wave1'!D:D) -> #N/A
A50: SECWAR Acq Reform Team | B50: https://serco.sharepoint.com/sites/SECWARAcqReformTeam | D50: Timothy.Ablay@serco-na.com | E50: Corporate Services | F50: Technology | G50: Wave 1 | H50: Migrate | I50: =_xlfn.XLOOKUP(B50,'Pilot-Wave1'!B:B,'Pilot-Wave1'!D:D) -> #N/A
A51: SERCO Airworthiness Team | B51: https://serco.sharepoint.com/sites/SERCOAirworthinessTeam | D51: Mark.Wilson@serco-na.com | E51: Corporate Services | F51: Technology | G51: Wave 1 | H51: Migrate | I51: =_xlfn.XLOOKUP(B51,'Pilot-Wave1'!B:B,'Pilot-Wave1'!D:D) -> #N/A | J51: https://gov.teams.microsoft.us/l/team/19%3Agcch%3A5b0526e975a748debd9231e2ddab8b70%40thread.tacv2/conversations?groupId=59010a5f-cd41-429a-9cf5-006a8ffdf72a&tenantId=fb1f5cc5-be84-4881-b037-2d641aea97fd
A52: SercoVets Leadership Team | B52: https://serco.sharepoint.com/sites/SercoVetsLeadershipTeam | D52: Vasilios.Pappas@serco-na.com | E52: Corporate Services | F52: Technology | G52: Wave 1 | H52: Migrate | I52: =_xlfn.XLOOKUP(B52,'Pilot-Wave1'!B:B,'Pilot-Wave1'!D:D) -> #N/A
A53: Tech Trakr | B53: https://serco.sharepoint.com/sites/TechTrakr | D53: Brian.Townsend@serco-na.com | E53: Corporate Services | F53: Technology | G53: Wave 1 | H53: Migrate | I53: =_xlfn.XLOOKUP(B53,'Pilot-Wave1'!B:B,'Pilot-Wave1'!D:D) -> #N/A
A54: TRR Test | B54: https://serco.sharepoint.com/sites/TRRTest | D54: Taryn.Trimble@serco-na.com | E54: Corporate Services | F54: Technology | G54: Wave 1 | H54: Migrate | I54: =_xlfn.XLOOKUP(B54,'Pilot-Wave1'!B:B,'Pilot-Wave1'!D:D) -> #N/A
A55: USASAC Team | B55: https://serco.sharepoint.com/sites/USASACTeam | D55: Michael.J.Harris@serco-na.com | E55: Corporate Services | F55: Technology | G55: Wave 1 | H55: Migrate | I55: =_xlfn.XLOOKUP(B55,'Pilot-Wave1'!B:B,'Pilot-Wave1'!D:D) -> #N/A
A56: USSF Training Red Team | B56: https://serco.sharepoint.com/sites/USSFTrainingRedTeam | D56: Raymond.Wier@serco-na.com | E56: Corporate Services | F56: Technology | G56: Wave 1 | H56: Migrate | I56: =_xlfn.XLOOKUP(B56,'Pilot-Wave1'!B:B,'Pilot-Wave1'!D:D) -> #N/A
A57: WBB_INT_DAI | B57: https://serco.sharepoint.com/sites/WBB_INT_DAI | D57: Brian.Marshall@serco-na.com | E57: Corporate Services | F57: #N/A | G57: Wave 1 | H57: Migrate | I57: =_xlfn.XLOOKUP(B57,'Pilot-Wave1'!B:B,'Pilot-Wave1'!D:D) -> #N/A

Sheet Wave1C
A1: MIGRATE | B1: SiteUrl | C1: WORKSTREAM | D1: Source | E1: UserDisplay | F1: UserEmail | G1: IDENTITY TYPE | H1: BU | I1: Program | J1: WAVE-1 | K1: OWNERS-EMAIL | L1: OWNERS-DISPLAYNAME | M1: Notes
A2: W1 | B2: https://serco.sharepoint.com/sites/GEODSSSPACEFENCE-QCLS | C2: TEAMS | D2: Owner | E2: Akins, Jessica, K (Serco NA US) | F2: Jessica.Akins@serco-na.com | G2: User | H2: SI2 | I2: C4ISR SS | J2: WAVE-1 | K2: Jessica.Akins@serco-na.com | L2: Akins, Jessica, K (Serco NA US)
A3: W1 | B3: https://serco.sharepoint.com/sites/IMCOMDeploymentOnBoarding | C3: TEAMS | D3: Owner | E3: Akins, Jessica, K (Serco NA US) | F3: Jessica.Akins@serco-na.com | G3: User | H3: SI2 | I3: C4ISR SS | J3: WAVE-1 | K3: Jessica.Akins@serco-na.com | L3: Akins, Jessica, K (Serco NA US)
A4: W1 | B4: https://serco.sharepoint.com/sites/PensacolaPlanner | C4: SPO - M365 GROUP | D4: Owner | E4: Allen, David, E (Serco NA US) | F4: David.Allen@SERCO-NA.COM | G4: User | H4: SI2 | I4: C4ISR SS | J4: WAVE-1 | K4: David.Allen@SERCO-NA.COM | L4: Allen, David, E (Serco NA US)
A5: W1 | B5: https://serco.sharepoint.com/sites/ResourcePlanning617 | C5: SPO - M365 GROUP | D5: Owner | E5: Allen, David, E (Serco NA US) | F5: David.Allen@SERCO-NA.COM | G5: User | H5: SI2 | I5: C4ISR SS | J5: WAVE-1 | K5: David.Allen@SERCO-NA.COM | L5: Allen, David, E (Serco NA US)
A6: W1 | B6: https://serco.sharepoint.com/sites/Serco_Charleston_Shore | C6: SPO - M365 GROUP | D6: Owner | E6: Allen, David, E (Serco NA US) | F6: David.Allen@SERCO-NA.COM | G6: User | H6: SI2 | I6: C4ISR SS | J6: WAVE-1 | K6: David.Allen@SERCO-NA.COM | L6: Allen, David, E (Serco NA US)
A7: W1 | B7: https://serco.sharepoint.com/sites/Serco_Pensacola | C7: SPO - M365 GROUP | D7: Owner | E7: Allen, David, E (Serco NA US) | F7: David.Allen@SERCO-NA.COM | G7: User | H7: SI2 | I7: C4ISR SS | J7: WAVE-1 | K7: David.Allen@SERCO-NA.COM | L7: Allen, David, E (Serco NA US)
A8: W1 | B8: https://serco.sharepoint.com/sites/TravelHelp_PNS_CHS | C8: SPO - M365 GROUP | D8: Owner | E8: Allen, David, E (Serco NA US) | F8: David.Allen@SERCO-NA.COM | G8: User | H8: SI2 | I8: C4ISR SS | J8: WAVE-1 | K8: David.Allen@SERCO-NA.COM | L8: Allen, David, E (Serco NA US)
A9: W1 | B9: https://serco.sharepoint.com/sites/C4ISRSS | C9: TEAMS | D9: Owner | E9: Barnes, Gary (Serco NA US) | F9: Gary.Barnes@serco-na.com | G9: User | H9: SI2 | I9: SI2 | J9: WAVE-1 | K9: Gary.Barnes@serco-na.com | L9: Barnes, Gary (Serco NA US)
A10: W1 | B10: https://serco.sharepoint.com/sites/C4ISRSSTeamChannel-StaffCall | C10: SPO | D10: SiteCollectionAdmin | E10: Barnes, Gary (Serco NA US) | F10: Gary.Barnes@serco-na.com | G10: USER | H10: SI2 | I10: SI2 | J10: WAVE-1 | K10: Gary.Barnes@serco-na.com;Gary.Barnes@serco-na.com | L10: Barnes, Gary (Serco NA US)
A11: W1 | B11: https://serco.sharepoint.com/sites/FDICIFWMS | C11: TEAMS | D11: Owner | E11: Case, Dave, A (Serco NA US) | F11: David.Case@serco-na.com | G11: User | H11: SI2 | I11: Citizens Services | J11: WAVE-1 | K11: David.Case@serco-na.com | L11: Case, Dave, A (Serco NA US) | M11: Migrated in Wave 1B
A12: W1 | B12: https://serco.sharepoint.com/sites/FDICIFWMS-ProjectTeam | C12: SPO | D12: SiteCollectionAdmin | E12: Case, Dave, A (Serco NA US) | F12: David.Case@serco-na.com | G12: USER | H12: SI2 | I12: Citizens Services | J12: WAVE-1 | K12: David.Case@serco-na.com;David.Case@serco-na.com | L12: Case, Dave, A (Serco NA US)
A13: W1 | B13: https://serco.sharepoint.com/sites/ESSVIISampleTaskDwgReview | C13: TEAMS | D13: Owner | E13: Ceva, Ed, J (Serco NA US) | F13: Edward.Ceva@serco-na.com | G13: User | H13: SI2 | I13: C4ISR SS | J13: WAVE-1 | K13: Edward.Ceva@serco-na.com | L13: Ceva, Ed, J (Serco NA US)
A14: W1 | B14: https://serco.sharepoint.com/sites/ElPasoC5ISR | C14: TEAMS | D14: Owner | E14: Corey, Bob, W (Serco NA US) | F14: Robert.Corey@serco-na.com | G14: User | H14: SI2 | I14: C4ISR SS | J14: WAVE-1 | K14: Robert.Corey@serco-na.com | L14: Corey, Bob, W (Serco NA US)
A15: W1 | B15: https://serco.sharepoint.com/sites/IBD-SS | C15: SPO - M365 GROUP | D15: Owner | E15: Corey, Bob, W (Serco NA US) | F15: Robert.Corey@serco-na.com | G15: User | H15: SI2 | I15: C4ISR SS | J15: WAVE-1 | K15: Robert.Corey@serco-na.com | L15: Corey, Bob, W (Serco NA US)
A16: W1 | B16: https://serco.sharepoint.com/sites/ISEManagement-Ludlow | C16: TEAMS | D16: Owner | E16: Girard, Michael (Serco NA US) | F16: Michael.Girard@serco-na.com | G16: User | H16: SI2 | I16: SI2 | J16: WAVE-1 | K16: Michael.Girard@serco-na.com | L16: Girard, Michael (Serco NA US)
A17: W1 | B17: https://serco.sharepoint.com/sites/LCOMProgramManagementReview | C17: TEAMS | D17: Owner | E17: Girard, Michael (Serco NA US) | F17: Michael.Girard@serco-na.com | G17: User | H17: SI2 | I17: SI2 | J17: WAVE-1 | K17: Michael.Girard@serco-na.com | L17: Girard, Michael (Serco NA US)
A18: W1 | B18: https://serco.sharepoint.com/sites/SI2ProgramManagementReview | C18: TEAMS | D18: Owner | E18: Girard, Michael (Serco NA US) | F18: Michael.Girard@serco-na.com | G18: User | H18: SI2 | I18: SI2 | J18: WAVE-1 | K18: Michael.Girard@serco-na.com | L18: Girard, Michael (Serco NA US)
A19: W1 | B19: https://serco.sharepoint.com/sites/FETS | C19: SPO - M365 GROUP | D19: Owner | E19: Griffin, Chris (Serco NA US) | F19: Chris.Griffin@serco-na.com | G19: User | H19: SI2 | I19: SIE | J19: WAVE-1 | K19: Chris.Griffin@serco-na.com | L19: Griffin, Chris (Serco NA US)
A20: W1 | B20: https://serco.sharepoint.com/sites/FETSTEST | C20: SPO - M365 GROUP | D20: Owner | E20: Griffin, Chris (Serco NA US) | F20: Chris.Griffin@serco-na.com | G20: User | H20: SI2 | I20: SIE | J20: WAVE-1 | K20: Chris.Griffin@serco-na.com | L20: Griffin, Chris (Serco NA US)
A21: W1 | B21: https://serco.sharepoint.com/sites/KidsBenefits401K | C21: SPO - M365 GROUP | D21: Owner | E21: Guzman, Leonel (Serco NA US) | F21: Leonel.Guzman@serco-na.com | G21: User | H21: SI2 | I21: SSM-SCH | J21: WAVE-1 | K21: Leonel.Guzman@serco-na.com | L21: Guzman, Leonel (Serco NA US)
A22: W1 | B22: https://serco.sharepoint.com/sites/CYSCCTVPilotEngineeringIMCOM | C22: TEAMS | D22: Owner | E22: Harlow, Josh, G (Serco NA US) | F22: Joshua.Harlow@serco-na.com | G22: User | H22: SI2 | I22: C4ISR SS | J22: WAVE-1 | K22: Joshua.Harlow@serco-na.com | L22: Harlow, Josh, G (Serco NA US)
A23: W1 | B23: https://serco.sharepoint.com/sites/cys-engineers | C23: SPO - M365 GROUP | D23: Owner | E23: Harlow, Josh, G (Serco NA US) | F23: Joshua.Harlow@serco-na.com | G23: User | H23: SI2 | I23: C4ISR SS | J23: WAVE-1 | K23: Joshua.Harlow@serco-na.com | L23: Harlow, Josh, G (Serco NA US)
... A29: W1 | B29: https://serco.sharepoint.com/sites/ATFPGSCPSAC-EA | C29: SPO - M365 GROUP | D29: Owner | E29: Mcconnell, Joseph, J (Serco NA US) | F29: Joseph.Mcconnell@serco-na.com | G29: User | H29: SI2 | I29: C4ISR SS | J29: WAVE-1 | K29: Joseph.Mcconnell@serco-na.com | L29: Mcconnell, Joseph, J (Serco NA US)
A30: W1 | B30: https://serco.sharepoint.com/sites/CP22744USACEESSVII | C30: TEAMS | D30: Owner | E30: Mcconnell, Joseph, J (Serco NA US) | F30: Joseph.Mcconnell@serco-na.com | G30: User | H30: SI2 | I30: C4ISR SS | J30: WAVE-1 | K30: Joseph.Mcconnell@serco-na.com | L30: Mcconnell, Joseph, J (Serco NA US) | M30: ShareGate to migrate
A31: W1 | B31: https://serco.sharepoint.com/sites/EM2P | C31: TEAMS | D31: Owner | E31: Mcconnell, Joseph, J (Serco NA US) | F31: Joseph.Mcconnell@serco-na.com | G31: User | H31: SI2 | I31: C4ISR SS | J31: WAVE-1 | K31: Joseph.Mcconnell@serco-na.com | L31: Mcconnell, Joseph, J (Serco NA US)
A32: W1 | B32: https://serco.sharepoint.com/sites/JacksonvilleAE | C32: TEAMS | D32: Owner | E32: Mcconnell, Joseph, J (Serco NA US) | F32: Joseph.Mcconnell@serco-na.com | G32: User | H32: SI2 | I32: C4ISR SS | J32: WAVE-1 | K32: Joseph.Mcconnell@serco-na.com | L32: Mcconnell, Joseph, J (Serco NA US)
A33: W1 | B33: https://serco.sharepoint.com/sites/NIWCLant | C33: TEAMS | D33: Owner | E33: Mcconnell, Joseph, J (Serco NA US) | F33: Joseph.Mcconnell@serco-na.com | G33: User | H33: SI2 | I33: C4ISR SS | J33: WAVE-1 | K33: Joseph.Mcconnell@serco-na.com | L33: Mcconnell, Joseph, J (Serco NA US)
A34: W1 | B34: https://serco.sharepoint.com/sites/RegionN6RecompeteProposal | C34: TEAMS | D34: Owner | E34: Mcconnell, Joseph, J (Serco NA US) | F34: Joseph.Mcconnell@serco-na.com | G34: User | H34: SI2 | I34: C4ISR SS | J34: WAVE-1 | K34: Joseph.Mcconnell@serco-na.com | L34: Mcconnell, Joseph, J (Serco NA US)
A35: W1 | B35: https://serco.sharepoint.com/sites/911Engineering | C35: TEAMS | D35: Owner | E35: Mitchell, John, W (Serco NA US) | F35: John.Mitchell@serco-na.com | G35: User | H35: SI2 | I35: C4ISR SS | J35: WAVE-1 | K35: smankel@SERCO-NA.COM;John.Mitchell@serco-na.com | L35: Mitchell, John, W (Serco NA US)
A36: W1 | B36: https://serco.sharepoint.com/sites/C4ISRSSTeamChannel | C36: TEAMS | D36: Owner | E36: Mitchell, John, W (Serco NA US) | F36: John.Mitchell@serco-na.com | G36: User | H36: SI2 | I36: C4ISR SS | J36: WAVE-1 | K36: Gary.Barnes@serco-na.com;Joseph.Mcconnell@serco-na.com;John.Mitchell@serco-na.com | L36: Gary.Barnes@serco-na.com;Mitchell, John, W (Serco NA US)
A37: W1 | B37: https://serco.sharepoint.com/sites/Gate6Review | C37: TEAMS | D37: Owner | E37: Mitchell, John, W (Serco NA US) | F37: John.Mitchell@serco-na.com | G37: User | H37: SI2 | I37: C4ISR SS | J37: WAVE-1 | K37: John.Mitchell@serco-na.com | L37: Mitchell, John, W (Serco NA US)
A38: W1 | B38: https://serco.sharepoint.com/sites/ProposalCenter228-BigBlueIIIReport | C38: SPO | D38: SiteCollectionAdmin | E38: Mitchell, John, W (Serco NA US) | F38: John.Mitchell@serco-na.com | G38: USER | H38: SI2 | I38: C4ISR SS | J38: WAVE-1 | K38: John.Mitchell@serco-na.com;John.Mitchell@serco-na.com | L38: Mitchell, John, W (Serco NA US)
A39: W1 | B39: https://serco.sharepoint.com/sites/ProposalCenter228-CNSLID | C39: SPO | D39: SiteCollectionAdmin | E39: Mitchell, John, W (Serco NA US) | F39: John.Mitchell@serco-na.com | G39: USER | H39: SI2 | I39: C4ISR SS | J39: WAVE-1 | K39: John.Mitchell@serco-na.com;John.Mitchell@serco-na.com | L39: Mitchell, John, W (Serco NA US)
A40: W1 | B40: https://serco.sharepoint.com/sites/ProposalCenter228-TEAM | C40: SPO | D40: SiteCollectionAdmin | E40: Mitchell, John, W (Serco NA US) | F40: John.Mitchell@serco-na.com | G40: USER | H40: SI2 | I40: C4ISR SS | J40: WAVE-1 | K40: John.Mitchell@serco-na.com;John.Mitchell@serco-na.com | L40: Mitchell, John, W (Serco NA US)
A41: W1 | B41: https://serco.sharepoint.com/sites/PS2-EA | C41: TEAMS | D41: Owner | E41: Mitchell, John, W (Serco NA US) | F41: John.Mitchell@serco-na.com | G41: User | H41: SI2 | I41: C4ISR SS | J41: WAVE-1 | K41: smankel@SERCO-NA.COM;John.Mitchell@serco-na.com | L41: Mitchell, John, W (Serco NA US)
A42: W1 | B42: https://serco.sharepoint.com/sites/SBMProgramManagementReview | C42: TEAMS | D42: Owner | E42: Mitchell, John, W (Serco NA US) | F42: John.Mitchell@serco-na.com | G42: User | H42: SI2 | I42: C4ISR SS | J42: WAVE-1 | K42: Gary.Barnes@serco-na.com;John.Mitchell@serco-na.com | L42: Mitchell, John, W (Serco NA US)
... A56: W1 | B56: https://serco.sharepoint.com/sites/department | C56: SPO - M365 GROUP | D56: Owner | E56: Trail, Becky, L (Serco NA US) | F56: Becky.Trail@serco-na.com | G56: User | H56: SI2 | I56: C4ISR SS | J56: WAVE-1 | K56: Becky.Trail@serco-na.com | L56: Trail, Becky, L (Serco NA US)

Sheet Wave 2A
A1: Site Title | B1: Site URL | C1: RelationType | D1: DisplayName | E1: UserPrincipalName | F1: Active User | G1: Quest | H1: W2BUser | I1: Migrated | J1: Notes
A2: 2023 STEP Summer Interns | B2: https://serco.sharepoint.com/sites/2023STEPSummerInterns | C2: Owner | D2: Saben, Clark (Serco NA US) | E2: clark.saben@serco-na.com | F2: Member | G2: Mapped | H2: Yes | I2: Yes
A3: 2023 STEP Summer Interns | B3: https://serco.sharepoint.com/sites/2023STEPSummerInterns | C3: Owner | D3: Zhang, Max (Serco NA US) | E3: max.zhang@serco-na.com | F3: Member | G3: #N/A | H3: #N/A | I3: No
A4: AI de Camp | B4: https://serco.sharepoint.com/sites/AIdeCamp | C4: Owner | D4: Murphy, Travis, W (Serco NA US) | E4: travis.murphy@serco-na.com | F4: Member | G4: Mapped | H4: Yes | I4: Yes
A5: AI Proctor - AI Team | B5: https://serco.sharepoint.com/sites/AIProctor-AITeam | C5: Owner | D5: Bowden, James, A (Serco NA US) | E5: james.bowden@serco-na.com | F5: Member | G5: Mapped | H5: #N/A | I5: No
A6: AI Proctor - AI Team | B6: https://serco.sharepoint.com/sites/AIProctor-AITeam | C6: Owner | D6: Colony, Mike, J (Serco NA US) | E6: michael.colony@serco-na.com | F6: Member | G6: Mapped | H6: Yes | I6: Yes
A7: AI Proctor - AI Team | B7: https://serco.sharepoint.com/sites/AIProctor-AITeam | C7: Owner | D7: Davenport, Jack, H (Serco NA US) | E7: jack.davenport@serco-na.com | F7: Member | G7: Mapped | H7: Yes | I7: Yes
A8: AI Proctor - AI Team | B8: https://serco.sharepoint.com/sites/AIProctor-AITeam | C8: Owner | D8: Murphy, Travis, W (Serco NA US) | E8: travis.murphy@serco-na.com | F8: Member | G8: Mapped | H8: Yes | I8: Yes
A9: AI Proctor - AI Team | B9: https://serco.sharepoint.com/sites/AIProctor-AITeam | C9: Owner | D9: Rua, Rob, A (Serco NA US) | E9: robert.rua@serco-na.com | F9: Member | G9: Mapped | H9: Yes | I9: Yes
A10: AirUBW_sercoTeam | B10: https://serco.sharepoint.com/sites/AirUBW_sercoTeam | C10: Owner | D10: Smith, Dan, C (Serco NA US) | E10: daniel.c.smith@serco-na.com | F10: Member | G10: Mapped | H10: Yes | I10: Yes
A11: Air U Initiatives | B11: https://serco.sharepoint.com/sites/AirUInitiatives | C11: Owner | D11: Martin, Jonathan, L (Serco NA US) | E11: jonathan.l.martin@serco-na.com | F11: Member | G11: Mapped | H11: #N/A | I11: No
A12: Air U Initiatives | B12: https://serco.sharepoint.com/sites/AirUInitiatives | C12: Owner | D12: Owens, Gregory (Serco NA US) | E12: gregory.owens@serco-na.com | F12: Member | G12: Migrated | H12: #N/A | I12: Yes
A13: Air U Initiatives | B13: https://serco.sharepoint.com/sites/AirUInitiatives | C13: Owner | D13: Smith, Dan, C (Serco NA US) | E13: daniel.c.smith@serco-na.com | F13: Member | G13: Mapped | H13: Yes | I13: Yes
A14: Alfonso PM Task Board | B14: https://serco.sharepoint.com/sites/AlfonsoPMTaskBoard | C14: Owner | D14: Gomez, Alfonso, N (Serco NA US) | E14: alfonso.gomez@serco-na.com | F14: Member | G14: Mapped | H14: Yes | I14: Yes
A15: Chatbot | B15: https://serco.sharepoint.com/sites/AlfonsosTasks | C15: Owner | D15: Gomez, Alfonso, N (Serco NA US) | E15: alfonso.gomez@serco-na.com | F15: Member | G15: Mapped | H15: Yes | I15: Yes
A16: ATG All Hands | B16: https://serco.sharepoint.com/sites/ATGAllHands | C16: Owner | D16: Davenport, Jack, H (Serco NA US) | E16: jack.davenport@serco-na.com | F16: Member | G16: Mapped | H16: Yes | I16: Yes
A17: ATG All Hands | B17: https://serco.sharepoint.com/sites/ATGAllHands | C17: Owner | D17: Durham, Debra, S (Serco NA US) | E17: debra.s.durham@serco-na.com | F17: Member | G17: Migrated | H17: #N/A | I17: Yes
A18: ATG - Chatbot - Project Space | B18: https://serco.sharepoint.com/sites/ATG-Chatbot-ProjectSpace | C18: Owner | D18: Gomez, Alfonso, N (Serco NA US) | E18: alfonso.gomez@serco-na.com | F18: Member | G18: Mapped | H18: Yes | I18: Yes
A19: ATG - Chatbot Team | B19: https://serco.sharepoint.com/sites/ATG-ChatbotTeam | C19: Owner | D19: Gomez, Alfonso, N (Serco NA US) | E19: alfonso.gomez@serco-na.com | F19: Member | G19: Mapped | H19: Yes | I19: Yes
A20: ATG Knowledge Share | B20: https://serco.sharepoint.com/sites/ATGKnowledgeShare | C20: Owner | D20: Colony, Mike, J (Serco NA US) | E20: michael.colony@serco-na.com | F20: Member | G20: Mapped | H20: Yes | I20: Yes
A21: ATG Knowledge Share | B21: https://serco.sharepoint.com/sites/ATGKnowledgeShare | C21: Owner | D21: Murphy, Travis, W (Serco NA US) | E21: travis.murphy@serco-na.com | F21: Member | G21: Mapped | H21: Yes | I21: Yes
A22: ATG Knowledge Share | B22: https://serco.sharepoint.com/sites/ATGKnowledgeShare | C22: Owner | D22: Rua, Rob, A (Serco NA US) | E22: robert.rua@serco-na.com | F22: Member | G22: Mapped | H22: Yes | I22: Yes
A23: Growth Automation Project | B23: https://serco.sharepoint.com/sites/BDAutomationProject | C23: Owner | D23: Gomez, Alfonso, N (Serco NA US) | E23: alfonso.gomez@serco-na.com | F23: Member | J23: Added 5/26
A24: BD Automation Project | B24: https://serco.sharepoint.com/sites/BI-AID | C24: Owner | D24: Gomez, Alfonso, N (Serco NA US) | E24: alfonso.gomez@serco-na.com | F24: Member | G24: Mapped | H24: Yes | I24: Yes
A25: Chatbot | B25: https://serco.sharepoint.com/sites/Chatbot | C25: Owner | D25: Davenport, Jack, H (Serco NA US) | E25: jack.davenport@serco-na.com | F25: Member | G25: Mapped | H25: Yes | I25: Yes
A26: Chatbot | B26: https://serco.sharepoint.com/sites/Chatbot | C26: Owner | D26: Fetz, Ryan (Serco NA US) | E26: ryan.fetz@serco-na.com | F26: Member | G26: Mapped | H26: Yes | I26: Yes
A27: Covan - Serco | B27: https://serco.sharepoint.com/sites/Covan-Serco | C27: Owner | D27: Chang, Yow-Ren (Serco NA) | E27: yowren.chang@serco-na.com | F27: Member | G27: Mapped | H27: Yes | I27: Yes
A28: Data Platform | B28: https://serco.sharepoint.com/sites/DataPlatformPOC | C28: Owner | D28: Bowden, James, A (Serco NA US) | E28: james.bowden@serco-na.com | F28: Member | G28: Mapped | H28: #N/A | I28: No
A29: Data Platform | B29: https://serco.sharepoint.com/sites/DataPlatformPOC | C29: Owner | D29: Olson, Miles, C (Serco NA US) | E29: miles.olson@serco-na.com | F29: Member | G29: Migrated | H29: #N/A | I29: Yes
A30: Data Platform | B30: https://serco.sharepoint.com/sites/DataPlatformPOC | C30: Owner | D30: Roffman, Samuel (Serco NA US) | E30: samuel.roffman@serco-na.com | F30: Member | G30: Mapped | H30: Yes | I30: Yes
A31: Data Platform | B31: https://serco.sharepoint.com/sites/DataPlatformPOC | C31: Owner | D31: Rojas, Alex, K (Serco NA) | E31: alex.rojas@serco-na.com | F31: Member | G31: Migrated | H31: #N/A | I31: Yes
A32: Data Platform | B32: https://serco.sharepoint.com/sites/DataPlatformPOC | C32: Owner | D32: Smith, Dan, C (Serco NA US) | E32: daniel.c.smith@serco-na.com | F32: Member | G32: Mapped | H32: Yes | I32: Yes
A33: EKB PVT and Test Automation | B33: https://serco.sharepoint.com/sites/EKBPVTandTestAutomation | C33: Owner | D33: Gomez, Alfonso, N (Serco NA US) | E33: alfonso.gomez@serco-na.com | F33: Member | J33: Added 5/26
A34: GAiT - Ai-Powered Business Development | B34: https://serco.sharepoint.com/sites/gait-ai-poweredbusinessdevelopment | C34: Owner | D34: Gomez, Alfonso, N (Serco NA US) | E34: alfonso.gomez@serco-na.com | F34: Member | J34: Added 5/26
A35: Serco PPM Home | B35: https://serco.sharepoint.com/sites/GLB-GB-PDCLIPWA-PJ | C35: AssociatedOwnersGroup | D35: o-bsabir | E35: o-bsabir@serco-na.com | F35: Member | G35: Mapped | H35: #N/A | I35: No | J35: Removed 5/26. Owners not in Wave2A users dataset.
A36: Serco PPM Home | B36: https://serco.sharepoint.com/sites/GLB-GB-PDCLIPWA-PJ | C36: AssociatedOwnersGroup | D36: Sabir, Bureera (Serco NA US) | E36: bureera.sabir@serco-na.com | F36: Member | G36: Mapped | H36: #N/A | I36: No | J36: Removed 5/26. Owners not in Wave2A users dataset.
A37: Growth Automation Tool User Support | B37: https://serco.sharepoint.com/sites/GrowthAutomationToolUserSupport | C37: Owner | D37: Davenport, Jack, H (Serco NA US) | E37: jack.davenport@serco-na.com | F37: Member | G37: Mapped | H37: Yes | I37: Yes | J37: Added 5/26
A38: Growth Automation Tool User Support | B38: https://serco.sharepoint.com/sites/GrowthAutomationToolUserSupport | C38: Owner | D38: Gomez, Alfonso, N (Serco NA US) | E38: alfonso.gomez@serco-na.com | F38: Member | J38: Added 5/26
A39: GSA AI Acquisition System RFI Opportunity | B39: https://serco.sharepoint.com/sites/GSAAIAcquisitionSystemRFIOpportunity | C39: Owner | D39: Cormack, Kyle (Serco NA US) | E39: kyle.cormack@serco-na.com | J39: Added 5/26
A40: GSA AI Acquisition System RFI Opportunity | B40: https://serco.sharepoint.com/sites/GSAAIAcquisitionSystemRFIOpportunity | C40: Owner | D40: Davenport, Jack, H (Serco NA US) | E40: jack.davenport@serco-na.com | F40: Member | G40: Mapped | H40: Yes | I40: Yes | J40: Added 5/26
A41: GSA Modification Discussion | B41: https://serco.sharepoint.com/sites/GSAModificationDiscussion | C41: Owner | D41: Clayton, Robert (Serco NA) | E41: robert.clayton@serco-na.com | J41: Added 5/26
A42: GSA Modification Discussion | B42: https://serco.sharepoint.com/sites/GSAModificationDiscussion | C42: Owner | D42: Cormack, Kyle (Serco NA US) | E42: kyle.cormack@serco-na.com | J42: Added 5/26
A43: GSA Modification Discussion | B43: https://serco.sharepoint.com/sites/GSAModificationDiscussion | C43: Owner | D43: Davenport, Jack, H (Serco NA US) | E43: jack.davenport@serco-na.com | F43: Member | G43: Mapped | H43: Yes | I43: Yes | J43: Added 5/26
A44: GSA Modification Discussion | B44: https://serco.sharepoint.com/sites/GSAModificationDiscussion | C44: Owner | D44: Ho, Dana (Serco NA US) | E44: dana.ho@serco-na.com | J44: Added 5/26
A45: GSA Modification Discussion | B45: https://serco.sharepoint.com/sites/GSAModificationDiscussion | C45: Owner | D45: Lewis, Melinda, R (Serco NA US) | E45: melinda.lewis@serco-na.com | J45: Added 5/26
A46: GSA Modification Discussion | B46: https://serco.sharepoint.com/sites/GSAModificationDiscussion | C46: Owner | D46: Stewart, Zachary (Serco NA US) | E46: zachary.stewart@serco-na.com | J46: Added 5/26
A47: GSA Modification Discussion | B47: https://serco.sharepoint.com/sites/GSAModificationDiscussion | C47: Owner | D47: Zamler, Lauren (Serco NA US) | E47: lauren.zamler@serco-na.com | J47: Added 5/26
A48: IT Service and Service Delivery | B48: https://serco.sharepoint.com/sites/ITServiceandServiceDelivery | C48: Owner | D48: Bourbeau, Sharie (Serco NA) | E48: sharie.bourbeau@serco-na.com | J48: Added 5/26
A49: IT Service and Service Delivery | B49: https://serco.sharepoint.com/sites/ITServiceandServiceDelivery | C49: Owner | D49: Davenport, Jack, H (Serco NA US) | E49: jack.davenport@serco-na.com | F49: Member | G49: Mapped | H49: Yes | I49: Yes | J49: Added 5/26
A50: IT Service and Service Delivery | B50: https://serco.sharepoint.com/sites/ITServiceandServiceDelivery | C50: Owner | D50: Kalb, Christine, M (Serco NA US) | E50: christine.kalb@serco-na.com | J50: Added 5/26
A51: Jared Internship 2024 | B51: https://serco.sharepoint.com/sites/JaredInternship2024 | C51: Owner | D51: Pipho, Seth, J (Serco NA) | E51: seth.pipho@serco-na.com | J51: Added 5/26
A52: Jeff Scotti | B52: https://serco.sharepoint.com/sites/JeffScotti | C52: Owner | D52: Scotti, Jeff (Serco NA US) | E52: jeff.scotti@serco-na.com | J52: Added 5/26
A53: Machine Learning Group | B53: https://serco.sharepoint.com/sites/MachineLearningGroup | C53: Owner | D53: Colony, Mike, J (Serco NA US) | E53: michael.colony@serco-na.com | F53: Member | G53: Mapped | H53: Yes | I53: Yes | J53: Added 5/26
A54: Machine Learning Group | B54: https://serco.sharepoint.com/sites/MachineLearningGroup | C54: Owner | D54: Davenport, Jack, H (Serco NA US) | E54: jack.davenport@serco-na.com | F54: Member | G54: Mapped | H54: Yes | I54: Yes | J54: Added 5/26
A55: Machine Learning Group | B55: https://serco.sharepoint.com/sites/MachineLearningGroup | C55: Owner | D55: Stevens, Mark, N (Serco NA US) | E55: mark.n.stevens@serco-na.com | J55: Added 5/26
A56: Machine Learning Group | B56: https://serco.sharepoint.com/sites/MachineLearningGroup | C56: Owner | D56: Wonders, Jonathan (Serco NA US) | E56: jonathan.wonders@serco-na.com | J56: Added 5/26
A57: Machine Learning Infrastructure | B57: https://serco.sharepoint.com/sites/MachineLearningInfrastructure | C57: Owner | D57: Davenport, Jack, H (Serco NA US) | E57: jack.davenport@serco-na.com | F57: Member | G57: Mapped | H57: Yes | I57: Yes | J57: Added 5/26
A58: ML Chatbot | B58: https://serco.sharepoint.com/sites/MLChatbot | C58: Owner | D58: Gomez, Alfonso, N (Serco NA US) | E58: alfonso.gomez@serco-na.com | F58: Member | J58: Added 5/26
A59: MLG | B59: https://serco.sharepoint.com/sites/MLG | C59: Owner | D59: Colony, Mike, J (Serco NA US) | E59: michael.colony@serco-na.com | F59: Member | G59: Mapped | H59: Yes | I59: Yes | J59: Added 5/26
A60: MLG BD | B60: https://serco.sharepoint.com/sites/MLGBD | C60: Owner | D60: Colony, Mike, J (Serco NA US) | E60: michael.colony@serco-na.com | F60: Member | G60: Mapped | H60: Yes | I60: Yes | J60: Added 5/26
A61: MLG BD | B61: https://serco.sharepoint.com/sites/MLGBD | C61: Owner | D61: Murphy, Travis, W (Serco NA US) | E61: travis.murphy@serco-na.com | J61: Added 5/26
A62: MLG BizDev | B62: https://serco.sharepoint.com/sites/MLGBizDev | C62: Owner | D62: Colony, Mike, J (Serco NA US) | E62: michael.colony@serco-na.com | F62: Member | G62: Mapped | H62: Yes | I62: Yes | J62: Added 5/26
A63: ML Group | B63: https://serco.sharepoint.com/sites/MLGroup | C63: Owner | D63: Colony, Mike, J (Serco NA US) | E63: michael.colony@serco-na.com | F63: Member | G63: Mapped | H63: Yes | I63: Yes | J63: Added 5/26
A64: PM Task Board | B64: https://serco.sharepoint.com/sites/PMTaskBoard | C64: Owner | D64: Gomez, Alfonso, N (Serco NA US) | E64: alfonso.gomez@serco-na.com | F64: Member | J64: Added 5/26
A65: Project Restart - Analytics & Insights | B65: https://serco.sharepoint.com/sites/ProjectRestart-AnalyticsInsights | C65: Owner | D65: Roffman, Samuel (Serco NA US) | E65: samuel.roffman@serco-na.com | J65: Added 5/26
A66: Project Restart - Analytics & Insights | B66: https://serco.sharepoint.com/sites/ProjectRestart-AnalyticsInsights | C66: Owner | D66: Smith, Dan, C (Serco NA US) | E66: daniel.c.smith@serco-na.com | J66: Added 5/26
A67: Project Restart - Analytics & Insights | B67: https://serco.sharepoint.com/sites/ProjectRestart-AnalyticsInsights | C67: Owner | D67: Stovall, Harry (Serco NA) | E67: harry.stovall@serco-na.com | J67: Added 5/26
A68: Project Restart - Analytics & Insights | B68: https://serco.sharepoint.com/sites/ProjectRestart-AnalyticsInsights | C68: Owner | D68: Tran, Zoe, M (Serco NA US) | E68: zoe.tran@serco-na.com | J68: Added 5/26
A69: Serco Covan Collaboration | B69: https://serco.sharepoint.com/sites/sercocovancollaboration | C69: Owner | D69: Chang, Yow-Ren (Serco NA) | E69: yowren.chang@serco-na.com | J69: Added 5/26
A70: Serco Data Science COI | B70: https://serco.sharepoint.com/sites/sercodatascience--test | C70: Owner | D70: Roffman, Samuel (Serco NA US) | E70: samuel.roffman@serco-na.com | J70: Added 5/26
A71: Serco Data Science COI | B71: https://serco.sharepoint.com/sites/sercodatascience--test | C71: Owner | D71: Tao, Derek, K (Serco NA US) | E71: derek.tao@serco-na.com | J71: Added 5/26
A72: Serco Global Data Science Collaboration | B72: https://serco.sharepoint.com/sites/SercoGlobalDataScienceCollaboration | C72: Owner | D72: Smith, Dan, C (Serco NA US) | E72: daniel.c.smith@serco-na.com | J72: Added 5/26
A73: Serco OTA Team Site | B73: https://serco.sharepoint.com/sites/SercoOTATeamSite | C73: Owner | D73: Brown, William, A (Serco NA US) | E73: william.brown@serco-na.com | J73: Added 5/26
A74: Serco OTA Team Site | B74: https://serco.sharepoint.com/sites/SercoOTATeamSite | C74: Owner | D74: Colony, Mike, J (Serco NA US) | E74: michael.colony@serco-na.com | F74: Member | G74: Mapped | H74: Yes | I74: Yes | J74: Added 5/26
A75: Serco OTA Team Site | B75: https://serco.sharepoint.com/sites/SercoOTATeamSite | C75: Owner | D75: Cormack, Kyle (Serco NA US) | E75: kyle.cormack@serco-na.com | J75: Added 5/26
A76: Serco OTA Team Site | B76: https://serco.sharepoint.com/sites/SercoOTATeamSite | C76: Owner | D76: Davenport, Jack, H (Serco NA US) | E76: jack.davenport@serco-na.com | F76: Member | G76: Mapped | H76: Yes | I76: Yes | J76: Added 5/26
A77: Serco OTA Team Site | B77: https://serco.sharepoint.com/sites/SercoOTATeamSite | C77: Owner | D77: Durham, Debra, S (Serco NA US) | E77: debra.s.durham@serco-na.com | J77: Added 5/26
A78: Serco OTA Team Site | B78: https://serco.sharepoint.com/sites/SercoOTATeamSite | C78: Owner | D78: Gulac, Roger, C (Serco NA US) | E78: roger.gulac@serco-na.com | J78: Added 5/26
A79: Serco Response to NATO | B79: https://serco.sharepoint.com/sites/TalendandSercoResponsetoNATO | C79: Owner | D79: Davenport, Jack, H (Serco NA US) | E79: jack.davenport@serco-na.com | F79: Member | G79: Mapped | H79: Yes | I79: Yes | J79: Added 5/26
A80: Serco Response to NATO | B80: https://serco.sharepoint.com/sites/TalendandSercoResponsetoNATO | C80: Owner | D80: Rojas, Alex, K (Serco NA) | E80: alex.rojas@serco-na.com | J80: Added 5/26
A81: Serco Response to NATO | B81: https://serco.sharepoint.com/sites/TalendandSercoResponsetoNATO | C81: Owner | D81: Stovall, Harry (Serco NA) | E81: harry.stovall@serco-na.com | J81: Added 5/26
A82: Tech Debt - Asset Inventory | B82: https://serco.sharepoint.com/sites/TechDebt-AssetInventory | C82: Owner | D82: Defrancisco, Nicolas, W (Serco NA US) | E82: nicolas.defrancisco@serco-na.com | J82: Added 5/26
A83: Tech Debt - Asset Inventory | B83: https://serco.sharepoint.com/sites/TechDebt-AssetInventory | C83: Owner | D83: Gaouette, Homer (Serco NA US) | E83: homer.gaouette@serco-na.com | J83: Added 5/26
A84: Tech Debt - Asset Inventory | B84: https://serco.sharepoint.com/sites/TechDebt-AssetInventory | C84: Owner | D84: Keyser, Matt, A (Serco NA) | E84: matthew.keyser@serco-na.com | J84: Added 5/26
A85: Tech Debt - Asset Inventory | B85: https://serco.sharepoint.com/sites/TechDebt-AssetInventory | C85: Owner | D85: Laxsav, Arnav (Serco NA US) | E85: arnav.laxsav@serco-na.com | J85: Added 5/26
A86: Tech Debt - Asset Inventory | B86: https://serco.sharepoint.com/sites/TechDebt-AssetInventory | C86: Owner | D86: Smith, Dan, C (Serco NA US) | E86: daniel.c.smith@serco-na.com | J86: Added 5/26
A87: Tech Debt - Asset Inventory | B87: https://serco.sharepoint.com/sites/TechDebt-AssetInventory | C87: Owner | D87: Sobti, Rahul (Serco NA US) | E87: rahul.sobti@serco-na.com | J87: Added 5/26
A88: Tech Debt - Asset Inventory | B88: https://serco.sharepoint.com/sites/TechDebt-AssetInventory | C88: Owner | D88: Thome, Geoffrey, D (Serco NA US) | E88: geoffrey.thome@serco-na.com | J88: Added 5/26
A89: Tech Debt - Asset Inventory | B89: https://serco.sharepoint.com/sites/TechDebt-AssetInventory | C89: Owner | D89: Williams-Donald, Claudine, C (Serco NA US) | E89: claudine.williamsdo@serco-na.com | J89: Added 5/26
A90: Tech Debt - Asset Inventory | B90: https://serco.sharepoint.com/sites/TechDebt-AssetInventory | C90: Owner | D90: Wilson, Anthony, M (Serco NA US) | E90: anthony.wilson@serco-na.com | J90: Added 5/26
A91: Tech Debt - Asset Inventory | B91: https://serco.sharepoint.com/sites/TechDebt-AssetInventory | C91: Owner | D91: Wynn, Aaron (Serco NA) | E91: aaron.wynn@serco-na.com | J91: Added 5/26
... A96: Tech-Trakr - DASEE | B96: https://serco.sharepoint.com/sites/Tech-Trakr | C96: Owner | D96: Taylor, Adam (Serco NA US) | E96: adam.taylor@serco-na.com | J96: Added 5/26
A97: Data Operations | B97: https://serco.sharepoint.com/sites/TestArea43 | C97: Owner | D97: Defrancisco, Nicolas, W (Serco NA US) | E97: nicolas.defrancisco@serco-na.com | F97: Member | G97: Mapped | H97: Yes | I97: Yes
A98: Data Operations | B98: https://serco.sharepoint.com/sites/TestArea43 | C98: Owner | D98: Keyser, Matt, A (Serco NA) | E98: matthew.keyser@serco-na.com | F98: Member | G98: Migrated | H98: #N/A | I98: Yes
A99: Data Operations | B99: https://serco.sharepoint.com/sites/TestArea43 | C99: Owner | D99: Kloc, Joshua, R (Serco NA US) | E99: joshua.kloc@serco-na.com | F99: Member | G99: Mapped | H99: #N/A | I99: No
A100: Data Operations | B100: https://serco.sharepoint.com/sites/TestArea43 | C100: Owner | D100: Roffman, Samuel (Serco NA US) | E100: samuel.roffman@serco-na.com | F100: Member | G100: Mapped | H100: Yes | I100: Yes
A101: Data Operations | B101: https://serco.sharepoint.com/sites/TestArea43 | C101: Owner | D101: Rojas, Alex, K (Serco NA) | E101: alex.rojas@serco-na.com | F101: Member | G101: Migrated | H101: #N/A | I101: Yes
A102: Data Operations | B102: https://serco.sharepoint.com/sites/TestArea43 | C102: Owner | D102: Shitemi, Mercy (Serco NA US) | E102: mercy.shitemi@serco-na.com | F102: Member | G102: Mapped | H102: #N/A | I102: No
A103: Data Operations | B103: https://serco.sharepoint.com/sites/TestArea43 | C103: Owner | D103: Smith, Dan, C (Serco NA US) | E103: daniel.c.smith@serco-na.com | F103: Member | G103: Mapped | H103: Yes | I103: Yes
A104: Data Operations | B104: https://serco.sharepoint.com/sites/TestArea43 | C104: Owner | D104: Tran, Zoe, M (Serco NA US) | E104: zoe.tran@serco-na.com | F104: Member | G104: Migrated | H104: #N/A | I104: Yes
...

Sheet Wave 2B
A1: Site Url | B1: Site Name | C1: Is Teams Site | D1: W1Granular | E1: W2Granular | F1: Registry
A2: https://serco.sharepoint.com/sites/0623-2025PSIUSSFPJDDG121 | B2: 0623-2025 PSI USS FPJ DDG121 | C2: FALSE | D2: No | E2: No | F2: #N/A
A3: https://serco.sharepoint.com/sites/22464-USSCC4I | B3: 22464-USSC C4I | C3: FALSE | D3: YES | E3: No | F3: #N/A
A4: https://serco.sharepoint.com/sites/3PDtrackerwJim | B4: 3PD tracker w/Jim | C4: FALSE | D4: YES | E4: No | F4: #N/A
A5: https://serco.sharepoint.com/sites/3rdPartyDamage | B5: 3rd Party Damage | C5: FALSE | D5: YES | E5: No | F5: #N/A
A6: https://serco.sharepoint.com/sites/70 | B6: 70 | C6: FALSE | D6: No | E6: YES | F6: #N/A
A7: https://serco.sharepoint.com/sites/911Engineering | B7: 911 Engineering | C7: TRUE | D7: YES | E7: No | F7: #N/A
A8: https://serco.sharepoint.com/sites/ADNSCANESNetworkEngineering | B8: ADNS/CANES Network Engineering | C8: TRUE | D8: No | E8: No | F8: #N/A
A9: https://serco.sharepoint.com/sites/AEEnclaveTeam | B9: AE Enclave Team | C9: FALSE | D9: YES | E9: No | F9: #N/A
A10: https://serco.sharepoint.com/sites/AIENEXT | B10: AIE NEXT | C10: TRUE | D10: No | E10: No | F10: #N/A
A11: https://serco.sharepoint.com/sites/AMAS_CYBER | B11: AMAS_CYBER | C11: TRUE | D11: No | E11: No | F11: #N/A
A12: https://serco.sharepoint.com/sites/ATFP | B12: GSC Proposals | C12: TRUE | D12: YES | E12: No | F12: #N/A
A13: https://serco.sharepoint.com/sites/ATFPBridgeSustainment | B13: Goebel - Sustainment Team | C13: TRUE | D13: YES | E13: No | F13: #N/A
A14: https://serco.sharepoint.com/sites/ATFPBridgeTickets | B14: ATFP Bridge Tickets | C14: FALSE | D14: YES | E14: No | F14: #N/A
A15: https://serco.sharepoint.com/sites/ATFPGSCAMAS | B15: ATFP GSC AMAS | C15: FALSE | D15: No | E15: No | F15: #N/A
A16: https://serco.sharepoint.com/sites/ATFPGSCContractCommunication | B16: ATFP GSC Contract Communication | C16: FALSE | D16: No | E16: No | F16: #N/A
A17: https://serco.sharepoint.com/sites/ATFPGSCENERMS | B17: ATFP GSC ENERMS | C17: FALSE | D17: No | E17: No | F17: #N/A
A18: https://serco.sharepoint.com/sites/ATFPGSCGBRS | B18: ATFP GSC GBRS | C18: FALSE | D18: YES | E18: No | F18: #N/A
... A276: https://serco.sharepoint.com/sites/WorkforceProposalData | B276: Workforce Proposal Data | C276: TRUE | D276: YES | E276: No | F276: #N/A

Sheet DoNotMigrate-W1
A1: SITE URL (MAIN) | B1: SIZE IN GB | C1: SITE OWNERS - EMAIL | D1: BU | E1: Portfolio | F1: Action | G1: Site Exist in GCCH? | H1: Teams
A2: https://serco.sharepoint.com/sites/EHSINSIGHT | C2: jmorrison@SERCO-NA.COM | D2: SI2 | E2: SSM-PMO
A3: https://serco.sharepoint.com/sites/EHSINSIGHT-AdminPrivateChannel | C3: jmorrison@serco-na.com | D3: SI2 | E3: SSM-PMO
A4: https://serco.sharepoint.com/sites/EHSInsightImplimentation | C4: jmorrison@SERCO-NA.COM | D4: SI2 | E4: SSM-PMO
A5: https://serco.sharepoint.com/sites/EHSInsightImplimentation-SpendPlan | C5: jmorrison@serco-na.com | D5: SI2 | E5: SSM-PMO
A6: https://serco.sharepoint.com/sites/ehsinsighttraining | C6: jmorrison@SERCO-NA.COM | D6: SI2 | E6: SSM-PMO
A7: https://serco.sharepoint.com/sites/EHSINSIGHT-TrainingModule | C7: jmorrison@serco-na.com | D7: SI2 | E7: SSM-PMO
A8: https://serco.sharepoint.com/sites/GrandForksADP2 | B8: 0 | C8: Randy.Brown@serco-na.com | D8: Corporate Services | E8: Technology | F8: Do NOT Migrate
A9: https://serco.sharepoint.com/sites/MilesOlson2 | B9: 0.01 | C9: Miles.Olson@serco-na.com | D9: Corporate Services | E9: Technology | F9: Do NOT Migrate
A10: https://serco.sharepoint.com/sites/MilesOlsonSite1 | B10: 0.01 | C10: Miles.Olson@serco-na.com | D10: Corporate Services | E10: Technology | F10: Do NOT Migrate
A11: https://serco.sharepoint.com/sites/PersonalTest2 | B11: 0.01 | C11: Zoe.Tran@serco-na.com | D11: Corporate Services | E11: Technology | F11: Do NOT Migrate
A12: https://serco.sharepoint.com/sites/PracticeSite | B12: 0.01 | C12: Miles.Olson@serco-na.com | D12: Corporate Services | E12: Technology | F12: Do NOT Migrate
A13: https://serco.sharepoint.com/sites/PracticeSite16 | B13: 0.01 | C13: Miles.Olson@serco-na.com | D13: Corporate Services | E13: Technology | F13: Do NOT Migrate
A14: https://serco.sharepoint.com/sites/TestSite20 | B14: 0.01 | C14: Zoe.Tran@serco-na.com | D14: Corporate Services | E14: Technology | F14: Do NOT Migrate
A15: https://serco.sharepoint.com/sites/BDOpportunityTracker | B15: 0.01 | C15: Whitney.Sessoms@SERCO-NA.COM | D15: Corporate Services | E15: Technology | F15: Do NOT Migrate
A16: https://serco.sharepoint.com/sites/C3BMT | B16: 0.01 | C16: Kevin.Pratte@serco-na.com | D16: Corporate Services | E16: Technology | F16: Do NOT Migrate
A17: https://serco.sharepoint.com/sites/Carp3 | B17: 0.01 | C17: Thomas.Glass@serco-na.com | D17: Corporate Services | E17: Technology | F17: Do NOT Migrate
A18: https://serco.sharepoint.com/sites/EmployeeEngagementProgram-PatuxentRiver | B18: 0.01 | C18: Robin.Landeros@serco-na.com | D18: Corporate Services | E18: Technology | F18: Do NOT Migrate
A19: https://serco.sharepoint.com/sites/ETSSOrg | B19: 0.01 | C19: Kelly.Cormican@serco-na.com | D19: Corporate Services | E19: Technology | F19: Do NOT Migrate
... A32: https://serco.sharepoint.com/sites/SWBBSchedulers | B32: 0.01 | C32: Teresa.Burke@serco-na.com | D32: Corporate Services | E32: Technology | F32: Do NOT Migrate
A33: https://serco.sharepoint.com/sites/ABMSArchitectureTeam | B33: 0.01 | C33: Preston.White@serco-na.com | D33: Corporate Services | E33: #N/A | F33: Do NOT Migrate
A34: https://serco.sharepoint.com/sites/AFRCCI2RFI | B34: 0.01 | C34: Luke.Mcdade@serco-na.com | D34: Corporate Services | E34: Technology | F34: Do NOT Migrate
A35: https://serco.sharepoint.com/sites/AgileImpactMissionPerformanceOptimizationTeam | B35: 0.01 | C35: Albert.Moseley@serco-na.com | D35: Corporate Services | E35: Technology | F35: Do NOT Migrate
A36: https://serco.sharepoint.com/sites/ArmyReview | B36: 0.01 | C36: Brian.Stehle@serco-na.com | D36: Corporate Services | E36: Technology | F36: Do NOT Migrate
A37: https://serco.sharepoint.com/sites/ATGandIDIQCollaborationSite | B37: 0.01 | C37: Tracy.West@serco-na.com | D37: Corporate Services | E37: Technology | F37: Do NOT Migrate
A38: https://serco.sharepoint.com/sites/CGBI | B38: 0.01 | C38: Gus.Burnette@serco-na.com | D38: Corporate Services | E38: Technology | F38: Do NOT Migrate
A39: https://serco.sharepoint.com/sites/DashboardDevelopment | B39: 0.01 | C39: Brian.Godfrey@serco-na.com | D39: Corporate Services | E39: Technology | F39: Do NOT Migrate
A40: https://serco.sharepoint.com/sites/DataCollectionYellowBeltProject | B40: 0.01 | C40: Brian.Godfrey@serco-na.com | D40: Corporate Services | E40: Technology | F40: Do NOT Migrate
A41: https://serco.sharepoint.com/sites/DeploymentHealthResearchSupportServicessections3.4and3.5 | B41: 0.01 | C41: Scott.Adams@serco-na.com | D41: Corporate Services | E41: Technology | F41: Do NOT Migrate
A42: https://serco.sharepoint.com/sites/FAR-RFOCompare | B42: 0.01 | C42: Christine.Diehl@serco-na.com | D42: Corporate Services | E42: Technology | F42: Do NOT Migrate
A43: https://serco.sharepoint.com/sites/GayleSpace | B43: 0.01 | C43: Gayle.Ingram@serco-na.com | D43: Corporate Services | E43: Technology | F43: Do NOT Migrate
A44: https://serco.sharepoint.com/sites/KC-YBCASchedule | B44: 0.01 | C44: Brian.Godfrey@serco-na.com | D44: Corporate Services | E44: Technology | F44: Do NOT Migrate
A45: https://serco.sharepoint.com/sites/LAWBurnPlan | B45: 0.01 | C45: Brian.Stehle@serco-na.com; Timothy.Baker@serco-na.com | D45: Corporate Services | E45: #N/A | F45: Do NOT Migrate
A46: https://serco.sharepoint.com/sites/PIO-Sandbox | B46: 0.01 | C46: Zoe.Tran@serco-na.com | D46: Corporate Services | E46: Technology | F46: Do NOT Migrate
A47: https://serco.sharepoint.com/sites/PMA-226Opportunity | B47: 0.01 | C47: Thomas.Glass@serco-na.com; Wayne.Borchers@serco-na.com | D47: Corporate Services | E47: #N/A | F47: Do NOT Migrate
A48: https://serco.sharepoint.com/sites/PNTSDUE | B48: 0.01 | C48: Bradley.Schlenker@serco-na.com | D48: Corporate Services | E48: Technology | F48: Do NOT Migrate
A49: https://serco.sharepoint.com/sites/ReformedPCOs | B49: 0.01 | C49: Christina.Hall@serco-na.com | D49: Corporate Services | E49: Technology | F49: Do NOT Migrate
A50: https://serco.sharepoint.com/sites/SAM-US-METS-DON-PIO_IMS-MTM | B50: 0.01 | C50: Cassidy.Kuzemka@serco-na.com | D50: Corporate Services | E50: Technology | F50: Do NOT Migrate
A51: https://serco.sharepoint.com/sites/SECOIA | B51: 0.01 | C51: George.Sanderlin@serco-na.com | D51: Corporate Services | E51: Technology | F51: Do NOT Migrate
A52: https://serco.sharepoint.com/sites/SercoWBBConsultingFileTransfer | B52: 0.01 | C52: Albert.Moseley@serco-na.com | D52: Corporate Services | E52: Technology | F52: Do NOT Migrate
A53: https://serco.sharepoint.com/sites/SercoWomen | B53: 0.01 | C53: Whitney.Sessoms@SERCO-NA.COM | D53: Corporate Services | E53: Technology | F53: Do NOT Migrate
A54: https://serco.sharepoint.com/sites/StrategyOpsGroup-AS | B54: 0.01 | C54: Albert.Moseley@serco-na.com | D54: Corporate Services | E54: Technology | F54: Do NOT Migrate
A55: https://serco.sharepoint.com/sites/TextronCraft-CONOPSforOperationsinaContestedLogisticsEnviron | B55: 0.01 | C55: Brock.Magnino@serco-na.com | D55: Corporate Services | E55: Technology | F55: Do NOT Migrate
A56: https://serco.sharepoint.com/sites/USAFUSSFCyberGrowthTeam | B56: 0.01 | C56: Matthew.Imperial@serco-na.com | D56: Corporate Services | E56: Technology | F56: Do NOT Migrate
A57: https://serco.sharepoint.com/sites/V-22BusinessDevelopment | B57: 0.01 | C57: Brock.Magnino@serco-na.com; Wayne.Borchers@serco-na.com | D57: Corporate Services | E57: #N/A | F57: Do NOT Migrate
A58: https://serco.sharepoint.com/sites/EMDecoyResearch | B58: 0.02 | C58: Robin.Landeros@serco-na.com; Vanessa.Bauer@SERCO-NA.COM | D58: Corporate Services | E58: #N/A | F58: Do NOT Migrate
A59: https://serco.sharepoint.com/sites/ABMSCostInfo | B59: 0.02 | C59: Katrina.Mims@serco-na.com; Gayle.Ingram@serco-na.com | D59: Corporate Services | E59: #N/A | F59: Do Not Migrate
A60: https://serco.sharepoint.com/sites/BelgiumMODPortSecurity | B60: 0.02 | C60: James.Hammond@serco-na.com; William.Burnette@serco-na.com | D60: Corporate Services | E60: #N/A | F60: Do NOT Migrate
A61: https://serco.sharepoint.com/sites/C-146Cost | B61: 0.02 | C61: Jacob.Heard@serco-na.com | D61: Corporate Services | E61: Technology | F61: Do NOT Migrate
A62: https://serco.sharepoint.com/sites/CriticalChainProjectManagement | B62: 0.02 | C62: Scott.Adams@serco-na.com | D62: Corporate Services | E62: Technology | F62: Do Not Migrate
A63: https://serco.sharepoint.com/sites/ETO-BD-AFCECyber | B63: 0.02 | C63: Tracy.West@serco-na.com; George.Sanderlin@serco-na.com; Randy.Brown@serco-na.com | D63: Corporate Services | E63: #N/A | F63: Do Not Migrate
A64: https://serco.sharepoint.com/sites/GEInitiative | B64: 0.02 | C64: Timothy.Hope@serco-na.com | D64: Corporate Services | E64: Technology | F64: Do NOT Migrate
A65: https://serco.sharepoint.com/sites/JSFModsTeam2 | B65: 0.02 | C65: Christina.Hall@serco-na.com | D65: Corporate Services | E65: Technology | F65: Do NOT Migrate
A66: https://serco.sharepoint.com/sites/NavyPMS450ITKMCollab | B66: 0.02 | C66: Matthew.Imperial@serco-na.com | D66: Corporate Services | E66: Technology | F66: Do NOT Migrate
A67: https://serco.sharepoint.com/sites/PMA-263TIPS | B67: 0.02 | C67: Thomas.Glass@serco-na.com; Timothy.Baker@serco-na.com | D67: Corporate Services | E67: #N/A | F67: Do Not Migrate
A68: https://serco.sharepoint.com/sites/RCOResumeReview | B68: 0.02 | C68: Michael.Lee@serco-na.com | D68: Corporate Services | E68: Technology | F68: Do NOT Migrate
A69: https://serco.sharepoint.com/sites/SEA21D | B69: 0.02 | C69: Scott.Adams@serco-na.com | D69: Corporate Services | E69: Technology | F69: Do NOT Migrate
A70: https://serco.sharepoint.com/sites/StrategicWorkforcePlanning | B70: 0.02 | C70: Luke.Mcdade@serco-na.com | D70: Corporate Services | E70: Technology | F70: Do NOT Migrate
A71: https://serco.sharepoint.com/sites/YellowBeltProject327 | B71: 0.02 | C71: Brian.Godfrey@serco-na.com | D71: Corporate Services | E71: Technology | F71: Do Not Migrate
A72: https://serco.sharepoint.com/sites/TextronCONOPS | B72: 0.03 | C72: Brock.Magnino@serco-na.com | D72: Corporate Services | E72: Technology | F72: Do Not Migrate
A73: https://serco.sharepoint.com/sites/DDGXAcquisitionSupport | B73: 0.03 | C73: Brian.Stehle@serco-na.com | D73: Corporate Services | E73: Technology | F73: Do Not Migrate
A74: https://serco.sharepoint.com/sites/GEAerospace-ContestedLogisticsEnvironment | B74: 0.03 | C74: Timothy.Hope@serco-na.com | D74: Corporate Services | E74: Technology | F74: Do NOT Migrate
A75: https://serco.sharepoint.com/sites/PMA-264-TeamPrecise | B75: 0.03 | C75: Timothy.Baker@serco-na.com | D75: Corporate Services | E75: Technology | F75: Do Not Migrate
A76: https://serco.sharepoint.com/sites/SEVProposal | B76: 0.03 | C76: Brian.Godfrey@serco-na.com; Richard.Branson@serco-na.com | D76: Corporate Services | E76: #N/A | F76: Do Not Migrate
A77: https://serco.sharepoint.com/sites/AdminTestTeam | B77: 0.04 | C77: Kyle.Hagen@serco-na.com; Kyle.Hagen@serco-na.com | D77: Corporate Services | E77: #N/A | F77: Do NOT Migrate
A78: https://serco.sharepoint.com/sites/AMCAGBPATeamSerco | B78: 0.04 | C78: Brian.Stehle@serco-na.com | D78: Corporate Services | E78: Technology | F78: Do Not Migrate
A79: https://serco.sharepoint.com/sites/AMCOMAIMLEffortMaximo | B79: 0.04 | C79: Brian.Stehle@serco-na.com | D79: Corporate Services | E79: Technology | F79: Do Not Migrate
A80: https://serco.sharepoint.com/sites/SercoPaxEmployeeEngagement | B80: 0.04 | C80: Timothy.Baker@serco-na.com | D80: Corporate Services | E80: Technology | F80: Do Not Migrate
A81: https://serco.sharepoint.com/sites/RCCTO | B81: 0.05 | C81: Michael.Mcneill@serco-na.com | D81: Corporate Services | E81: Technology | F81: Do Not Migrate
A82: https://serco.sharepoint.com/sites/DCGS | B82: 0.05 | C82: Christopher.Pritchet@serco-na.com | D82: Corporate Services | E82: Technology | F82: Do Not Migrate
A83: https://serco.sharepoint.com/sites/PowerAppsTesting | B83: 0.05 | C83: Zoe.Tran@serco-na.com; Miles.Olson@serco-na.com | D83: Corporate Services | E83: #N/A | F83: Do NOT Migrate
A84: https://serco.sharepoint.com/sites/SA-US-GLASS-CT | B84: 0.06 | C84: Whitney.Sessoms@serco-na.com | D84: Corporate Services | E84: Technology | F84: Do NOT Migrate
A85: https://serco.sharepoint.com/sites/NASASEWPVIpre-WINSTEAMSsite | B85: 0.06 | C85: Tracy.West@serco-na.com | D85: Corporate Services | E85: Technology | F85: Do Not Migrate
A86: https://serco.sharepoint.com/sites/NATOACT | B86: 0.07 | C86: Matthew.Sharpe@serco-na.com | D86: Corporate Services | E86: Technology | F86: Do Not Migrate
A87: https://serco.sharepoint.com/sites/CNALDisruptiveReorganization | B87: 0.08 | C87: Matthew.Sharpe@serco-na.com; Kelly.Cormican@serco-na.com | D87: Corporate Services | E87: #N/A | F87: Do Not Migrate
A88: https://serco.sharepoint.com/sites/AgileViewpointSurvey-RetentionTeam | B88: 0.08 | C88: Thomas.Ober@serco-na.com | D88: Corporate Services | E88: Technology | F88: Do NOT Migrate
A89: https://serco.sharepoint.com/sites/PBGCFOSSCXWhitePaper | B89: 0.08 | C89: Luke.Mcdade@serco-na.com | D89: Corporate Services | E89: Technology | F89: Do NOT Migrate
A90: https://serco.sharepoint.com/sites/USAFEC2 | B90: 0.09 | C90: Tracy.West@serco-na.com | D90: Corporate Services | E90: Technology | F90: Do Not Migrate
A91: https://serco.sharepoint.com/sites/sercorisingemployeeresourcegroup | B91: 0.1 | C91: Zoe.Tran@serco-na.com | D91: Corporate Services | E91: Technology | F91: Do Not Migrate
A92: https://serco.sharepoint.com/sites/ArmyCrossFunctionalTeam-ContestedLogistics | B92: 0.1 | C92: Brian.Stehle@serco-na.com | D92: Corporate Services | E92: Technology | F92: Do Not Migrate
A93: https://serco.sharepoint.com/sites/TankerRecapWS1 | B93: 0.1 | C93: Wayne.Rohe@serco-na.com; Cheryl.Lawrence@serco-na.com | D93: Corporate Services | E93: #N/A | F93: Do Not Migrate
A94: https://serco.sharepoint.com/sites/USAFRCOFMProcess | B94: 0.1 | C94: Isma.Zeghmi@serco-na.com | D94: Corporate Services | E94: Technology | F94: Do Not Migrate
A95: https://serco.sharepoint.com/sites/CARDs | B95: 0.11 | C95: Kimberly.Jarvi@serco-na.com | D95: Corporate Services | E95: Technology | F95: Do Not Migrate
A96: https://serco.sharepoint.com/sites/ILCBMProposal | B96: 0.11 | C96: William.Burnette@serco-na.com | D96: Corporate Services | E96: Technology | F96: Do Not Migrate
A97: https://serco.sharepoint.com/sites/F-22PPPs | B97: 0.14 | C97: Wayne.Rohe@serco-na.com | D97: Corporate Services | E97: Technology | F97: Do Not Migrate
A98: https://serco.sharepoint.com/sites/SA-US-APMBD-FT | B98: 0.16 | C98: Whitney.Sessoms@serco-na.com | D98: Corporate Services | E98: Technology | F98: Do NOT Migrate
A99: https://serco.sharepoint.com/sites/KC-YBCA308 | B99: 0.16 | C99: Brian.Godfrey@serco-na.com | D99: Corporate Services | E99: Technology | F99: Do Not Migrate
A100: https://serco.sharepoint.com/sites/UkraineBD | B100: 0.21 | C100: Timothy.Hope@serco-na.com; Kenneth.A.Brown@serco-na.com | D100: Corporate Services | E100: #N/A | F100: Do NOT Migrate
A101: https://serco.sharepoint.com/sites/vbo | B101: 0.22 | C101: Matthew.Sharpe@serco-na.com | D101: Corporate Services | E101: Technology | F101: Do Not Migrate
A102: https://serco.sharepoint.com/sites/FacilityAssetManagment | B102: 0.25 | C102: Timothy.Hope@serco-na.com | D102: Corporate Services | E102: Technology | F102: Do NOT Migrate
A103: https://serco.sharepoint.com/sites/NWFISSM | B103: 0.26 | C103: Bradley.Schlenker@serco-na.com | D103: Corporate Services | E103: Technology | F103: Do NOT Migrate
A104: https://serco.sharepoint.com/sites/PNT-Roadmap | B104: 0.27 | C104: Timothy.Hope@serco-na.com | D104: Corporate Services | E104: Technology | F104: Do Not Migrate
A105: https://serco.sharepoint.com/sites/2023NDAAReportLSM-MSV | B105: 0.3 | C105: Brian.Stehle@serco-na.com | D105: Corporate Services | E105: Technology | F105: Do Not Migrate
A106: https://serco.sharepoint.com/sites/AUSLand8710Project | B106: 0.3 | C106: William.Burnette@serco-na.com | D106: Corporate Services | E106: Technology | F106: Do Not Migrate
A107: https://serco.sharepoint.com/sites/KC-YBCA | B107: 0.3 | C107: Brian.Godfrey@serco-na.com | D107: Corporate Services | E107: Technology | F107: Do Not Migrate
A108: https://serco.sharepoint.com/sites/USFFCSGRiskAssessment | B108: 0.3 | C108: Matthew.Sharpe@serco-na.com | D108: Corporate Services | E108: Technology | F108: Do Not Migrate
A109: https://serco.sharepoint.com/sites/Test36 | B109: 0.31 | C109: Zoe.Tran@serco-na.com; Kelly.Cormican@serco-na.com | D109: Corporate Services | E109: #N/A | F109: Do NOT Migrate
A110: https://serco.sharepoint.com/sites/ironsharpensiron | B110: 0.31 | C110: Matthew.Sharpe@serco-na.com | D110: Corporate Services | E110: Technology | F110: Do Not Migrate
A111: https://serco.sharepoint.com/sites/AirUInitiatives | B111: 0.31 | C111: Gregory.Owens@serco-na.com | D111: Corporate Services | E111: Technology | F111: Do Not Migrate
A112: https://serco.sharepoint.com/sites/DES-KPI12FindingsRecommendations | B112: 0.35 | C112: Luke.Mcdade@serco-na.com | D112: Corporate Services | E112: Technology | F112: Do NOT Migrate
...

Sheet All Sites_20260129180943356
A1: ﻿"Site name" | B1: , | C1: Teams | D1: Channel sites | E1: IBMode | F1: Storage used (GB) | G1: Primary admin | H1: Hub | I1: Template | J1: Last activity (UTC) | K1: Date created | L1: Created by | M1: Storage limit (GB) | N1: Storage used (%) | O1: Microsoft 365 group | P1: Files viewed or edited | Q1: Page views | R1: Page visits | S1: Files | T1: Sensitivity | U1: External sharing | V1: Wave
A2: 0 | B2: https://serco.sharepoint.com/sites/00000 | C2: TRUE | E2: Open | F2: 0.01 | I2: Team site | K2: 44222.585 | L2: 00000 Owners | M2: 25600 | N2: 0 | O2: TRUE | P2: 0 | Q2: 0 | R2: 0 | S2: 16 | U2: On | V2: Unplanned
A3: 70 | B3: https://serco.sharepoint.com/sites/70 | C3: FALSE | E3: Open | F3: 0 | I3: Team site | J3: 45947 | K3: 43651.66 | L3: Kitchin, Todd, M (Serco NA US) | M3: 25600 | N3: 0 | O3: TRUE | P3: 0 | Q3: 0 | R3: 0 | S3: 132 | U3: On | V3: Unplanned
A4: 99 | B4: https://serco.sharepoint.com/sites/99 | C4: FALSE | E4: Open | F4: 0.02 | I4: Team site | J4: 44490 | K4: 44412.857 | L4: 99 Owners | M4: 25600 | N4: 0 | O4: TRUE | P4: 0 | Q4: 0 | R4: 0 | S4: 14 | U4: On | V4: Unplanned
A5: 123 | B5: https://serco.sharepoint.com/sites/1234 | C5: TRUE | E5: Open | F5: 0.05 | I5: Team site | J5: 45742 | K5: 44239.434 | L5: 123 Owners | M5: 25600 | N5: 0 | O5: TRUE | P5: 0 | Q5: 0 | R5: 0 | S5: 21 | U5: On | V5: Unplanned
A6: 397 | B6: https://serco.sharepoint.com/sites/397 | C6: FALSE | E6: Open | F6: 0 | I6: Team site | K6: 45967.742 | L6: 397 Owners | M6: 25600 | N6: 0 | O6: TRUE | P6: 0 | Q6: 0 | R6: 0 | S6: 0 | U6: On | V6: Unplanned
A7: 401 | B7: https://serco.sharepoint.com/sites/401 | C7: TRUE | E7: Open | F7: 0 | I7: Team site | J7: 45692 | K7: 45442.495 | L7: 401 Owners | M7: 25600 | N7: 0 | O7: TRUE | P7: 0 | Q7: 0 | R7: 0 | S7: 7 | U7: On | V7: Unplanned
A8: 2018 | B8: https://serco.sharepoint.com/sites/2018 | C8: FALSE | E8: Open | F8: 0.01 | I8: Team site | J8: 43916 | K8: 43313.554 | L8: Castledine, Annabel | M8: 25600 | N8: 0 | O8: TRUE | P8: 0 | Q8: 0 | R8: 0 | S8: 39 | U8: On | V8: Unplanned
A9: 21585 | B9: https://serco.sharepoint.com/sites/21585 | C9: FALSE | E9: Open | F9: 0.01 | I9: Team site | K9: 44310.083 | L9: 21585 Owners | M9: 25600 | N9: 0 | O9: TRUE | P9: 0 | Q9: 0 | R9: 0 | S9: 15 | U9: On | V9: Unplanned
A10: 44624 | B10: https://serco.sharepoint.com/sites/03042022 | C10: FALSE | E10: Open | F10: 0 | I10: Team site | K10: 44653.739 | L10: 03/04/2022 Owners | M10: 25600 | N10: 0 | O10: TRUE | P10: 0 | Q10: 0 | R10: 0 | S10: 8 | U10: On | V10: Unplanned
A11: 44625 | B11: https://serco.sharepoint.com/sites/030522 | C11: FALSE | E11: Open | F11: 0 | I11: Team site | K11: 44684.244 | L11: 03/05/22 Owners | M11: 25600 | N11: 0 | O11: TRUE | P11: 0 | Q11: 0 | R11: 0 | S11: 8 | U11: On | V11: Unplanned
A12: 44627 | B12: https://serco.sharepoint.com/sites/03072022 | C12: FALSE | E12: Open | F12: 0 | I12: Team site | K12: 44744.677 | L12: 03/07/2022 Owners | M12: 25600 | N12: 0 | O12: TRUE | P12: 0 | Q12: 0 | R12: 0 | S12: 8 | U12: On | V12: Unplanned
A13: 46287 | B13: https://serco.sharepoint.com/sites/September2022 | C13: FALSE | E13: Open | F13: 0.01 | I13: Team site | J13: 44825 | K13: 44789.541 | L13: September 2022 Owners | M13: 25600 | N13: 0 | O13: TRUE | P13: 0 | Q13: 0 | R13: 0 | S13: 13 | U13: On | V13: Unplanned
A14: 60031 | B14: https://serco.sharepoint.com/sites/60031 | C14: FALSE | E14: Open | F14: 0.01 | I14: Team site | K14: 44139.582 | L14: Hendricks, Patsy, A (Serco NA) | M14: 25600 | N14: 0 | O14: TRUE | P14: 0 | Q14: 0 | R14: 0 | S14: 18 | U14: On | V14: Unplanned
A15: Defense Services Business Unit | B15: https://serco.sharepoint.com/sites/SAM-US-DefSerBU-FT | C15: FALSE | E15: Open | F15: 0.03 | G15: System Account | I15: Team site (classic experience) | J15: 45866 | K15: 42429.647 | L15: System Account | M15: 25600 | N15: 0 | O15: FALSE | P15: 0 | Q15: 0 | R15: 0 | S15: 159 | U15: Off | V15: Unplanned
A16: !Finance Home Team Theo Teams Site | B16: https://serco.sharepoint.com/sites/FinanceHomeTeamTheoTeamsSite | C16: TRUE | E16: Open | F16: 0.02 | I16: Team site | J16: 45903 | K16: 45707.799 | L16: !Finance Home Team Theo Teams Site Owners | M16: 25600 | N16: 0 | O16: TRUE | P16: 0 | Q16: 0 | R16: 0 | S16: 11 | U16: On | V16: Unplanned
A17: #TeamC&W | B17: https://serco.sharepoint.com/sites/TeamCW | C17: TRUE | E17: Open | F17: 0.01 | I17: Team site | J17: 45979 | K17: 43910.353 | L17: Harrison, Linda | M17: 25600 | N17: 0 | O17: TRUE | P17: 0 | Q17: 0 | R17: 0 | S17: 23 | U17: On | V17: Unplanned
A18: (DO NOT USE) OLD Trust Room Booking | B18: https://serco.sharepoint.com/sites/TrustRoomBooking | C18: TRUE | E18: Open | F18: 0.28 | I18: Team site | J18: 44472 | K18: 43911.383 | L18: Marlow, Martin | M18: 25600 | N18: 0 | O18: TRUE | P18: 0 | Q18: 0 | R18: 0 | S18: 43 | U18: On | V18: Unplanned
A19: (USAF21001.00) | B19: https://serco.sharepoint.com/sites/WBBProjects | C19: FALSE | E19: Open | F19: 0 | G19: o-fkruk | I19: Team site (no Microsoft 365 group) | J19: 45482 | K19: 44887.801 | L19: o-jtinsley | M19: 25600 | N19: 0 | O19: FALSE | P19: 0 | Q19: 0 | R19: 0 | S19: 6 | U19: Off | V19: Unplanned
A20: *DO NOT USE* Archived ExperienceLab Business Development | B20: https://serco.sharepoint.com/sites/ExperienceLabBusinessDevelopment | C20: TRUE | E20: Open | F20: 70.7 | I20: Team site | J20: 46049 | K20: 43206.46 | L20: Child, Rebecca | M20: 25600 | N20: 0 | O20: TRUE | P20: 1 | Q20: 0 | R20: 0 | S20: 4245 | U20: On | V20: Unplanned
A21: *P3 Planning | B21: https://serco.sharepoint.com/sites/P3Planning | C21: TRUE | D21: 0 | E21: Open | F21: 0.22 | I21: Team site | J21: 46042 | K21: 45308.648 | L21: *P3 Planning Owners | M21: 25600 | N21: 0 | O21: TRUE | P21: 1 | Q21: 0 | R21: 0 | S21: 79 | U21: On | V21: Unplanned
A22: . | B22: https://serco.sharepoint.com/sites/msteams_c161e2 | C22: TRUE | E22: Open | F22: 0 | I22: Team site | J22: 45202 | K22: 45019.285 | L22: . Owners | M22: 25600 | N22: 0 | O22: TRUE | P22: 0 | Q22: 0 | R22: 0 | S22: 8 | U22: On | V22: Unplanned
A23: .. | B23: https://serco.sharepoint.com/sites/msteams_112594 | C23: TRUE | D23: 1 | E23: Open | F23: 0 | I23: Team site | J23: 45596 | K23: 45596.645 | L23: .. Owners | M23: 25600 | N23: 0 | O23: TRUE | P23: 0 | Q23: 0 | R23: 0 | S23: 7 | U23: On | V23: Unplanned
A24: ... | B24: https://serco.sharepoint.com/sites/msteams_8e9a23 | C24: TRUE | E24: Open | F24: 0.01 | I24: Team site | J24: 44130 | K24: 43913.488 | L24: Weir, Chloe Russell | M24: 25600 | N24: 0 | O24: TRUE | P24: 0 | Q24: 0 | R24: 0 | S24: 21 | U24: On | V24: Unplanned
A25: .xxx 3PD Planner | B25: https://serco.sharepoint.com/sites/xxx3PDPlanner | C25: FALSE | E25: Open | F25: 0.1 | I25: Team site | J25: 45993 | K25: 44795.685 | L25: .xxx 3PD Planner Owners | M25: 25600 | N25: 0 | O25: TRUE | P25: 0 | Q25: 0 | R25: 0 | S25: 232 | U25: On | V25: Unplanned
A26: [ML-Internal]Azure | B26: https://serco.sharepoint.com/sites/ML-InternalAzure | C26: TRUE | E26: Open | F26: 0.01 | I26: Team site | J26: 44810 | K26: 44312.775 | L26: [ML-Internal]Azure Owners | M26: 25600 | N26: 0 | O26: TRUE | P26: 0 | Q26: 0 | R26: 0 | S26: 45 | U26: On | V26: Unplanned
A27: [NEWS] | B27: https://serco.sharepoint.com/sites/news | C27: FALSE | E27: Open | F27: 0.01 | I27: Team site | J27: 45783 | K27: 43685.822 | L27: Zografos, Gus (Serco NA) | M27: 25600 | N27: 0 | O27: TRUE | P27: 0 | Q27: 0 | R27: 0 | S27: 25 | U27: On | V27: Unplanned
A28: _Serco Leadership Email CC | B28: https://serco.sharepoint.com/sites/a_SercoLeadershipEmailCC | C28: FALSE | E28: Open | F28: 0.01 | I28: Team site | J28: 44123 | K28: 44068.702 | L28: Carlson, Scott, M (Serco NA US) | M28: 25600 | N28: 0 | O28: TRUE | P28: 0 | Q28: 0 | R28: 0 | S28: 21 | U28: On | V28: Unplanned
A29: _Serco SDO 06.02.05.04 Blish Team OBS | B29: https://serco.sharepoint.com/sites/a_SercoSDO06.02.05.04BlishTeamOBS | C29: FALSE | E29: Open | F29: 0 | I29: Team site | J29: 45902 | K29: 45742.715 | L29: _Serco SDO 06.02.05.04 Blish Team OBS Owners | M29: 25600 | N29: 0 | O29: TRUE | P29: 0 | Q29: 0 | R29: 0 | S29: 3 | U29: On | V29: Unplanned
A30: +IMPACT Workshop (15-16 August 2024) | B30: https://serco.sharepoint.com/sites/IMPACTWorkshop15-16August2024 | C30: TRUE | E30: Open | F30: 0.06 | I30: Team site | J30: 45700 | K30: 45518.316 | L30: +IMPACT Workshop (15-16 August 2024) Owners | M30: 25600 | N30: 0 | O30: TRUE | P30: 0 | Q30: 0 | R30: 0 | S30: 14 | U30: On | V30: Unplanned
A31: ✨ ER Management Team ✨ | B31: https://serco.sharepoint.com/sites/MyHRSupport | C31: TRUE | E31: Open | F31: 6.04 | I31: Team site | J31: 46001 | K31: 43619.457 | L31: Polson, Charlotte | M31: 25600 | N31: 0 | O31: TRUE | P31: 0 | Q31: 0 | R31: 0 | S31: 339 | U31: On | V31: Unplanned
A32: 0. Template Plan | B32: https://serco.sharepoint.com/sites/0TemplatePlan | C32: FALSE | E32: Open | F32: 0 | I32: Team site | J32: 45824 | K32: 45575.429 | L32: 0. Template Plan Owners | M32: 25600 | N32: 0 | O32: TRUE | P32: 0 | Q32: 0 | R32: 0 | S32: 5 | U32: On | V32: Unplanned
A33: 0000002 - Test Opportunity 2 opportunity site | B33: https://serco.sharepoint.com/sites/Dynamics_Opportunity_287c376f-f5f0-e911-a812-000d3a5460bd | C33: FALSE | E33: Open | F33: 0.01 | G33: Williams, Stephen | I33: Team site (no Microsoft 365 group) | J33: 43917 | K33: 43832.659 | L33: Williams, Stephen | M33: 25600 | N33: 0 | O33: FALSE | P33: 0 | Q33: 0 | R33: 0 | S33: 20 | U33: Off | V33: Unplanned
A34: 0000003 - Test Opportunity 1 Opportunity Site | B34: https://serco.sharepoint.com/sites/Dynamics_Opportunity_Dev_0000003 | C34: FALSE | E34: Open | F34: 0.01 | G34: Williams, Stephen | I34: Team site (no Microsoft 365 group) | J34: 43917 | K34: 43866.616 | L34: Williams, Stephen | M34: 25600 | N34: 0 | O34: FALSE | P34: 0 | Q34: 0 | R34: 0 | S34: 25 | U34: Off | V34: Unplanned
A35: 0001263 - Steve Test opportunity site | B35: https://serco.sharepoint.com/sites/Dynamics_Opportunity_Dev_0001263 | C35: FALSE | E35: Open | F35: 0.01 | G35: Williams, Stephen | I35: Team site (no Microsoft 365 group) | J35: 43917 | K35: 43833.398 | L35: Williams, Stephen | M35: 25600 | N35: 0 | O35: FALSE | P35: 0 | Q35: 0 | R35: 0 | S35: 20 | U35: Off | V35: Unplanned
A36: 0001267 - Test BJ 001 opportunity site | B36: https://serco.sharepoint.com/sites/Dynamics_Opportunity_Dev_0001267 | C36: FALSE | E36: Open | F36: 0.01 | G36: Williams, Stephen | I36: Team site (no Microsoft 365 group) | J36: 43918 | K36: 43833.426 | L36: Williams, Stephen | M36: 25600 | N36: 0 | O36: FALSE | P36: 0 | Q36: 0 | R36: 0 | S36: 21 | U36: Off | V36: Unplanned
A37: 0001268 - Test BJ 002 opportunity site | B37: https://serco.sharepoint.com/sites/Dynamics_Opportunity_Dev_0001268 | C37: FALSE | E37: Open | F37: 0.01 | G37: Williams, Stephen | I37: Team site (no Microsoft 365 group) | J37: 43917 | K37: 43833.434 | L37: Williams, Stephen | M37: 25600 | N37: 0 | O37: FALSE | P37: 0 | Q37: 0 | R37: 0 | S37: 21 | U37: Off | V37: Unplanned
A38: 0001269 - Test BJ 003 opportunity site | B38: https://serco.sharepoint.com/sites/Dynamics_Opportunity_Dev_0001269 | C38: FALSE | E38: Open | F38: 0.01 | G38: Williams, Stephen | I38: Team site (no Microsoft 365 group) | J38: 43917 | K38: 43833.446 | L38: Williams, Stephen | M38: 25600 | N38: 0 | O38: FALSE | P38: 0 | Q38: 0 | R38: 0 | S38: 20 | U38: Off | V38: Unplanned
A39: 0001269 - Test BJ 003 opportunity site | B39: https://serco.sharepoint.com/sites/Dynamics_Opportunity_Dev_0001269_1 | C39: FALSE | E39: Open | F39: 0.01 | G39: Williams, Stephen | I39: Team site (no Microsoft 365 group) | J39: 43917 | K39: 43833.447 | L39: Williams, Stephen | M39: 25600 | N39: 0 | O39: FALSE | P39: 0 | Q39: 0 | R39: 0 | S39: 20 | U39: Off | V39: Unplanned
A40: 0001270 - Test Sharepoint Opportunity Site | B40: https://serco.sharepoint.com/sites/Dynamics_Opportunity_Dev0001270 | C40: FALSE | E40: Open | F40: 0.01 | G40: Williams, Stephen | I40: Team site (no Microsoft 365 group) | J40: 43917 | K40: 43837.674 | L40: Williams, Stephen | M40: 25600 | N40: 0 | O40: FALSE | P40: 0 | Q40: 0 | R40: 0 | S40: 20 | U40: Off | V40: Unplanned
A41: 0001271 - test opp opportunity site | B41: https://serco.sharepoint.com/sites/Dynamics_Opportunity_Dev_0001271 | C41: FALSE | E41: Open | F41: 0.01 | G41: Williams, Stephen | I41: Team site (no Microsoft 365 group) | J41: 43917 | K41: 43837.481 | L41: Williams, Stephen | M41: 25600 | N41: 0 | O41: FALSE | P41: 0 | Q41: 0 | R41: 0 | S41: 20 | U41: Off | V41: Unplanned
A42: 0001271 - test opp opportunity site | B42: https://serco.sharepoint.com/sites/Dynamics_Opportunity_Dev_1 | C42: FALSE | E42: Open | F42: 0.01 | G42: Williams, Stephen | I42: Team site (no Microsoft 365 group) | J42: 43917 | K42: 43837.585 | L42: Williams, Stephen | M42: 25600 | N42: 0 | O42: FALSE | P42: 0 | Q42: 0 | R42: 0 | S42: 20 | U42: Off | V42: Unplanned
A43: 0001271 - test opp opportunity site | B43: https://serco.sharepoint.com/sites/Dynamics_Opportunity_Dev_2 | C43: FALSE | E43: Open | F43: 0.01 | G43: Williams, Stephen | I43: Team site (no Microsoft 365 group) | J43: 43917 | K43: 43837.599 | L43: Williams, Stephen | M43: 25600 | N43: 0 | O43: FALSE | P43: 0 | Q43: 0 | R43: 0 | S43: 20 | U43: Off | V43: Unplanned
A44: 0001271 - test opp opportunity site | B44: https://serco.sharepoint.com/sites/Dynamics_Opportunity_Dev_3 | C44: FALSE | E44: Open | F44: 0.01 | G44: Williams, Stephen | I44: Team site (no Microsoft 365 group) | J44: 43917 | K44: 43837.611 | L44: Williams, Stephen | M44: 25600 | N44: 0 | O44: FALSE | P44: 0 | Q44: 0 | R44: 0 | S44: 20 | U44: Off | V44: Unplanned
... A85: 0037132 - Opportunity SharePoint Site Test - 3 Opportunity Site | B85: https://serco.sharepoint.com/sites/Opportunity_UAT_0037132 | C85: FALSE | E85: Open | F85: 0.01 | G85: Williams, Stephen | I85: Team site (no Microsoft 365 group) | J85: 43949 | K85: 43872.44 | L85: Williams, Stephen | M85: 25600 | N85: 0 | O85: FALSE | P85: 0 | Q85: 0 | R85: 0 | S85: 20 | U85: Off | V85: Unplanned
A86: 0051761 WMCA ESOL Alternative Language Provision | B86: https://serco.sharepoint.com/sites/WMCAESOLAlternativeLanguageProvision | C86: TRUE | E86: Open | F86: 0.03 | I86: Team site | J86: 45495 | K86: 45478.532 | L86: WMCA ESOL Alternative Language Provision Owners | M86: 25600 | N86: 0 | O86: TRUE | P86: 0 | Q86: 0 | R86: 0 | S86: 7 | U86: On | V86: Unplanned
A87: 0052142 GMCA Functional Skills Training and Certification (Level 2 - Maths and English) | B87: https://serco.sharepoint.com/sites/GMCAFunctionalSkillsTrainingandCertificationLevel2-MathsandE | C87: TRUE | E87: Open | F87: 0.08 | I87: Team site | J87: 45562 | K87: 45559.622 | L87: GMCA Functional Skills Training and Certification (Level 2 - Maths and English) Owners | M87: 25600 | N87: 0 | O87: TRUE | P87: 0 | Q87: 0 | R87: 0 | S87: 12 | U87: On | V87: Unplanned
A88: 01. LFCP: Lambeth Fortnightly Collections Project | B88: https://serco.sharepoint.com/sites/LambethFortnightlyCollectionsProjectTeam | C88: TRUE | D88: 0 | E88: Open | F88: 34.56 | I88: Team site | J88: 46025 | K88: 45155.526 | L88: Lambeth Fortnightly Collections Project Team Owners | M88: 25600 | N88: 0 | O88: TRUE | P88: 2 | Q88: 0 | R88: 0 | S88: 1828 | U88: On | V88: Unplanned
A89: 03. MFWC: Mid-Sussex Food Waste Collections Project | B89: https://serco.sharepoint.com/sites/MFWCProject | C89: TRUE | E89: Open | F89: 91.86 | I89: Team site | J89: 46049 | K89: 45461.33 | L89: Macani, Erithier | M89: 25600 | N89: 0 | O89: TRUE | P89: 31 | Q89: 165 | R89: 6 | S89: 484 | U89: On | V89: Unplanned
A90: 03.09 SUCCESS plan | B90: https://serco.sharepoint.com/sites/03.09SUCCESSplan | C90: TRUE | E90: Open | F90: 0.01 | I90: Team site | J90: 44575 | K90: 44442.372 | L90: 03.09 SUCCESS plan Owners | M90: 25600 | N90: 0 | O90: TRUE | P90: 0 | Q90: 0 | R90: 0 | S90: 14 | U90: On | V90: Unplanned
A91: 04. BHCR: Basingstoke & Hart Contract Remobilisation Project | B91: https://serco.sharepoint.com/sites/SercoES.BHCRProject | C91: TRUE | E91: Open | F91: 1.81 | I91: Team site | J91: 46048 | K91: 45518.364 | L91: Macani, Erithier | M91: 25600 | N91: 0 | O91: TRUE | P91: 9 | Q91: 2 | R91: 2 | S91: 158 | U91: On | V91: Unplanned
A92: 05S Drafting Team | B92: https://serco.sharepoint.com/sites/05SDraftingTeam | C92: TRUE | E92: Open | F92: 0 | I92: Team site | J92: 45916 | K92: 45908.492 | L92: 05S Drafting Team Owners | M92: 25600 | N92: 0 | O92: TRUE | P92: 0 | Q92: 0 | R92: 0 | S92: 4 | U92: On | V92: Unplanned
A93: 0623-2025 PSI USS FPJ DDG121 | B93: https://serco.sharepoint.com/sites/0623-2025PSIUSSFPJDDG121 | C93: FALSE | E93: Open | F93: 0.1 | I93: Team site | J93: 45954 | K93: 45945.512 | L93: 0623-2025 PSI USS FPJ DDG121 Owners | M93: 25600 | N93: 0 | O93: TRUE | P93: 0 | Q93: 0 | R93: 0 | S93: 11 | U93: On | V93: Unplanned
A94: 0EK19 ATO Workflows | B94: https://serco.sharepoint.com/sites/0EK19ATOWorkflows | C94: FALSE | E94: Open | F94: 0 | I94: Team site | K94: 45770.722 | L94: 0EK19 ATO Workflows Owners | M94: 25600 | N94: 0 | O94: TRUE | P94: 0 | Q94: 0 | R94: 0 | S94: 0 | U94: On | V94: Unplanned
A95: 1_ACP | B95: https://serco.sharepoint.com/sites/1_ACP | C95: FALSE | E95: Open | F95: 0 | I95: Team site | J95: 45947 | K95: 45594.676 | L95: 1_ACP Owners | M95: 25600 | N95: 0 | O95: TRUE | P95: 0 | Q95: 0 | R95: 0 | S95: 6 | U95: On | V95: Unplanned
A96: 10/17 GCIII RTW | B96: https://serco.sharepoint.com/sites/1017GCIIIRTW | C96: FALSE | E96: Open | F96: 0 | I96: Team site | K96: 44846.928 | L96: 10/17 GCIII RTW Owners | M96: 25600 | N96: 0 | O96: TRUE | P96: 0 | Q96: 0 | R96: 0 | S96: 6 | U96: On | V96: Unplanned
A97: 100 Day Assessment | B97: https://serco.sharepoint.com/sites/100DayAssessment | C97: FALSE | E97: Open | F97: 0.01 | I97: Team site | K97: 43999.804 | L97: 100 Day Assessment Owners | M97: 25600 | N97: 0 | O97: TRUE | P97: 0 | Q97: 0 | R97: 0 | S97: 19 | U97: On | V97: Unplanned
A98: 101 Workloads Server Migration | B98: https://serco.sharepoint.com/sites/101On-PREMWorkloadsMigration | C98: TRUE | E98: Open | F98: 0.19 | I98: Team site | J98: 45342 | K98: 44799.639 | L98: 101 On-PREM Workloads Migration Owners | M98: 25600 | N98: 0 | O98: TRUE | P98: 0 | Q98: 0 | R98: 0 | S98: 15 | U98: On | V98: Unplanned
A99: 1040FORMS | B99: https://serco.sharepoint.com/sites/1040FORMS | C99: FALSE | E99: Open | F99: 0.01 | I99: Team site | K99: 44111.882 | L99: Borowski, Olivia (Serco NA) | M99: 25600 | N99: 0 | O99: TRUE | P99: 0 | Q99: 0 | R99: 0 | S99: 18 | U99: On | V99: Unplanned
A100: 108th ADA Coaches | B100: https://serco.sharepoint.com/sites/108thadacoaches | C100: FALSE | E100: Open | F100: 0 | I100: Team site | J100: 46043 | K100: 45698.638 | L100: 108th ADA Coaches Owners | M100: 25600 | N100: 0 | O100: TRUE | P100: 1 | Q100: 1 | R100: 1 | S100: 2 | U100: On | V100: Unplanned
A101: 10thCABH2FSCC | B101: https://serco.sharepoint.com/sites/10thcabh2fscc | C101: FALSE | E101: Open | F101: 0 | I101: Team site | J101: 45695 | K101: 45681.773 | L101: 10thCABH2FSCC Owners | M101: 25600 | N101: 0 | O101: TRUE | P101: 0 | Q101: 0 | R101: 0 | S101: 5 | U101: On | V101: Unplanned
A102: 10thMTNDIVH2F | B102: https://serco.sharepoint.com/sites/10thmtndivh2f | C102: FALSE | E102: Open | F102: 0 | I102: Team site | J102: 45709 | K102: 45680.838 | L102: 10thMTNDIVH2F Owners | M102: 25600 | N102: 0 | O102: TRUE | P102: 0 | Q102: 0 | R102: 0 | S102: 6 | U102: On | V102: Unplanned
A103: 10thMTNDIVLSCC | B103: https://serco.sharepoint.com/sites/10thmtndivlscc | C103: FALSE | E103: Open | F103: 0 | I103: Team site | J103: 45923 | K103: 45680.765 | L103: 10thMTNDIVLSCC Owners | M103: 25600 | N103: 0 | O103: TRUE | P103: 0 | Q103: 0 | R103: 0 | S103: 5 | U103: On | V103: Unplanned
A104: 10thMTNDIVPD | B104: https://serco.sharepoint.com/sites/10thmtndivpd | C104: FALSE | E104: Open | F104: 0 | I104: Team site | K104: 45709.713 | L104: 10thMTNDIVPD Owners | M104: 25600 | N104: 0 | O104: TRUE | P104: 0 | Q104: 0 | R104: 0 | S104: 2 | U104: On | V104: Unplanned
A105: 1100 New Jersey | B105: https://serco.sharepoint.com/sites/1100NewJersey | C105: TRUE | E105: Open | F105: 0.01 | I105: Team site | J105: 44741 | K105: 43924.567 | L105: Jones, Derrick, A (Serco NA US) | M105: 25600 | N105: 0 | O105: TRUE | P105: 0 | Q105: 0 | R105: 0 | S105: 22 | U105: On | V105: Unplanned
A106: 1100 New Jersey Ave - Conference room buildout | B106: https://serco.sharepoint.com/sites/1100NewJerseyAve-Conferenceroombuildout | C106: TRUE | E106: Open | F106: 0.02 | I106: Team site | J106: 45558 | K106: 45476.73 | L106: 1100 New Jersey Ave - Conference room buildout Owners | M106: 25600 | N106: 0 | O106: TRUE | P106: 0 | Q106: 0 | R106: 0 | S106: 7 | U106: On | V106: Unplanned
A107: 119 S2 T4 | B107: https://serco.sharepoint.com/sites/119S2T4 | C107: FALSE | E107: Open | F107: 0 | I107: Team site | K107: 45079.672 | L107: 119 S2 T4 Owners | M107: 25600 | N107: 0 | O107: TRUE | P107: 0 | Q107: 0 | R107: 0 | S107: 6 | U107: On | V107: Unplanned
A108: 12Wing Shearwater | B108: https://serco.sharepoint.com/sites/12WingShearwater | C108: TRUE | E108: Open | F108: 0.05 | I108: Team site | J108: 44718 | K108: 44406.721 | L108: 12Wing Shearwater Owners | M108: 25600 | N108: 0 | O108: TRUE | P108: 0 | Q108: 0 | R108: 0 | S108: 63 | U108: On | V108: Unplanned
A109: 148 3PD | B109: https://serco.sharepoint.com/sites/1483PD | C109: FALSE | E109: Open | F109: 0.09 | I109: Team site | J109: 45496 | K109: 45139.526 | L109: 148 3PD Owners | M109: 25600 | N109: 0 | O109: TRUE | P109: 0 | Q109: 0 | R109: 0 | S109: 154 | U109: On | V109: Unplanned
A110: 148 Bridge Tickets Non-3PD | B110: https://serco.sharepoint.com/sites/148BridgeTicketsNon-3PD | C110: FALSE | E110: Open | F110: 0.01 | I110: Team site | J110: 45463 | K110: 45139.528 | L110: 148 Bridge Tickets Non-3PD Owners | M110: 25600 | N110: 0 | O110: TRUE | P110: 0 | Q110: 0 | R110: 0 | S110: 18 | U110: On | V110: Unplanned
A111: 156 shop | B111: https://serco.sharepoint.com/sites/156shop | C111: TRUE | E111: Open | F111: 0.01 | I111: Team site | J111: 45448 | K111: 44312.621 | L111: 156 shop Owners | M111: 25600 | N111: 0 | O111: TRUE | P111: 0 | Q111: 0 | R111: 0 | S111: 18 | U111: On | V111: Unplanned
A112: 16.08.2021 - UC Telephony Training | B112: https://serco.sharepoint.com/sites/16.08.2021-UCTelephonyTraining | C112: FALSE | E112: Open | F112: 0.01 | I112: Team site | J112: 44439 | K112: 44425.353 | L112: 16.08.2021 - UC Telephony Training Owners | M112: 25600 | N112: 0 | O112: TRUE | P112: 0 | Q112: 0 | R112: 0 | S112: 16 | U112: On | V112: Unplanned
A113: 19 Oct 2018 IOI | B113: https://serco.sharepoint.com/sites/19Oct2018IOI | C113: FALSE | E113: Open | F113: 0.01 | I113: Team site | J113: 43918 | K113: 43385.522 | L113: Griffith, Janet, E (Serco NA) | M113: 25600 | N113: 0 | O113: TRUE | P113: 0 | Q113: 0 | R113: 0 | S113: 31 | U113: On | V113: Unplanned
A114: 1Q2N4 ATO Workflows | B114: https://serco.sharepoint.com/sites/1Q2N4ATOWorkflows | C114: FALSE | E114: Open | F114: 0 | I114: Team site | K114: 45770.724 | L114: 1Q2N4 ATO Workflows Owners | M114: 25600 | N114: 0 | O114: TRUE | P114: 0 | Q114: 0 | R114: 0 | S114: 0 | U114: On | V114: Unplanned
A115: 1SBCT H2F | B115: https://serco.sharepoint.com/sites/1SBCTH2F | C115: TRUE | E115: Open | F115: 0.12 | I115: Team site | J115: 46049 | K115: 46021.811 | L115: 1SBCT H2F Owners | M115: 25600 | N115: 0 | O115: TRUE | P115: 59 | Q115: 37 | R115: 3 | S115: 57 | U115: On | V115: Unplanned
A116: 1st Shift Sun - Thurs | B116: https://serco.sharepoint.com/sites/1stShiftSun-Thurs | C116: FALSE | E116: Open | F116: 0.01 | I116: Team site | J116: 45636 | K116: 43965.934 | L116: Donohue, James, D (Serco NA) | M116: 25600 | N116: 0 | O116: TRUE | P116: 0 | Q116: 0 | R116: 0 | S116: 21 | U116: On | V116: Unplanned
A117: 1st Shift OK Training | B117: https://serco.sharepoint.com/sites/1stShiftOKTraining | C117: TRUE | E117: Open | F117: 0.01 | I117: Team site | J117: 44614 | K117: 43986.594 | L117: 1st Shift OK Training Owners | M117: 25600 | N117: 0 | O117: TRUE | P117: 0 | Q117: 0 | R117: 0 | S117: 24 | U117: On | V117: Unplanned
A118: 1st Shift Tue - Sat | B118: https://serco.sharepoint.com/sites/1stShiftTue-Sat | C118: FALSE | E118: Open | F118: 0.01 | I118: Team site | K118: 43965.942 | L118: Donohue, James, D (Serco NA) | M118: 25600 | N118: 0 | O118: TRUE | P118: 0 | Q118: 0 | R118: 0 | S118: 19 | U118: On | V118: Unplanned
A119: 2 Div | B119: https://serco.sharepoint.com/sites/2Div | C119: TRUE | E119: Open | F119: 0.01 | I119: Team site | K119: 43907.631 | L119: Longo, Ryan, J (Serco NA) | M119: 25600 | N119: 0 | O119: TRUE | P119: 0 | Q119: 0 | R119: 0 | S119: 19 | U119: On | V119: Unplanned
A120: 2 Million Metre Challenge | B120: https://serco.sharepoint.com/sites/2millionmetrechallenge | C120: FALSE | E120: Open | F120: 0.01 | I120: Team site | J120: 45294 | K120: 44006.742 | L120: 2 Million Metre Challenge Owners | M120: 25600 | N120: 0 | O120: TRUE | P120: 0 | Q120: 0 | R120: 0 | S120: 25 | U120: On | V120: Unplanned
A121: 2 stooges | B121: https://serco.sharepoint.com/sites/2stooges | C121: TRUE | E121: Open | F121: 0 | I121: Team site | K121: 44972.626 | L121: 2 stooges Owners | M121: 25600 | N121: 0 | O121: TRUE | P121: 0 | Q121: 0 | R121: 0 | S121: 6 | U121: On | V121: Unplanned
A122: 2.4.15.1 - Rations Use & Quarters Occupancy Report In the plan Contract Deliverables linked to Deliverables > General | B122: https://serco.sharepoint.com/sites/24151-RationsUseQuartersOccupancyReportIntheplanContractDelivera | C122: FALSE | E122: Open | F122: 0.01 | I122: Team site | K122: 44553.443 | L122: 2.4.15.1 - Rations Use & Quarters Occupancy Report In the plan Contract Deliverables linked to Deliverables > General Owners | M122: 25600 | N122: 0 | O122: TRUE | P122: 0 | Q122: 0 | R122: 0 | S122: 10 | U122: On | V122: Unplanned
A123: 2/1 H2F Teams | B123: https://serco.sharepoint.com/sites/21H2FTeams | C123: TRUE | E123: Open | F123: 1.05 | I123: Team site | J123: 46049 | K123: 45922.958 | L123: 2/1 H2F Teams Owners | M123: 25600 | N123: 0 | O123: TRUE | P123: 72 | Q123: 53 | R123: 6 | S123: 76 | U123: On | V123: Unplanned
A124: 2/21/2020-Work-7/30am-6pm | B124: https://serco.sharepoint.com/sites/2212020Work730am6pm | C124: FALSE | E124: Open | F124: 0.01 | I124: Team site | J124: 43917 | K124: 43885.074 | L124: Sanders Sr., Quadry, M (Serco NA) | M124: 25600 | N124: 0 | O124: TRUE | P124: 0 | Q124: 0 | R124: 0 | S124: 20 | U124: On | V124: Unplanned
A125: 20/095 Gas Networks Ireland | B125: https://serco.sharepoint.com/sites/20095GasNetworksIreland | C125: TRUE | E125: Open | F125: 0.07 | I125: Team site | J125: 45337 | K125: 44222.359 | L125: 20/095 Gas Networks Ireland Owners | M125: 25600 | N125: 0 | O125: TRUE | P125: 0 | Q125: 0 | R125: 0 | S125: 66 | U125: On | V125: Unplanned
A126: 200 12th Street Arlington, VA | B126: https://serco.sharepoint.com/sites/20012thStreetArlingtonVA | C126: TRUE | E126: Open | F126: 0.07 | I126: Team site | J126: 45691 | K126: 45461.619 | L126: 200 12th Street Arlington, VA Owners | M126: 25600 | N126: 0 | O126: TRUE | P126: 0 | Q126: 0 | R126: 0 | S126: 81 | U126: On | V126: Unplanned
A127: 2008 server migrations | B127: https://serco.sharepoint.com/sites/2008servermigrations | C127: TRUE | E127: Open | F127: 0.01 | I127: Team site | J127: 45636 | K127: 43902.689 | L127: Weeks, Norman (Serco NA) | M127: 25600 | N127: 0 | O127: TRUE | P127: 0 | Q127: 0 | R127: 0 | S127: 26 | U127: On | V127: Unplanned
A128: 2010FL | B128: https://serco.sharepoint.com/sites/2010FL | C128: FALSE | E128: Open | F128: 0.01 | I128: Team site | K128: 44134.795 | L128: 2010FL Owners | M128: 25600 | N128: 0 | O128: TRUE | P128: 0 | Q128: 0 | R128: 0 | S128: 18 | U128: On | V128: Unplanned
A129: 2013 SharePoint Workflow Rebuilds | B129: https://serco.sharepoint.com/sites/2013SharePointWorkflowRebuilds | C129: TRUE | D129: 1 | E129: Open | F129: 0 | I129: Team site | K129: 44935.876 | L129: 2013 SharePoint Workflow Rebuilds Owners | M129: 25600 | N129: 0 | O129: TRUE | P129: 0 | Q129: 0 | R129: 0 | S129: 16 | U129: On | V129: Unplanned
A130: 2016 Server Compliancy Baseline | B130: https://serco.sharepoint.com/sites/2016ServerCompliancyBaseline | C130: FALSE | E130: Open | F130: 0.01 | I130: Team site | J130: 44124 | K130: 43243.031 | L130: Sosa, Marc (Serco NA US) | M130: 25600 | N130: 0 | O130: TRUE | P130: 0 | Q130: 0 | R130: 0 | S130: 44 | U130: On | V130: Unplanned
A131: 2017 Performance Share Plan Participants Group | B131: https://serco.sharepoint.com/sites/2017performanceshareplanparticipantsgroup | C131: FALSE | E131: Open | F131: 0.01 | I131: Team site | K131: 44006.742 | L131: 2017 Performance Share Plan Participants Group Owners | M131: 25600 | N131: 0 | O131: TRUE | P131: 0 | Q131: 0 | R131: 0 | S131: 22 | U131: On | V131: Unplanned
A132: 2017 yr end performance review | B132: https://serco.sharepoint.com/sites/2017yrendperformancereview | C132: FALSE | E132: Open | F132: 0.01 | I132: Team site | J132: 45621 | K132: 43029.104 | L132: 2017 yr end performance review | M132: 25600 | N132: 0 | O132: TRUE | P132: 0 | Q132: 0 | R132: 0 | S132: 49 | U132: On | V132: Unplanned
A133: 2018 Bolton Compliance | B133: https://serco.sharepoint.com/sites/BoltonCompliance | C133: TRUE | E133: Open | F133: 0.17 | I133: Team site | J133: 45418 | K133: 43368.39 | L133: McCabe, Helen | M133: 25600 | N133: 0 | O133: TRUE | P133: 0 | Q133: 0 | R133: 0 | S133: 839 | U133: On | V133: Unplanned
A134: 2018 South Ribble Compliance | B134: https://serco.sharepoint.com/sites/SouthRibbleCompliance | C134: TRUE | E134: Open | F134: 0.13 | I134: Team site | J134: 44719 | K134: 43369.499 | L134: McCabe, Helen | M134: 25600 | N134: 0 | O134: TRUE | P134: 0 | Q134: 0 | R134: 0 | S134: 604 | U134: On | V134: Unplanned
A135: 2018 West Lancashire Compliance | B135: https://serco.sharepoint.com/sites/WestLancsCompliance | C135: TRUE | E135: Open | F135: 0.06 | I135: Team site | J135: 44813 | K135: 43369.442 | L135: McCabe, Helen | M135: 25600 | N135: 0 | O135: TRUE | P135: 0 | Q135: 0 | R135: 0 | S135: 231 | U135: On | V135: Unplanned
A136: 2018.03 PSSP Transformation | B136: https://serco.sharepoint.com/sites/201803PSSPTransformation | C136: FALSE | E136: Open | F136: 0.01 | I136: Team site | J136: 43917 | K136: 43199.51 | L136: Chris O'Connor | M136: 25600 | N136: 0 | O136: TRUE | P136: 0 | Q136: 0 | R136: 0 | S136: 44 | U136: On | V136: Unplanned
A137: 2019 DCAA Financial System / IT Audit | B137: https://serco.sharepoint.com/sites/2019DCAAFinancialSystemITAudit | C137: TRUE | E137: Open | F137: 0.01 | I137: Team site | J137: 45258 | K137: 43542.842 | L137: Sullivan, Christopher, M (Serco NA US) | M137: 25600 | N137: 0 | O137: TRUE | P137: 0 | Q137: 0 | R137: 0 | S137: 45 | U137: On | V137: Unplanned
A138: 2019 IAR Planning | B138: https://serco.sharepoint.com/sites/2019IARPlanning | C138: TRUE | E138: Open | F138: 0.01 | I138: Team site | J138: 44972 | K138: 43347.582 | L138: Cameron, Graeme | M138: 25600 | N138: 0 | O138: TRUE | P138: 0 | Q138: 0 | R138: 0 | S138: 41 | U138: On | V138: Unplanned
A139: 2019 Leadership Conference videos | B139: https://serco.sharepoint.com/sites/2019LeadershipConferencevideos | C139: TRUE | E139: Open | F139: 1.8 | I139: Team site | J139: 43993 | K139: 43517.552 | L139: Britton, Emma | M139: 25600 | N139: 0 | O139: TRUE | P139: 0 | Q139: 0 | R139: 0 | S139: 39 | U139: On | V139: Unplanned
A140: 2019 Stakeholder Meetings | B140: https://serco.sharepoint.com/sites/2019StakeholderMeetings | C140: TRUE | E140: Open | F140: 0 | I140: Team site | J140: 45413 | K140: 43565.797 | L140: Stow, Jane | M140: 25600 | N140: 0 | O140: TRUE | P140: 0 | Q140: 0 | R140: 0 | S140: 29 | U140: On | V140: Unplanned
...

Sheet REF-OriginalPilotList
A1: URL | B1: Name | C1: Storage(GB) | D1: UPN | E1: Row # | F1: Type | H1: Inheritance | I1: Details | J1: User/group | K1: Principal type | L1: Account name | M1: Given through | N1: Full Control | O1: Design | P1: Contribute | Q1: Edit | R1: Read | S1: Web-Only Limited Access | T1: Serco Admin | U1: Serco Member
A2: https://serco.sharepoint.com/sites/ContractTrainingRequirements | B2: Contract Training Requirements | C2: 2.04 | D2: aaron.rocha@serco-na.com | E2: 68236 | F2: Site collection | H2: Custom | J2: Rocha, Aaron, S (Serco NA US) | K2: User | L2: i:0#.f|membership|aaron.rocha@serco-na.com | M2: 1040FORMS Owners | N2: X
A3: https://serco.sharepoint.com/sites/GSCATFP | B3: GSC AT/FP | C3: 87.38 | D3: aaron.rocha@serco-na.com | E3: 137822 | F3: Site collection | H3: Custom | J3: Rocha, Aaron, S (Serco NA US) | K3: User | L3: i:0#.f|membership|aaron.rocha@serco-na.com | M3: 1st Shift Sun - Thurs Owners | N3: X
A4: https://serco.sharepoint.com/sites/ITServiceDelivery | B4: IT Service Delivery | C4: 0.02 | D4: aaron.rocha@serco-na.com | E4: 161506 | F4: Site collection | H4: Custom | J4: Rocha, Aaron, S (Serco NA US) | K4: User | L4: i:0#.f|membership|aaron.rocha@serco-na.com | M4: 2013 SharePoint Workflow Rebuilds - ETSS - Communications Approval Members, 2013 SharePoint Workflow Rebuilds - ETSS - Communications Approval Owners | N4: X | Q4: X
A5: https://serco.sharepoint.com/sites/DDG51HMESystemsManagement | B5: DDG 51: Task 2 PMS 400 D4 support | C5: 3.36 | D5: abbas.faisal@serco-na.com | E5: 84183 | F5: Site collection | H5: Custom | J5: Faisal, Abbas, A (Serco NA) | K5: User | L5: i:0#.f|membership|abbas.faisal@serco-na.com | M5: 2022 Serco Leadership Conference - Contracts - Procurement Items Members, 2022 Serco Leadership Conference - Contracts - Procurement Items Owners | N5: X | Q5: X
A6: https://serco.sharepoint.com/sites/AdvanceTechnologiesGroup | B6: ATG: Advance Technologies Group | C6: 27.52 | D6: albert.moseley@serco-na.com | E6: 16757 | F6: Site collection | H6: Custom | J6: Moseley, Albert, G (Serco NA US) | K6: User | L6: i:0#.f|membership|albert.moseley@serco-na.com | M6: 2023 Leadership Conference Resource Center Owners, 2023 Leadership Conference Resource Center Visitors | N6: X | R6: X
A7: https://serco.sharepoint.com/sites/NIHNIAID-PM | B7: NIH NIAID-PM | C7: 6.02 | D7: albert.moseley@serco-na.com | E7: 211659 | F7: Site collection | H7: Custom | J7: Moseley, Albert, G (Serco NA US) | K7: User | L7: i:0#.f|membership|albert.moseley@serco-na.com | M7: 2023 Leadership Conference Resource Center Owners | N7: X
A8: https://serco.sharepoint.com/sites/IMCOMCSD-NSS | B8: IMCOM CSD-NSS | C8: 0.3 | D8: alex.garcia@serco-na.com | E8: 155543 | F8: Site collection | H8: Custom | J8: Garcia, Alex, R (Serco NA US) | K8: User | L8: i:0#.f|membership|alex.garcia@serco-na.com | M8: 2025 Summer Deep Sea Associate - Jeopardy Template Members, 2025 Summer Deep Sea Associate - Jeopardy Template Owners | N8: X | Q8: X
A9: https://serco.sharepoint.com/sites/AsBuilt | B9: As Built | C9: 0.14 | D9: alex.rojas@serco-na.com | E9: 15198 | F9: Site collection | H9: Custom | J9: Rojas, Alex, K (Serco NA) | K9: User | L9: i:0#.f|membership|alex.rojas@serco-na.com | M9: 2025 Summer Deep Sea Associate - Jeopardy Template Members, 2025 Summer Deep Sea Associate - Jeopardy Template Owners | N9: X | Q9: X
A10: https://serco.sharepoint.com/sites/SA-US-RiskMgmt-FT | B10: Risk Management | C10: 3.72 | D10: alexander.wagner@serco-na.com | E10: 263601 | F10: Site collection | H10: Custom | J10: Wagner, Alexander (Serco NA US) | K10: User | L10: i:0#.f|membership|alexander.wagner@serco-na.com | M10: 21802.25.0828 - 99994 - Model Opportunity Site (WINS SMS) Owners | N10: X
A11: https://serco.sharepoint.com/sites/AdministrativeProfessionalsofSercoNorthAmerica2 | B11: Administrative Professionals of Serco North America | C11: 0.39 | D11: alexandra.gomez@serco-na.com | E11: 8213 | F11: Site collection | H11: Custom | J11: Gomez, Alexandra, N (Serco NA US) | K11: User | L11: i:0#.f|membership|alexandra.gomez@serco-na.com | M11: 21802.25.0828 - 99994 - Model Opportunity Site (WINS SMS) Owners | N11: X
A12: https://serco.sharepoint.com/sites/SA-US-BCM-CTM | B12: Business Continuity Management | C12: 0.92 | D12: alissa.lucia@serco-na.com | E12: 25735 | F12: Site collection | H12: Custom | J12: Lucia, Alissa, A (Serco NA US) | K12: User | L12: i:0#.f|membership|alissa.lucia@serco-na.com | M12: 21802.25.0828 - 99994 - Model Opportunity Site (WINS SMS) Owners | N12: X
A13: https://serco.sharepoint.com/sites/CorporateSecurity-AnnualSecurityTraining | B13: Corporate Security-Annual Security Training | C13: #N/A | D13: alissa.lucia@serco-na.com | E13: 73939 | F13: Site collection | H13: Custom | J13: Lucia, Alissa, A (Serco NA US) | K13: User | L13: i:0#.f|membership|alissa.lucia@serco-na.com | M13: 21802.25.0828 - 99994 - Model Opportunity Site (WINS SMS) Members, 21802.25.0828 - 99994 - Model Opportunity Site (WINS SMS) Owners | N13: X | Q13: X
A14: https://serco.sharepoint.com/sites/SWIFMANAGEMENTTEAM-LudlowHIPProgramManagementStatus | B14: HARDWARE INTEGRATION PROGRAMS-Ludlow HIP Program Management Status | C14: 102.2 | D14: alissa.lucia@serco-na.com | E14: 140717 | F14: Site collection | H14: Custom | J14: Lucia, Alissa, A (Serco NA US) | K14: User | L14: i:0#.f|membership|alissa.lucia@serco-na.com | M14: 22487 PMS377_317 Task 5 Logistics - Project Management Members, 22487 PMS377_317 Task 5 Logistics - Project Management Owners | N14: X | Q14: X
A15: https://serco.sharepoint.com/sites/SercoDeepSeaAssociateProgram | B15: Serco Deep Sea Associate Program | C15: 1.06 | D15: alyskate.olid@serco-na.com | E15: 291310 | F15: Site collection | H15: Custom | J15: Olid, Kate, B (Serco NA) | K15: User | L15: i:0#.f|membership|alyskate.olid@serco-na.com | M15: 22633.25.0762 - Special Projects and Electronic Systems Engineering Support for Electronic Surveillance Systems (SPECTECH) Members, 22633.25.0762 - Special Projects and Electronic Systems Engineering Support for Electronic Surveillance Systems (SPECTECH) Owners | N15: X | Q15: X
A16: https://serco.sharepoint.com/sites/PerformanceManagement-MeritBonus2021-SI2-HopkinsKevin | B16: Performance Management - Merit & Bonus 2021 - SI2-Hopkins, Kevin | C16: #N/A | D16: amanda.miller@serco-na.com | E16: 231164 | F16: Site collection | H16: Custom | J16: Miller, Amanda, C (Serco NA US) | K16: User | L16: i:0#.f|membership|amanda.miller@serco-na.com | M16: 23066 SDAES - Controlled Info Members, 23066 SDAES - Controlled Info Owners | N16: X | Q16: X
A17: https://serco.sharepoint.com/sites/PerformanceManagement-MeritBonus2021-SI2-SteagallClifford | B17: Performance Management - Merit & Bonus 2021 - SI2-Steagall, Clifford | C17: #N/A | D17: amanda.miller@serco-na.com | E17: 231249 | F17: Site collection | H17: Custom | J17: Miller, Amanda, C (Serco NA US) | K17: User | L17: i:0#.f|membership|amanda.miller@serco-na.com | M17: 23457.25.0724 - DoS VISA Support Services for KCC and NVC Owners | N17: X
A18: https://serco.sharepoint.com/sites/SBMProgramManagementReview-MitchellPortfolio | B18: SBM Program Management Review-McConnell Portfolio | C18: 2.9 | D18: amanda.miller@serco-na.com | E18: 274338 | F18: Site collection | H18: Custom | J18: Miller, Amanda, C (Serco NA US) | K18: User | L18: i:0#.f|membership|amanda.miller@serco-na.com | M18: 24566.1.022.25.0742 - RS3 TO - Next Generation Command and Control (NGC2) Engineering_ Integration_ and Fielding (EIF) (RS3-25-0041) Members, 24566.1.022.25.0742 - RS3 TO - Next Generation Command and Control (NGC2) Engineering_ Integration_ and Fielding (EIF) (RS3-25-0041) Owners | N18: X | Q18: X
A19: https://serco.sharepoint.com/sites/GLB-AA-sercooxf-FT | B19: Serco Oxford Management Programme | C19: 0.73 | D19: amanda.miller@serco-na.com | E19: 332059 | F19: Site collection | H19: Custom | J19: Miller, Amanda, C (Serco NA US) | K19: User | L19: i:0#.f|membership|amanda.miller@serco-na.com | M19: 24566.1.022.25.0742 - RS3 TO - Next Generation Command and Control (NGC2) Engineering_ Integration_ and Fielding (EIF) (RS3-25-0041) Owners | N19: X
A20: https://serco.sharepoint.com/sites/SpaceFence-CPARDraftResponseJune2025 | B20: Space Fence-CPAR Draft Response (June 2025) | C20: 0 | D20: amanda.miller@serco-na.com | E20: 460522 | F20: Site collection | H20: Custom | J20: Miller, Amanda, C (Serco NA US) | K20: User | L20: i:0#.f|membership|amanda.miller@serco-na.com | M20: 27591.25.0729 - Transition Assistance Program for VA VBA Office of Transition and Economic Development (TAP) Owners | N20: X
A21: https://serco.sharepoint.com/sites/FairOaksTransitionOpsHRRecruiting | B21: Fair Oaks Transition Ops/HR/Recruiting | C21: 0 | D21: amie.jordan@serco-na.com | E21: 115421 | F21: Site collection | H21: Custom | J21: Jordan, Amie, N (Serco NA US) | K21: User | L21: i:0#.f|membership|amie.jordan@serco-na.com | M21: 28377.25.0769 - Recompete NAVSEA PEO Team Submarine SHAPM (PMS397 and PMS450) - EWCSS Contract (2026) Owners | N21: X
A22: https://serco.sharepoint.com/sites/SA-US-FRTIB-CTM | B22: FRTIB Operations Center | C22: 0.02 | D22: amie.jordan@serco-na.com | E22: 124538 | F22: Site collection | H22: Custom | J22: Jordan, Amie, N (Serco NA US) | K22: User | L22: i:0#.f|membership|amie.jordan@serco-na.com | M22: 28377.25.0769 - Recompete NAVSEA PEO Team Submarine SHAPM (PMS397 and PMS450) - EWCSS Contract (2026) Owners | N22: X
A23: https://serco.sharepoint.com/sites/ViewpointEngagementSurvey | B23: Viewpoint Engagement Survey | C23: 0.04 | D23: amie.jordan@serco-na.com | E23: 836379 | F23: Site collection | H23: Custom | J23: Jordan, Amie, N (Serco NA US) | K23: User | L23: i:0#.f|membership|amie.jordan@serco-na.com | M23: 28643.25.0766 - PMS 317 PSS_ PM Eng Intgr T&E PD GFE (2026) Owners | N23: X
A24: https://serco.sharepoint.com/sites/ESRI | B24: ESRI | C24: 181.28 | D24: andrian.hanson@serco-na.com | E24: 110776 | F24: Site collection | H24: Custom | J24: Hanson, Andrian (Serco NA US) | K24: User | L24: i:0#.f|membership|andrian.hanson@serco-na.com | M24: 28793.25.0770 - NUWC Code 34 Military Satellite Communications Systems (MILSATCOM)-Follow on Owners | N24: X
A25: https://serco.sharepoint.com/sites/SI2GCCHProjectsite-METSMEO | B25: GCCH Project site-METS MEO | C25: 0.08 | D25: andrian.hanson@serco-na.com | E25: 127297 | F25: Site collection | H25: Custom | J25: Hanson, Andrian (Serco NA US) | K25: User | L25: i:0#.f|membership|andrian.hanson@serco-na.com | M25: 28885.25.0743 - F-35 JPO Directorate of Enterprise Services Acquisition Program Support Services Owners | N25: X
A26: https://serco.sharepoint.com/sites/GMCProject | B26: 'the GMC' | C26: 29.57 | D26: andrian.hanson@serco-na.com | E26: 481681 | F26: Site collection | H26: Custom | J26: Hanson, Andrian (Serco NA US) | K26: User | L26: i:0#.f|membership|andrian.hanson@serco-na.com | M26: 29561.25.0747 - USSF SpOC Ground-Based Electro-Optical Deep Space Surveillance (GEODSS) OMS Owners | N26: X
A27: https://serco.sharepoint.com/sites/MaritimeEngineeringOperation | B27: Maritime Engineering Operation | C27: 0.11 | D27: angelo.mazzenga@serco-na.com | E27: 190000 | F27: Site collection | H27: Custom | J27: Mazzenga, Angelo (Serco NA US) | K27: User | L27: i:0#.f|membership|angelo.mazzenga@serco-na.com | M27: 29780.25.0732 - GSA Public Experience Portfolio C.C. Owners | N27: X
A28: https://serco.sharepoint.com/sites/SSMProgramManagementReview-SkokPortfolio | B28: SSM Program Management Review-Combat Systems Portfolio | C28: 0 | D28: anthony.beckner@serco-na.com | E28: 462163 | F28: Site collection | H28: Custom | J28: Beckner, Anthony, P (Serco NA US) | K28: User | L28: i:0#.f|membership|anthony.beckner@serco-na.com | M28: 30649.25.0757 - AFRL Storm Castle CSFD Owners | N28: X
A29: https://serco.sharepoint.com/sites/SercoWellness | B29: Serco Wellbeing | C29: 3.09 | D29: antoinette.phelps@serco-na.com | E29: 437726 | F29: Site collection | H29: Custom | J29: Phelps, Antoinette (Serco NA US) | K29: User | L29: i:0#.f|membership|antoinette.phelps@serco-na.com | M29: 30923.1.071.25.0772 - GIC Afloat IDIQ – TOID 5203 CVN Class PAC AOR - LOE Owners | N29: X
A30: https://serco.sharepoint.com/sites/GSCATFP-CNRH | B30: GSC AT/FP-CNRH | C30: 87.38 | D30: august.goebel@serco-na.com | E30: 137888 | F30: Site collection | H30: Custom | J30: Goebel, August (Serco NA US) | K30: User | L30: i:0#.f|membership|august.goebel@serco-na.com | M30: 30923.1.075.25.0775 - GIC Afloat IDIQ – TOID 5210 - HAWAII AOR - LOE Owners | N30: X
... A41: https://serco.sharepoint.com/sites/ADNSCANESNetworkEngineering | B41: ADNS/CANES Network Engineering | C41: 0.46 | D41: caitlin.martinez@serco-na.com | E41: 8267 | F41: Site collection | H41: Custom | J41: Martinez, Caitlin (Serco NA US) | K41: User | L41: i:0#.f|membership|caitlin.martinez@serco-na.com | M41: 32636.26.0781 - USCG Physical Access Control Systems (PACS) Owners | N41: X
A42: https://serco.sharepoint.com/sites/CTIIMaterialManagement | B42: CTII Material Management | C42: 10.14 | D42: calvin.brooks@serco-na.com | E42: 78595 | F42: Site collection | H42: Custom | J42: Brooks, Calvin, C (Serco NA US) | K42: User | L42: i:0#.f|membership|calvin.brooks@serco-na.com | M42: 365 Projects - Serco Americas (Andrea Selby) - 2010 Workflow Migration - ETSS Members, 365 Projects - Serco Americas (Andrea Selby) - 2010 Workflow Migration - ETSS Owners | N42: X | Q42: X
A43: https://serco.sharepoint.com/sites/na-epmo | B43: Enterprise Program Management Office | C43: 15.03 | D43: carlos.moreno@serco-na.com | E43: 99208 | F43: Site collection | H43: Custom | J43: Moreno, Carlos (Serco NA US) | K43: User | L43: i:0#.f|membership|carlos.moreno@serco-na.com | M43: 365 Projects - Serco Americas (Andrea Selby) - 2010 Workflow Migration - InfoSec Members, 365 Projects - Serco Americas (Andrea Selby) - 2010 Workflow Migration - InfoSec Owners | N43: X | Q43: X
A44: https://serco.sharepoint.com/sites/CorporateBCMAnnualUpdate | B44: Corporate BCM Annual Update | C44: 3.1 | D44: cassidy.kuzemka@serco-na.com | E44: 71992 | F44: Site collection | H44: Custom | J44: Kuzemka, Cassidy, H (Serco NA US) | K44: User | L44: i:0#.f|membership|cassidy.kuzemka@serco-na.com | M44: 365 Projects - Serco Americas (Andrea Selby) - HR- Employee Recognition - Praise Members, 365 Projects - Serco Americas (Andrea Selby) - HR- Employee Recognition - Praise Owners | N44: X | Q44: X
A45: https://serco.sharepoint.com/sites/QualitativeResearch | B45: Qualitative Research | C45: 23.12 | D45: cassidy.kuzemka@serco-na.com | E45: 257466 | F45: Site collection | H45: Custom | J45: Kuzemka, Cassidy, H (Serco NA US) | K45: User | L45: i:0#.f|membership|cassidy.kuzemka@serco-na.com | M45: 365 Projects - Serco Americas (Andrea Selby) - PM Dashboard Site Members, 365 Projects - Serco Americas (Andrea Selby) - PM Dashboard Site Owners | N45: X | Q45: X
A46: https://serco.sharepoint.com/sites/LCOMFinanceTeam-Fabian | B46: CB Finance Team-Fabian | C46: 0.65 | D46: cathy.bendos@serco-na.com | E46: 29722 | F46: Site collection | H46: Custom | J46: Bendos, Cathy, M (Serco NA US) | K46: User | L46: i:0#.f|membership|cathy.bendos@serco-na.com | M46: 3-D Model Distribution List Owners | N46: X
A47: https://serco.sharepoint.com/sites/LCOMProgramManagementReview-Pituffik | B47: LCOM Program Management Review-Pituffik | C47: 0 | D47: cathy.bendos@serco-na.com | E47: 176416 | F47: Site collection | H47: Custom | J47: Bendos, Cathy, M (Serco NA US) | K47: User | L47: i:0#.f|membership|cathy.bendos@serco-na.com | M47: 3PL Management - FRCSW Orders Members, 3PL Management - FRCSW Orders Owners | N47: X | Q47: X
A48: https://serco.sharepoint.com/sites/LCOMProgramManagementReview-WorthingtonPortfolio | B48: LCOM Program Management Review-Worthington Portfolio | C48: 0 | D48: cathy.bendos@serco-na.com | E48: 176424 | F48: Site collection | H48: Custom | J48: Bendos, Cathy, M (Serco NA US) | K48: User | L48: i:0#.f|membership|cathy.bendos@serco-na.com | M48: 3PL Management - FRCSW Orders Members, 3PL Management - FRCSW Orders Owners | N48: X | Q48: X
A49: https://serco.sharepoint.com/sites/FAMteam | B49: FAM Team | C49: 21.04 | D49: charles.dewar@serco-na.com | E49: 115523 | F49: Site collection | H49: Custom | J49: Dewar, Chuck (CD), A (Serco NA US) | K49: User | L49: i:0#.f|membership|charles.dewar@serco-na.com | M49: 450T Owners | N49: X
A50: https://serco.sharepoint.com/sites/SA-US-NOSC-CT | B50: Navy Operational Support Center | C50: 13.36 | D50: chase.deal@serco-na.com | E50: 208140 | F50: Site collection | H50: Custom | J50: Deal, Chase, P (Serco NA US) | K50: User | L50: i:0#.f|membership|chase.deal@serco-na.com | M50: 4th Canadian Division Meaford Base Operations Owners | N50: X
A51: https://serco.sharepoint.com/sites/CSEC-PolicyandProcedureReview | B51: Corporate Security-Policy and Procedure Review | C51: 4.25 | D51: cheryl.cotsimopoulos@serco-na.com | E51: 73958 | F51: Site collection | H51: Custom | J51: Cotsimopoulos, Cheryl, A (Serco NA US) | K51: User | L51: i:0#.f|membership|cheryl.cotsimopoulos@serco-na.com | M51: 60031 Owners | N51: X
A52: https://serco.sharepoint.com/sites/SAM-US-SAMSecTe-FT | B52: Serco Americas Security Team | C52: 12.23 | D52: cheryl.cotsimopoulos@serco-na.com | E52: 289741 | F52: Site collection | H52: Custom | J52: Cotsimopoulos, Cheryl, A (Serco NA US) | K52: User | L52: i:0#.f|membership|cheryl.cotsimopoulos@serco-na.com | M52: AADS DC Owners | N52: X
A53: https://serco.sharepoint.com/sites/SercoInc.SercoUKSharedServicesSMEEs | B53: Serco Inc. & Serco UK Shared Services SMEEs | C53: 0 | D53: cheryl.cotsimopoulos@serco-na.com | E53: 303998 | F53: Site collection | H53: Custom | J53: Cotsimopoulos, Cheryl, A (Serco NA US) | K53: User | L53: i:0#.f|membership|cheryl.cotsimopoulos@serco-na.com | M53: AADS DC Owners | N53: X
A54: https://serco.sharepoint.com/sites/SercoNAComplianceStatement | B54: Serco NA Compliance Statement | C54: 0.15 | D54: cheryl.cotsimopoulos@serco-na.com | E54: 328846 | F54: Site collection | H54: Custom | J54: Cotsimopoulos, Cheryl, A (Serco NA US) | K54: User | L54: i:0#.f|membership|cheryl.cotsimopoulos@serco-na.com | M54: AADS PCD Owners | N54: X
A55: https://serco.sharepoint.com/sites/TotalRewardsHRSystems-GlobalMobilit | B55: Total Rewards-Global Mobility Program | C55: 25.57 | D55: cheryl.cotsimopoulos@serco-na.com | E55: 485891 | F55: Site collection | H55: Custom | J55: Cotsimopoulos, Cheryl, A (Serco NA US) | K55: User | L55: i:0#.f|membership|cheryl.cotsimopoulos@serco-na.com | M55: AC Rack Deployment Vendor-AC Rack - PUBLIC Members, AC Rack Deployment Vendor-AC Rack - PUBLIC Owners | N55: X | Q55: X
A56: https://serco.sharepoint.com/sites/SI2InServiceEngineering-NUWC-HSIOperations | B56: SI2 Hardware & Software Integration-HSI Hy Operations | C56: 0 | D56: chris.griffin@serco-na.com | E56: 454561 | F56: Site collection | H56: Custom | J56: Griffin, Chris (Serco NA US) | K56: User | L56: i:0#.f|membership|chris.griffin@serco-na.com | M56: AccelerateSerco Owners | N56: X
A57: https://serco.sharepoint.com/sites/SI2InServiceEngineering-HSI-In-ServiceEngineering | B57: SI2 Hardware & Software Integration-HSI In-Service Engineering | C57: 0 | D57: chris.griffin@serco-na.com | E57: 454592 | F57: Site collection | H57: Custom | J57: Griffin, Chris (Serco NA US) | K57: User | L57: i:0#.f|membership|chris.griffin@serco-na.com | M57: Accounting_ Finance & Payroll (Restricted) Owners | N57: X
A58: https://serco.sharepoint.com/sites/SA-PMInsightKC | B58: PM Insight Knowledge Center | C58: 7.26 | D58: cole.alldredge@serco-na.com | E58: 234650 | F58: Site collection | H58: Custom | J58: Alldredge, Cole, S (Serco NA US) | K58: User | L58: i:0#.f|membership|cole.alldredge@serco-na.com | M58: Acquisition Management (AQM) - AUiX Briefing Members, Acquisition Management (AQM) - AUiX Briefing Owners, Limited Access System Group For Web 12de1c4b-324d-4bf7-b50d-16faa79b4850 | N58: X | Q58: X | S58: X
A59: https://serco.sharepoint.com/sites/SSMFinanceTeam-BustosDerek | B59: SSM Finance Team-Bustos, Derek | C59: 3.17 | D59: cole.alldredge@serco-na.com | E59: 462028 | F59: Site collection | H59: Custom | J59: Alldredge, Cole, S (Serco NA US) | K59: User | L59: i:0#.f|membership|cole.alldredge@serco-na.com | M59: AF_SF Market Team - BD Engagement Strategy Members, AF_SF Market Team - BD Engagement Strategy Owners, Limited Access System Group For Web 0f9e8b6f-30bc-4235-ba80-562426d0bb7a | N59: X | Q59: X | S59: X
A60: https://serco.sharepoint.com/sites/SSMFinanceTeam-RobinettRudy | B60: SSM Finance Team-Robinett, Rudy | C60: #N/A | D60: cole.alldredge@serco-na.com | E60: 462081 | F60: Site collection | H60: Custom | J60: Alldredge, Cole, S (Serco NA US) | K60: User | L60: i:0#.f|membership|cole.alldredge@serco-na.com | M60: AF_SF Market Team - BD Engagement Strategy Members, AF_SF Market Team - BD Engagement Strategy Owners | N60: X | Q60: X
A61: https://serco.sharepoint.com/sites/SSMFinanceTeam-SE3ReportingAnalyst | B61: SSM Finance Team-SE3 Reporting | C61: #N/A | D61: cole.alldredge@serco-na.com | E61: 462098 | F61: Site collection | H61: Custom | J61: Alldredge, Cole, S (Serco NA US) | K61: User | L61: i:0#.f|membership|cole.alldredge@serco-na.com | M61: AF_SF Market Team - BD Engagement Strategy Members, AF_SF Market Team - BD Engagement Strategy Owners | N61: X | Q61: X
A62: https://serco.sharepoint.com/sites/SSMProgramManagementReview-SeigenthalerPortfolio | B62: SSM Program Management Review-750 and 760 Portfolio | C62: 0 | D62: cole.alldredge@serco-na.com | E62: 462151 | F62: Site collection | H62: Custom | J62: Alldredge, Cole, S (Serco NA US) | K62: User | L62: i:0#.f|membership|cole.alldredge@serco-na.com | M62: Explicit, AF_SF Market Team - BD Engagement Strategy Members, AF_SF Market Team - BD Engagement Strategy Owners | N62: X | Q62: X
A63: https://serco.sharepoint.com/sites/DONPIOIRMERM | B63: DON PIO IRM & ERM | C63: 5.03 | D63: courtney.kelly@serco-na.com | E63: 93490 | F63: Site collection | H63: Custom | J63: Kelly, Courtney, R (Serco NA US) | K63: User | L63: i:0#.f|membership|courtney.kelly@serco-na.com | M63: AF_SF Market Team-DAF RCO HWW Members, AF_SF Market Team-DAF RCO HWW Owners | N63: X | Q63: X
A64: https://serco.sharepoint.com/sites/PerformanceExcellenceServicesLEADS-ISO45001 | B64: Performance Excellence Services Direct Reports-ISO 45001 | C64: 1.46 | D64: csteagall@serco-na.com | E64: 230033 | F64: Site collection | H64: Custom | J64: Steagall, Clifford (Serco NA US) | K64: User | L64: i:0#.f|membership|csteagall@serco-na.com | M64: AF_SF Market Team - Market Team Members, AF_SF Market Team - Market Team Owners | N64: X | Q64: X
A65: https://serco.sharepoint.com/sites/QAScheduling | B65: QA Surveillance Count | C65: 0.03 | D65: csteagall@serco-na.com | E65: 256856 | F65: Site collection | H65: Custom | J65: Steagall, Clifford (Serco NA US) | K65: User | L65: i:0#.f|membership|csteagall@serco-na.com | M65: AF_SF Market Team - Market Team Members, AF_SF Market Team - Market Team Owners | N65: X | Q65: X
A66: https://serco.sharepoint.com/sites/ProposalCenter228-TEAM | B66: Proposal Center-TEAM | C66: 42.21 | D66: cvargas@serco-na.com | E66: 245266 | F66: Site collection | H66: Custom | J66: Vargas, Cesar (Serco NA US) | K66: User | L66: i:0#.f|membership|cvargas@serco-na.com | M66: AF_SF Market Team - Market Team Members, AF_SF Market Team - Market Team Owners | N66: X | Q66: X
A67: https://serco.sharepoint.com/sites/LSM | B67: LSM | C67: 0.05 | D67: cynthia.hartmann@serco-na.com | E67: 187666 | F67: Site collection | H67: Custom | J67: Hartmann, Cindy, C (Serco NA US) | K67: User | L67: i:0#.f|membership|cynthia.hartmann@serco-na.com | M67: AF_SF Market Team - Market Team Members, AF_SF Market Team - Market Team Owners, Limited Access System Group For Web 035be6b8-5bb5-4830-aefc-88640fcae4d2 | N67: X | Q67: X | S67: X
A68: https://serco.sharepoint.com/sites/MBSETeam | B68: MBSE Team | C68: 2.45 | D68: cynthia.hartmann@serco-na.com | E68: 193706 | F68: Site collection | H68: Custom | J68: Hartmann, Cindy, C (Serco NA US) | K68: User | L68: i:0#.f|membership|cynthia.hartmann@serco-na.com | M68: AF_SF Market Team - Market Team Members, AF_SF Market Team - Market Team Owners, Limited Access System Group For Web 035be6b8-5bb5-4830-aefc-88640fcae4d2 | N68: X | Q68: X | S68: X
A69: https://serco.sharepoint.com/sites/HSI-LUDLOWOPERATIONS-MATTANDSHAWNEE | B69: HSI - LUDLOW OPERATIONS-MATT AND SHAWNEE | C69: 6.25 | D69: cynthiadawn.tec@serco-na.com | E69: 152297 | F69: Site collection | H69: Custom | J69: Tec, Cynthia Dawn (Serco NA US) | K69: User | L69: i:0#.f|membership|cynthiadawn.tec@serco-na.com | M69: AF_SF Market Team - Market Team Members, AF_SF Market Team - Market Team Owners | N69: X | Q69: X
A70: https://serco.sharepoint.com/sites/SI2BDGroup-PipelinePulls | B70: SI2 BD Group-Pipeline Pulls | C70: 38.36 | D70: dainee.locsin@serco-na.com | E70: 454315 | F70: Site collection | H70: Custom | J70: Locsin, Dainee (Serco NA US) | K70: User | L70: i:0#.f|membership|dainee.locsin@serco-na.com | M70: Acquisition Management (AQM) - Proposals Members, Acquisition Management (AQM) - Proposals Owners | N70: X | Q70: X
A71: https://serco.sharepoint.com/sites/SI2BDGroup-Prop-CaptureProposalSupport | B71: SI2 BD Group-Prop-Capture Corporate Support | C71: #N/A | D71: dainee.locsin@serco-na.com | E71: 454324 | F71: Site collection | H71: Custom | J71: Locsin, Dainee (Serco NA US) | K71: User | L71: i:0#.f|membership|dainee.locsin@serco-na.com | M71: Acquisition Management (AQM) - Proposals Members, Acquisition Management (AQM) - Proposals Owners | N71: X | Q71: X
A72: https://serco.sharepoint.com/sites/SI2ProgramManagementReview | B72: HSI Program Management Review | C72: 0 | D72: dana.andersen@serco-na.com | E72: 152428 | F72: Site collection | H72: Custom | J72: Andersen, Dana, J (Serco NA US) | K72: User | L72: i:0#.f|membership|dana.andersen@serco-na.com | M72: Acquisition Management (AQM) - RS3 PM PNT PSS VP 31231 Members, Acquisition Management (AQM) - RS3 PM PNT PSS VP 31231 Owners | N72: X | Q72: X
A73: https://serco.sharepoint.com/sites/SA-TECH-ApplicationServices-MG-PMInsight | B73: SA-TECH-Application Services-MG-PM Insight | C73: #N/A | D73: dana.andersen@serco-na.com | E73: 271882 | F73: Site collection | H73: Custom | J73: Andersen, Dana, J (Serco NA US) | K73: User | L73: i:0#.f|membership|dana.andersen@serco-na.com | M73: Acquisition Management (AQM) - Storm Castle Members, Acquisition Management (AQM) - Storm Castle Owners | N73: X | Q73: X
A74: https://serco.sharepoint.com/sites/SA-TECH-ApplicationServices-MG-ReorgFeb2025 | B74: SA-TECH-Application Services-MG-Reorg Feb 2025 | C74: #N/A | D74: dana.andersen@serco-na.com | E74: 271952 | F74: Site collection | H74: Custom | J74: Andersen, Dana, J (Serco NA US) | K74: User | L74: i:0#.f|membership|dana.andersen@serco-na.com | M74: Acquisition Management (AQM) - Storm Castle Members, Acquisition Management (AQM) - Storm Castle Owners | N74: X | Q74: X
A75: https://serco.sharepoint.com/sites/AppEngineProjects | B75: ServiceNow App Engine Projects | C75: 1.8 | D75: dana.andersen@serco-na.com | E75: 444189 | F75: Site collection | H75: Custom | J75: Andersen, Dana, J (Serco NA US) | K75: User | L75: i:0#.f|membership|dana.andersen@serco-na.com | M75: Acquisition Management (AQM) - Storm Castle Members, Acquisition Management (AQM) - Storm Castle Owners | N75: X | Q75: X
A76: https://serco.sharepoint.com/sites/SI2ContractsTeam960 | B76: SI2 & ICS Contracts Team | C76: 0.22 | D76: dana.andersen@serco-na.com | E76: 454076 | F76: Site collection | H76: Custom | J76: Andersen, Dana, J (Serco NA US) | K76: User | L76: i:0#.f|membership|dana.andersen@serco-na.com | M76: Acquisition Management (AQM) - Storm Castle Members, Acquisition Management (AQM) - Storm Castle Owners | N76: X | Q76: X
A77: https://serco.sharepoint.com/sites/SI2Finance-C4ISRSecuritySolutions | B77: SI2 Finance-C4ISR Security Solutions | C77: #N/A | D77: dana.andersen@serco-na.com | E77: 454482 | F77: Site collection | H77: Custom | J77: Andersen, Dana, J (Serco NA US) | K77: User | L77: i:0#.f|membership|dana.andersen@serco-na.com | M77: Acquisition Management (AQM) - Storm Castle Members, Acquisition Management (AQM) - Storm Castle Owners | N77: X | Q77: X
A78: https://serco.sharepoint.com/sites/Theo2.0-FinanceandTax | B78: Theo 2.0-Finance and Tax | C78: 17.14 | D78: dana.andersen@serco-na.com | E78: 482774 | F78: Site collection | H78: Custom | J78: Andersen, Dana, J (Serco NA US) | K78: User | L78: i:0#.f|membership|dana.andersen@serco-na.com | M78: Acquisition Management (AQM) - Storm Castle Members, Acquisition Management (AQM) - Storm Castle Owners | N78: X | Q78: X
A79: https://serco.sharepoint.com/sites/MeetSerco | B79: Transition Hub | C79: 4.33 | D79: dana.andersen@serco-na.com | E79: 487665 | F79: Site collection | H79: Custom | J79: Andersen, Dana, J (Serco NA US) | K79: User | L79: i:0#.f|membership|dana.andersen@serco-na.com | M79: Acquisition Management (AQM) - Storm Castle Members, Acquisition Management (AQM) - Storm Castle Owners | N79: X | Q79: X
A80: https://serco.sharepoint.com/sites/EHSTrainingModuleTeam | B80: EHS Training Module Team | C80: 0.1 | D80: daniel.beiler@serco-na.com | E80: 95784 | F80: Site collection | H80: Custom | J80: Beiler, Daniel, S (Serco NA US) | K80: User | L80: i:0#.f|membership|daniel.beiler@serco-na.com | M80: Acquisition Management (AQM) - Storm Castle Members, Acquisition Management (AQM) - Storm Castle Owners | N80: X | Q80: X
A81: https://serco.sharepoint.com/sites/DonationsandCharitableContributions | B81: Donations and Charitable Contributions | C81: 0.46 | D81: danielle.thompson@serco-na.com | E81: 93539 | F81: Site collection | H81: Custom | J81: Thompson, Danielle, L (Serco NA US) | K81: User | L81: i:0#.f|membership|danielle.thompson@serco-na.com | M81: ADO CCA PS-BCA - 0. Admin Members, ADO CCA PS-BCA - 0. Admin Owners | N81: X | Q81: X
A82: https://serco.sharepoint.com/sites/AgileImpactSupporttoSEA04XIPTDEventsandCoachingInitiatives | B82: Agile Impact Support to SEA 04X IPTD Events and Coaching Initiatives | C82: 1.81 | D82: gary.humes@serco-na.com | E82: 8820 | F82: Site collection | H82: Custom | J82: Humes, Gary, A (Serco NA US) | K82: User | L82: i:0#.f|membership|gary.humes@serco-na.com | M82: DL2-CMS-IT-Appian - Developers Members, DL2-CMS-IT-Appian - Developers Owners | N82: X | P82: X | Q82: X
A83: https://serco.sharepoint.com/sites/N81WMineCounterMeasures30238.TO9 | B83: N81W Mine Counter Measures 30238.TO9 | C83: 2.52 | D83: gary.humes@serco-na.com | E83: 206843 | F83: Site collection | H83: Custom | J83: Humes, Gary, A (Serco NA US) | K83: User | L83: i:0#.f|membership|gary.humes@serco-na.com | M83: DL2-CMS-IT-Appian - Developers Members, DL2-CMS-IT-Appian - Developers Owners | N83: X | P83: X | Q83: X
A84: https://serco.sharepoint.com/sites/MOSPursuit | B84: MOS | C84: 0.11 | D84: george.sanderlin@serco-na.com | E84: 200914 | F84: Site collection | H84: Custom | J84: Sanderlin, George (Serco NA US) | K84: User | L84: i:0#.f|membership|george.sanderlin@serco-na.com | M84: Application Management (Sandbox) Communication Owners | N84: X
A85: https://serco.sharepoint.com/sites/CoachingMentoringandEngagement | B85: SI2 Travel & Events | C85: 0.15 | D85: gskok@serco-na.com | E85: 454874 | F85: Site collection | H85: Custom | J85: Skok, Greg, J (Serco NA US) | K85: User | L85: i:0#.f|membership|gskok@serco-na.com | M85: Army GV DSRs Owners | N85: X
A86: https://serco.sharepoint.com/sites/SAM-US-VXV2I-CT | B86: Voice Video and Virtual Infrastructure | C86: 1.9 | D86: jeanne.paton@serco-na.com | E86: 837486 | F86: Site collection | H86: Custom | J86: Paton, Jeanne, L (Serco NA US) | K86: User | L86: i:0#.f|membership|jeanne.paton@serco-na.com | M86: ATG_ Advance Technologies Group - Digital Transformation Members, ATG_ Advance Technologies Group - Digital Transformation Owners | N86: X | Q86: X
A87: https://serco.sharepoint.com/sites/METSAhoyAugust2023 | B87: METS Ahoy! August 2023 | C87: 0.03 | D87: jeffrey.kendrick@serco-na.com | E87: 196194 | F87: Site collection | H87: Custom | J87: Kendrick, Jeffrey, D (Serco NA US) | K87: User | L87: i:0#.f|membership|jeffrey.kendrick@serco-na.com | M87: ATG_ Advance Technologies Group - Digital Transformation Members, ATG_ Advance Technologies Group - Digital Transformation Owners | N87: X | Q87: X
A88: https://serco.sharepoint.com/sites/SercoNAVSEA04X | B88: Serco NAVSEA 04X | C88: 2.99 | D88: jeffrey.kendrick@serco-na.com | E88: 331536 | F88: Site collection | H88: Custom | J88: Kendrick, Jeffrey, D (Serco NA US) | K88: User | L88: i:0#.f|membership|jeffrey.kendrick@serco-na.com | M88: ATG_ Advance Technologies Group - Digital Transformation Members, ATG_ Advance Technologies Group - Digital Transformation Owners | N88: X | Q88: X
A89: https://serco.sharepoint.com/sites/SA-GE-WINS-US-28643-MG | B89: 28643.25.0766 - PMS 317 PSS: PM Eng Intgr T&E PD GFE (2026) | C89: 0 | D89: jeffrey.white@serco-na.com | E89: 3496 | F89: Site collection | H89: Custom | J89: White, Jeffrey, B (Serco NA) | K89: User | L89: i:0#.f|membership|jeffrey.white@serco-na.com | M89: ATG_ Advance Technologies Group - Digital Transformation Members, ATG_ Advance Technologies Group - Digital Transformation Owners | N89: X | Q89: X
A90: https://serco.sharepoint.com/sites/PerformanceManagement-MeritBonus2021-Fortune-WhiteJeffrey | B90: Performance Management - Merit & Bonus 2021 - METS-White, Jeffrey | C90: #N/A | D90: jeffrey.white@serco-na.com | E90: 230946 | F90: Site collection | H90: Custom | J90: White, Jeffrey, B (Serco NA) | K90: User | L90: i:0#.f|membership|jeffrey.white@serco-na.com | M90: ATG_ Advance Technologies Group - Digital Transformation Members, ATG_ Advance Technologies Group - Digital Transformation Owners | N90: X | Q90: X
A91: https://serco.sharepoint.com/sites/SAM-US-SCCJ-CT | B91: Sector Command Center-Joint | C91: 33.92 | D91: jena.cloney@serco-na.com | E91: 277601 | F91: Site collection | H91: Custom | J91: Cloney, Jena, A (Serco NA US) | K91: User | L91: i:0#.f|membership|jena.cloney@serco-na.com | M91: ATG_ Advance Technologies Group - Digital Transformation Members, ATG_ Advance Technologies Group - Digital Transformation Owners | N91: X | Q91: X
A92: https://serco.sharepoint.com/sites/OnSitePMS515ContractorGroup-Managers | B92: FFG Task 4 Support Team - Production, QA, Risk, Estimating-Managers | C92: 30.37 | D92: jennifer.cheney@serco-na.com | E92: 117094 | F92: Site collection | H92: Custom | J92: Cheney, Jennifer, L (Serco NA US) | K92: User | L92: i:0#.f|membership|jennifer.cheney@serco-na.com | M92: ATG_ Advance Technologies Group-ATG Technology Roadmap Members, ATG_ Advance Technologies Group-ATG Technology Roadmap Owners, Limited Access System Group For List 9787f119-7f73-40c8-9b2e-61b347ebf550, Limited Access System Group For Web 83fefe98-a69e-4c7b-a04a-49eab905ad10 | N92: X | Q92: X | S92: X
A93: https://serco.sharepoint.com/sites/HSI-LUDLOWOPERATIONS-ShawneeandFinance | B93: HSI - LUDLOW OPERATIONS-Shawnee and Finance | C93: #N/A | D93: jennifer.manoff@serco-na.com | E93: 152375 | F93: Site collection | H93: Custom | J93: Manoff, Jen, E (Serco NA US) | K93: User | L93: i:0#.f|membership|jennifer.manoff@serco-na.com | M93: ATG_ Advance Technologies Group-ATG Technology Roadmap Members, ATG_ Advance Technologies Group-ATG Technology Roadmap Owners, Limited Access System Group, Limited Access System Group For List 9787f119-7f73-40c8-9b2e-61b347ebf550, Limited Access System Group For Web 83fefe98-a69e-4c7b-a04a-49eab905ad10 | N93: X | Q93: X | S93: X
A94: https://serco.sharepoint.com/sites/LCSSRDs | B94: LCS SRDs | C94: 0.01 | D94: jim.horn@serco-na.com | E94: 176467 | F94: Site collection | H94: Custom | J94: Horn, Jim (Serco NA US) | K94: User | L94: i:0#.f|membership|jim.horn@serco-na.com | M94: Aviation Knowledge Sharing Network Functional Team Management, Aviation Knowledge Sharing Network Ops Mgr, Aviation Knowledge Sharing Network Owners, Serco Data Custodians, Serco Members, Serco Site Admins | N94: X | Q94: X | S94: X | T94: X | U94: X
A95: https://serco.sharepoint.com/sites/ProgramManagementOperationalExcellence | B95: Program Management & Operational Excellence | C95: 0.44 | D95: jmorrison@serco-na.com | E95: 241316 | F95: Site collection | H95: Custom | J95: Morrison, John, E (Serco NA US) | K95: User | L95: i:0#.f|membership|jmorrison@serco-na.com | M95: Aviation Knowledge Sharing Network Functional Team Management, Aviation Knowledge Sharing Network Ops Mgr, Aviation Knowledge Sharing Network Owners, Aviation Knowledge Sharing Network Training, Serco Data Custodians, Serco Members, Serco Site Admins | N95: X | P95: X | Q95: X | R95: X | S95: X | T95: X | U95: X
A96: https://serco.sharepoint.com/sites/BuyersandOC | B96: Buyers and OC | C96: 0.01 | D96: john.dye@serco-na.com | E96: 26308 | F96: Site collection | H96: Custom | J96: Dye, Johnny (Serco NA US) | K96: User | L96: i:0#.f|membership|john.dye@serco-na.com | M96: Aviation Knowledge Sharing Network Functional Team Management, Aviation Knowledge Sharing Network Ops Mgr, Aviation Knowledge Sharing Network Owners, Aviation Knowledge Sharing Network Training, Serco Data Custodians, Serco Members, Serco Site Admins | N96: X | P96: X | Q96: X | R96: X | T96: X | U96: X
A97: https://serco.sharepoint.com/sites/LogisticsPMs | B97: Logistics PMs | C97: 0.01 | D97: john.dye@serco-na.com | E97: 184883 | F97: Site collection | H97: Custom | J97: Dye, Johnny (Serco NA US) | K97: User | L97: i:0#.f|membership|john.dye@serco-na.com | M97: Aviation Knowledge Sharing Network Functional Team Management, Aviation Knowledge Sharing Network Ops Mgr, Aviation Knowledge Sharing Network Owners, Aviation Knowledge Sharing Network Training | N97: X | P97: X | Q97: X | R97: X
A98: https://serco.sharepoint.com/sites/NFL-Internal | B98: NFL - Internal | C98: 2.02 | D98: john.dye@serco-na.com | E98: 210496 | F98: Site collection | H98: Custom | J98: Dye, Johnny (Serco NA US) | K98: User | L98: i:0#.f|membership|john.dye@serco-na.com | M98: Aviation Knowledge Sharing Network Functional Team Management, Aviation Knowledge Sharing Network Ops Mgr, Aviation Knowledge Sharing Network Owners, Aviation Knowledge Sharing Network Training | N98: X | P98: X | Q98: X | R98: X
A99: https://serco.sharepoint.com/sites/SercoDLACMS-ProjectLevels | B99: Serco DLA CMS-Levels Discussion | C99: 0.85 | D99: john.dye@serco-na.com | E99: 291436 | F99: Site collection | H99: Custom | J99: Dye, Johnny (Serco NA US) | K99: User | L99: i:0#.f|membership|john.dye@serco-na.com | M99: Aviation Knowledge Sharing Network Functional Team Management, Aviation Knowledge Sharing Network Ops Mgr, Aviation Knowledge Sharing Network Owners | N99: X | P99: X | Q99: X
A100: https://serco.sharepoint.com/sites/SercoDLACMS-CDRLSandAPLS | B100: Serco DLA CMS-OLD - CDRLS and APLS | C100: #N/A | D100: john.dye@serco-na.com | E100: 291449 | F100: Site collection | H100: Custom | J100: Dye, Johnny (Serco NA US) | K100: User | L100: i:0#.f|membership|john.dye@serco-na.com | M100: Aviation Knowledge Sharing Network Functional Team Management, Aviation Knowledge Sharing Network Ops Mgr, Aviation Knowledge Sharing Network Owners, Aviation Knowledge Sharing Network Training | N100: X | P100: X | Q100: X | R100: X
A101: https://serco.sharepoint.com/sites/SA-US-PATACIV-MTM | B101: Serco FEMA PA TAC IV | C101: 0.03 | D101: john.dye@serco-na.com | E101: 293154 | F101: Site collection | H101: Custom | J101: Dye, Johnny (Serco NA US) | K101: User | L101: i:0#.f|membership|john.dye@serco-na.com | M101: Aviation Knowledge Sharing Network Functional Team Management, Aviation Knowledge Sharing Network Ops Mgr, Aviation Knowledge Sharing Network Owners | N101: X | P101: X | Q101: X
A102: https://serco.sharepoint.com/sites/HSLFSSDesignReviewProgram | B102: HSL FSS Design Review Program | C102: 0.16 | D102: john.fleming@serco-na.com | E102: 152547 | F102: Site collection | H102: Custom | J102: Fleming, John, A (Serco NA US) | K102: User | L102: i:0#.f|membership|john.fleming@serco-na.com | M102: Aviation Knowledge Sharing Network Functional Team Management, Aviation Knowledge Sharing Network Ops Mgr, Aviation Knowledge Sharing Network Owners | N102: X | P102: X | Q102: X
A103: https://serco.sharepoint.com/sites/PMS397OnboardingTeam | B103: PMS397 Onboarding Team | C103: 0.12 | D103: john.kargas@serco-na.com | E103: 236202 | F103: Site collection | H103: Custom | J103: Kargas, Chris , C (Serco NA US) | K103: User | L103: i:0#.f|membership|john.kargas@serco-na.com | M103: Aviation Knowledge Sharing Network Functional Team Management, Aviation Knowledge Sharing Network Ops Mgr, Aviation Knowledge Sharing Network Owners, Aviation Knowledge Sharing Network Training | N103: X | P103: X | Q103: X | R103: X
A104: https://serco.sharepoint.com/sites/ALaMO | B104: ALaMO | C104: 0.01 | D104: john.melting@serco-na.com | E104: 9751 | F104: Site collection | H104: Custom | J104: Melting, John, L (Serco NA US) | K104: User | L104: i:0#.f|membership|john.melting@serco-na.com | M104: Aviation Knowledge Sharing Network Functional Team Management, Aviation Knowledge Sharing Network Ops Mgr, Aviation Knowledge Sharing Network Owners, Aviation Knowledge Sharing Network Training | N104: X | P104: X | Q104: X | R104: X | S104: X
A105: https://serco.sharepoint.com/sites/ILCBMProposal | B105: CD&I LCE ID CBM+ Proposal | C105: 0.1 | D105: john.robusto@serco-na.com | E105: 30144 | F105: Site collection | H105: Custom | J105: Robusto, John, A (Serco NA US) | K105: User | L105: i:0#.f|membership|john.robusto@serco-na.com | M105: Aviation Knowledge Sharing Network Functional Team Management, Aviation Knowledge Sharing Network Ops Mgr, Aviation Knowledge Sharing Network Owners | N105: X | P105: X | Q105: X | S105: X
A106: https://serco.sharepoint.com/sites/Serco-WBB-CMA | B106: Serco-WBB - CMA | C106: 24.62 | D106: john.robusto@serco-na.com | E106: 441799 | F106: Site collection | H106: Custom | J106: Robusto, John, A (Serco NA US) | K106: User | L106: i:0#.f|membership|john.robusto@serco-na.com | M106: Aviation Knowledge Sharing Network Functional Team Management, Aviation Knowledge Sharing Network Ops Mgr, Aviation Knowledge Sharing Network Owners | N106: X | P106: X | Q106: X
A107: https://serco.sharepoint.com/sites/Serco-WBBDOD-Comp | B107: Serco-WBB DOD-Comp | C107: 3.61 | D107: john.robusto@serco-na.com | E107: 441913 | F107: Site collection | H107: Custom | J107: Robusto, John, A (Serco NA US) | K107: User | L107: i:0#.f|membership|john.robusto@serco-na.com | M107: Aviation Knowledge Sharing Network Functional Team Management, Aviation Knowledge Sharing Network Ops Mgr, Aviation Knowledge Sharing Network Owners, Aviation Knowledge Sharing Network Training, Serco Data Custodians, Serco Members, Serco Site Admins | N107: X | P107: X | Q107: X | R107: X | T107: X | U107: X
A108: https://serco.sharepoint.com/sites/TotalRewardsHRSystems-Benefits | B108: Total Rewards-Benefits | C108: 25.57 | D108: john.robusto@serco-na.com | E108: 485759 | F108: Site collection | H108: Custom | J108: Robusto, John, A (Serco NA US) | K108: User | L108: i:0#.f|membership|john.robusto@serco-na.com | M108: Aviation Knowledge Sharing Network Functional Team Management, Aviation Knowledge Sharing Network Ops Mgr, Aviation Knowledge Sharing Network Owners | N108: X | P108: X | Q108: X
A109: https://serco.sharepoint.com/sites/SERCO-PHNSY-PHNSYIPTDMANAGEMENT | B109: SERCO - PHNSY-PHNSY IPTD MANAGEMENT | C109: 6.34 | D109: jordan.mossman@serco-na.com | E109: 278729 | F109: Site collection | H109: Custom | J109: Mossman, Po'okela, B (Serco NA US) | K109: User | L109: i:0#.f|membership|jordan.mossman@serco-na.com | M109: Aviation Knowledge Sharing Network Functional Team Management, Aviation Knowledge Sharing Network Ops Mgr, Aviation Knowledge Sharing Network Owners, Aviation Knowledge Sharing Network Training, Serco Data Custodians, Serco Members, Serco Site Admins | N109: X | P109: X | Q109: X | R109: X | T109: X | U109: X
A110: https://serco.sharepoint.com/sites/METS_NASAS | B110: METS_NASAS | C110: 0.01 | D110: joshua.blower@serco-na.com | E110: 196638 | F110: Site collection | H110: Custom | J110: Blower, Joshua (Serco NA US) | K110: User | L110: i:0#.f|membership|joshua.blower@serco-na.com | M110: Aviation Knowledge Sharing Network Functional Team Management, Aviation Knowledge Sharing Network Ops Mgr, Aviation Knowledge Sharing Network Owners | N110: X | P110: X | Q110: X
...
