Workbook

Sheet Agile1BSites
A1: SITE Name | B1: SITE URL (MAIN) | C1: TARGET URL | D1: SITE OWNERS - EMAIL | E1: BU | F1: Portfolio | G1: Wave | H1: Action | I1: Wave 1B Status | J1: Site Exist in GCCH?
A2: AAAA | B2: https://serco.sharepoint.com/sites/aaaa | C2: https://serconagcch.sharepoint.us/sites/aaaa | D2: Michael.J.Harris@serco-na.com | E2: Corporate Services | F2: Technology | G2: Wave 1B | H2: Migrate | I2: Sync Started
A3: AAAAPlanning | B3: https://serco.sharepoint.com/sites/aaaaplanning | C3: https://serconagcch.sharepoint.us/sites/aaaaplanning | D3: Michael.J.Harris@serco-na.com | E3: Corporate Services | F3: Technology | G3: Wave 1B | H3: Migrate | I3: Sync Started
A4: Acquisition Management (AQM) | B4: https://serco.sharepoint.com/sites/AFSFMarketTeam | D4: Raymond.Wier@serco-na.com | E4: Corporate Services | F4: Technology | G4: Wave 1B | H4: Migrate | I4: ShareGate - connected | J4: https://gov.teams.microsoft.us/l/team/19%3Agcch%3Af9f705e178ae4d588e8f42e0406241f8%40thread.tacv2/conversations?groupId=d95aa34f-d2f3-4d7e-a0ab-ed6d7d8c8d22&tenantId=fb1f5cc5-be84-4881-b037-2d641aea97fd
A5: Acquisition Management (AQM)-AUiX | B5: https://serco.sharepoint.com/sites/AFSFMarketTeam-AUiXBriefing | D5: Raymond.Wier@serco-na.com | E5: Corporate Services | F5: Technology | G5: Wave 1B | H5: Migrate | I5: See above - connected
A6: Acquisition Management (AQM)-RS3 PM PNT PSS VP 31231 | B6: https://serco.sharepoint.com/sites/AFSFMarketTeam-RS3PMPNTPSSVP31231 | D6: Raymond.Wier@serco-na.com | E6: Corporate Services | F6: Technology | G6: Wave 1B | H6: Migrate | I6: See above - connected
A7: Acquisition Management (AQM)-Training | B7: https://serco.sharepoint.com/sites/AFSFMarketTeam-Training | D7: Raymond.Wier@serco-na.com | E7: Corporate Services | F7: Technology | G7: Wave 1B | H7: Migrate | I7: See above - connected
A8: Acquisition Management (AQM)-USSF Training | B8: https://serco.sharepoint.com/sites/AFSFMarketTeam-USSFTraining | D8: Raymond.Wier@serco-na.com | E8: Corporate Services | F8: Technology | G8: Wave 1B | H8: Migrate | I8: See above - connected
A9: WRO Team | B9: https://serco.sharepoint.com/sites/AFWROSpecialProjects | C9: https://serconagcch.sharepoint.us/sites/AFWROSpecialProjects | D9: Raymond.Wier@serco-na.com | E9: Corporate Services | F9: Technology | G9: Wave 1B | H9: Migrate | I9: Sync Started-connected
A10: WRO Team-HBG Special Projects 2 | B10: https://serco.sharepoint.com/sites/AFWROSpecialProjects-HBGSpecialProjects2 | C10: https://serconagcch.sharepoint.us/sites/AFWROSpecialProjects | I10: Sync Started-connected
A11: WRO Team-37025 programmatics | B11: https://serco.sharepoint.com/sites/AFWROSpecialProjects-programatics | C11: https://serconagcch.sharepoint.us/sites/AFWROSpecialProjects | D11: James.Mathis@serco-na.com | E11: Corporate Services | F11: Technology | G11: Wave 1B | H11: Migrate | I11: Sync Started-connected
A12: AHFRM | B12: https://serco.sharepoint.com/sites/ahfrm | C12: https://serconagcch.sharepoint.us/sites/ahfrm | D12: Raymond.Wier@serco-na.com | E12: Corporate Services | F12: Technology | G12: Wave 1B | H12: Migrate | I12: Sync Started
A13: AHFRM Rapid Fielding Planning and Support-AHFRM DTIC Management Channel | B13: https://serco.sharepoint.com/sites/AHFRMDTICKICKOFF-AHFRMDTICManagementChannel | C13: https://serconagcch.sharepoint.us/sites/AHFRMDTICKICKOFF | D13: Steven.Yelverton@serco-na.com | E13: Corporate Services | F13: Technology | G13: Wave 1B | H13: Migrate | I13: Sync Started
A14: AHFRM Manufacturing Emails | B14: https://serco.sharepoint.com/sites/AHFRMManufacturingEmails | C14: https://serconagcch.sharepoint.us/sites/AHFRMManufacturingEmails | D14: Brian.Townsend@serco-na.com | E14: Corporate Services | F14: Technology | G14: Wave 1B | H14: Migrate | I14: Sync Started
A15: AmeriCorps Workforce Analysis | B15: https://serco.sharepoint.com/sites/AmeriCorpsWorkforceAnalysis | C15: https://serconagcch.sharepoint.us/sites/AmeriCorpsWorkforceAnalysis | D15: Allison.Gervasio@serco-na.com | E15: Corporate Services | F15: Technology | G15: Wave 1B | H15: Migrate | I15: Sync Started
A16: Angelo B-52 Files | B16: https://serco.sharepoint.com/sites/AngeloFiles | C16: https://serconagcch.sharepoint.us/sites/AngeloFiles | D16: Brian.Townsend@serco-na.com | E16: Corporate Services | F16: Technology | G16: Wave 1B | H16: Migrate | I16: Sync Started
A17: Armed Overwatch | B17: https://serco.sharepoint.com/sites/ArmedOverwatch | C17: https://serconagcch.sharepoint.us/sites/ArmedOverwatch | D17: Gary.Leavy@serco-na.com | E17: Corporate Services | F17: Technology | G17: Wave 1B | H17: Migrate | I17: Sync Started
A18: Army CONOPS Team | B18: https://serco.sharepoint.com/sites/ArmyCONOPSTeam | C18: https://serconagcch.sharepoint.us/sites/ArmyCONOPSTeam | D18: Jay.Voorhees@serco-na.com | E18: Corporate Services | F18: Technology | G18: Wave 1B | H18: Migrate | I18: Sync Started
A19: Army Team | B19: https://serco.sharepoint.com/sites/armyteam | C19: https://serconagcch.sharepoint.us/sites/armyteam | D19: Michael.J.Harris@serco-na.com | E19: Corporate Services | F19: Technology | G19: Wave 1B | H19: Migrate | I19: Sync Started
A20: AUSA Group | B20: https://serco.sharepoint.com/sites/AUSAGroup | C20: https://serconagcch.sharepoint.us/sites/AUSAGroup | D20: Michael.J.Harris@serco-na.com | E20: Corporate Services | F20: Technology | G20: Wave 1B | H20: Migrate | I20: Sync Started
A21: B-52 DTIC IAC Team | B21: https://serco.sharepoint.com/sites/B-52DTICIACTeam | C21: https://serconagcch.sharepoint.us/sites/B-52DTICIACTeam | D21: Brian.Townsend@serco-na.com | E21: Corporate Services | F21: Technology | G21: Wave 1B | H21: Migrate | I21: Sync Started | J21: https://gov.teams.microsoft.us/l/channel/19%3Agcch%3Ad84581d74cd642a2a5d7289286422301%40thread.tacv2/31688%20B-52%20Analysis%20and%20Modernization?groupId=d63110a1-af9a-4b18-a770-bf272eaafe3b&tenantId=fb1f5cc5-be84-4881-b037-2d641aea97fd&ngc=true
A22: B-52 Legacy TS PWS | B22: https://serco.sharepoint.com/sites/B-52LegacyTSPWS | C22: https://serconagcch.sharepoint.us/sites/B-52LegacyTSPWS | D22: Brian.Townsend@serco-na.com | E22: Corporate Services | F22: Technology | G22: Wave 1B | H22: Migrate | I22: Sync Started
A23: B-52 Nuc Cert Collaboration | B23: https://serco.sharepoint.com/sites/B-52NucCertCollaboration | C23: https://serconagcch.sharepoint.us/sites/B-52NucCertCollaboration | D23: Brian.Townsend@serco-na.com | E23: Corporate Services | F23: Technology | G23: Wave 1B | H23: Migrate | I23: Sync Started | J23: https://gov.teams.microsoft.us/l/team/19%3Agcch%3Ac923882e1fae430db5a2a5b92ae4857e%40thread.tacv2/conversations?groupId=6558baf4-9ed8-4d91-95bf-6e8e7a9df34b&tenantId=fb1f5cc5-be84-4881-b037-2d641aea97fd
A24: B-52 TS | B24: https://serco.sharepoint.com/sites/B-52TS | C24: https://serconagcch.sharepoint.us/sites/B-52TS | D24: Gary.Leavy@serco-na.com | E24: Corporate Services | F24: Technology | G24: Wave 1B | H24: Migrate | I24: Sync Started
A25: CBP RFI | B25: https://serco.sharepoint.com/sites/CBPRFI | C25: https://serconagcch.sharepoint.us/sites/CBPRFI | D25: Maggie.Irons@serco-na.com | E25: Corporate Services | F25: Technology | G25: Wave 1B | H25: Migrate | I25: Sync Started
A26: Consultancy+ Army Market-Army Aviation Concept 2040-PACOM | B26: https://serco.sharepoint.com/sites/ConsultancyArmyMarket-ArmyAviationConcept2040-PACOM | D26: Michael.Bentley@serco-na.com | E26: Corporate Services | F26: Technology | G26: Wave 1B | H26: Migrate | I26: Migrated in Wave 1 - Agile Impact Army Team
A27: Agile Impact Army Team-Army Aviation Concept 2040-PACOM | B27: https://serco.sharepoint.com/sites/ConsultancyArmyMarket-ArmyAviationConcept2040-PACOM2 | D27: Michael.Bentley@serco-na.com | E27: Corporate Services | F27: Technology | G27: Wave 1B | H27: Migrate | I27: Migrated in Wave 1 - Agile Impact Army Team
A28: Agile Impact Army Team-FT Novosel UAS Industry Day and AVCOE Industry Day | B28: https://serco.sharepoint.com/sites/ConsultancyArmyMarket-FTNovoselUASIndustryDayandAVCOEIndustryDay | D28: Michael.Bentley@serco-na.com | E28: Corporate Services | F28: Technology | G28: Wave 1B | H28: Migrate | I28: Migrated in Wave 1 - Agile Impact Army Team
A29: DAF RCO 24-C-0007 | B29: https://serco.sharepoint.com/sites/DAFRCO24-C-0007 | C29: https://serconagcch.sharepoint.us/sites/DAFRCO24-C-0007 | D29: Alexander.Brown@serco-na.com | E29: Corporate Services | F29: Technology | G29: Wave 1B | H29: Migrate | I29: Migrated in Wave 1
A30: DAF RCO Bridge | B30: https://serco.sharepoint.com/sites/DAFRCOBridge | C30: https://serconagcch.sharepoint.us/sites/DAFRCOBridge | D30: Alexander.Brown@serco-na.com | E30: Corporate Services | F30: Technology | G30: Wave 1B | H30: Migrate | I30: Sync Started
A31: Defense Exportability Features - Bell | B31: https://serco.sharepoint.com/sites/DefenseExportabilityFeatures-Bell | C31: https://serconagcch.sharepoint.us/sites/DefenseExportabilityFeatures-Bell | D31: Joana.Rivera@serco-na.com | E31: Corporate Services | F31: Technology | G31: Wave 1B | H31: Migrate | I31: Sync Started
A32: DHS FPS Acquisition #32094 | B32: https://serco.sharepoint.com/sites/DHSFPSAcquisition32094 | C32: https://serconagcch.sharepoint.us/sites/DHSFPSAcquisition32094 | D32: Leonard.Geshan@serco-na.com | E32: Corporate Services | F32: Technology | G32: Wave 1B | H32: Migrate | I32: Sync Started
A33: Digital Enterprise BD Campaign-DE Consortium 2025 | B33: https://serco.sharepoint.com/sites/DigitalEnterprise-EWAACDEConsortium | D33: Robert.Hoffman@serco-na.com | E33: Corporate Services | F33: Technology | G33: Wave 1B | H33: Migrate | I33: Migrated in Wave 1 - Digital Enterprise BD Campaign
A34: DTIC IAC MAC - Pool One | B34: https://serco.sharepoint.com/sites/DTICIACMAC-PoolOne | C34: https://serconagcch.sharepoint.us/sites/DTICIACMAC-PoolOne | D34: Raymond.Wier@serco-na.com | E34: Corporate Services | F34: Technology | G34: Wave 1B | H34: Migrate | I34: Sync Started-connected
A35: DTIC IAC MAC - Pool One-IAC MAC 2673 448 SCMW | B35: https://serco.sharepoint.com/sites/DTICIACMAC-PoolOne-IACMAC2673448SCMW | C35: https://serconagcch.sharepoint.us/sites/DTICIACMAC-PoolOne | D35: Raymond.Wier@serco-na.com | E35: Corporate Services | F35: Technology | G35: Wave 1B | H35: Migrate | I35: Sync Started-connected
A36: DTIC IAC MAC - Pool One-MECSIP | B36: https://serco.sharepoint.com/sites/DTICIACMAC-PoolOne-MECSIP | C36: https://serconagcch.sharepoint.us/sites/DTICIACMAC-PoolOne | D36: Raymond.Wier@serco-na.com | E36: Corporate Services | F36: Technology | G36: Wave 1B | H36: Migrate | I36: Sync Started-connected
A37: DTIC TO # 1 Group | B37: https://serco.sharepoint.com/sites/DTICTO1Group | C37: https://serconagcch.sharepoint.us/sites/DTICTO1Group | D37: Robert.Hoffman@serco-na.com | E37: Corporate Services | F37: Technology | G37: Wave 1B | H37: Migrate | I37: Sync Started
A38: Eglin Wide Agile Acquisition Contract (EWAAC) | B38: https://serco.sharepoint.com/sites/EglinWideAgileAcquisitionContractEWAAC | C38: https://serconagcch.sharepoint.us/sites/EglinWideAgileAcquisitionContractEWAAC | D38: Robert.Hoffman@serco-na.com | E38: Corporate Services | F38: Technology | G38: Wave 1B | H38: Migrate | I38: Sync Started
A39: F-35 FM KBS | B39: https://serco.sharepoint.com/sites/F-35FMKBS | C39: https://serconagcch.sharepoint.us/sites/F-35FMKBS | D39: Alex.Stathopoulos@serco-na.com | E39: Corporate Services | F39: Technology | G39: Wave 1B | H39: Migrate | I39: Sync Started
A40: F-35 Logistics KBS | B40: https://serco.sharepoint.com/sites/F-35LogisticsKBS | C40: https://serconagcch.sharepoint.us/sites/F-35LogisticsKBS | D40: Alex.Stathopoulos@serco-na.com | E40: Corporate Services | F40: Technology | G40: Wave 1B | H40: Migrate | I40: Sync Started
A41: F-35 Team Site | B41: https://serco.sharepoint.com/sites/F-35TeamSite | C41: https://serconagcch.sharepoint.us/sites/F-35TeamSite | D41: Kevin.Harms@serco-na.com | E41: Corporate Services | F41: Technology | G41: Wave 1B | H41: Migrate | I41: Sync Started
A42: FDIC IFWMS | B42: https://serco.sharepoint.com/sites/FDICIFWMS | C42: https://serconagcch.sharepoint.us/sites/FDICIFWMS | D42: David.Case@serco-na.com | E42: Corporate Services | F42: Citizens Services | G42: Wave 1B | H42: Migrate | I42: Sync Started-connected
A43: FDIC IFWMS-Project Team | B43: https://serco.sharepoint.com/sites/FDICIFWMS-ProjectTeam | C43: https://serconagcch.sharepoint.us/sites/FDICIFWMS | D43: David.Case@serco-na.com | E43: Corporate Services | F43: Citizens Services | G43: Wave 1B | H43: Migrate | I43: Sync Started-connected
A44: FEMA CID Bid | B44: https://serco.sharepoint.com/sites/FEMACIDBid | C44: https://serconagcch.sharepoint.us/sites/FEMACIDBid | D44: Maggie.Irons@serco-na.com | E44: Corporate Services | F44: Technology | G44: Wave 1B | H44: Migrate | I44: Sync Started
A45: Graphics Hub | B45: https://serco.sharepoint.com/sites/GraphicsHub | C45: https://serconagcch.sharepoint.us/sites/GraphicsHub | D45: Maggie.Irons@serco-na.com | E45: Corporate Services | F45: Technology | G45: Wave 1B | H45: Migrate | I45: Sync Started
... A47: JSSMO (PNT PO) - Wright Patterson Client Site Team | B47: https://serco.sharepoint.com/sites/JSSMOPNTPO-WrightPattersonClientSiteTeam | C47: https://serconagcch.sharepoint.us/sites/JSSMOPNTPO-WrightPattersonClientSiteTeam | D47: Jeffrey.Braun@serco-na.com | E47: Corporate Services | F47: Technology | G47: Wave 1B | H47: Migrate | I47: Sync Started
A48: KC-135 AW | B48: https://serco.sharepoint.com/sites/KC-135AW | C48: https://serconagcch.sharepoint.us/sites/KC-135AW | D48: Brian.Townsend@serco-na.com | E48: Corporate Services | F48: Technology | G48: Wave 1B | H48: Migrate | I48: Sync Started | J48: https://gov.teams.microsoft.us/l/team/19%3Agcch%3A5b0526e975a748debd9231e2ddab8b70%40thread.tacv2/conversations?groupId=59010a5f-cd41-429a-9cf5-006a8ffdf72a&tenantId=fb1f5cc5-be84-4881-b037-2d641aea97fd
A49: KC-135 Engineering Support | B49: https://serco.sharepoint.com/sites/KC-135EngineeringSupport | C49: https://serconagcch.sharepoint.us/sites/KC-135EngineeringSupport | D49: Brian.Townsend@serco-na.com | E49: Corporate Services | F49: Technology | G49: Wave 1B | H49: Migrate | I49: Sync Started | J49: https://gov.teams.microsoft.us/l/team/19%3Agcch%3A5b0526e975a748debd9231e2ddab8b70%40thread.tacv2/conversations?groupId=59010a5f-cd41-429a-9cf5-006a8ffdf72a&tenantId=fb1f5cc5-be84-4881-b037-2d641aea97fd
A50: MDA Threat Systems Engineering -Threat Products and Services | B50: https://serco.sharepoint.com/sites/MDAThreatSystemsEngineering-ThreatProductsandServices | C50: https://serconagcch.sharepoint.us/sites/MDAThreatSystemsEngineering-ThreatProductsandServices | D50: Robert.Hoffman@serco-na.com | E50: Corporate Services | F50: Technology | G50: Wave 1B | H50: Migrate | I50: Sync Started
A51: MTUAS Acq Support-98. Previous MTUAS Project - Working | B51: https://serco.sharepoint.com/sites/MTUASAcqSupport-Working | D51: Christopher.Richards@serco-na.com | E51: Corporate Services | F51: Technology | G51: Wave 1B | H51: Migrate | I51: Migrated in Wave 1 | J51: https://gov.teams.microsoft.us/l/team/19%3Agcch%3AvoILPavh_NiLuBYstR0tquVGJwDUED6usGDn1e3LmXE1%40thread.tacv2/conversations?groupId=3f997a95-bcf4-49f2-9cc0-a93c1bbf3489&tenantId=fb1f5cc5-be84-4881-b037-2d641aea97fd
A52: N81F Combat System Sustainment | B52: https://serco.sharepoint.com/sites/N81FCombatSystemSustainment | C52: https://serconagcch.sharepoint.us/sites/N81FCombatSystemSustainment | D52: Allison.Gervasio@serco-na.com | E52: Corporate Services | F52: Technology | G52: Wave 1B | H52: Migrate | I52: Sync Started
A53: Navigating Business Webinar Series | B53: https://serco.sharepoint.com/sites/NavigatingBusinessWebinarSeries | C53: https://serconagcch.sharepoint.us/sites/NavigatingBusinessWebinarSeries | D53: Allison.Gervasio@serco-na.com | E53: Corporate Services | F53: Technology | G53: Wave 1B | H53: Migrate | I53: Sync Started
A54: NIH NIAID | B54: https://serco.sharepoint.com/sites/NIHNIAID | C54: https://serconagcch.sharepoint.us/sites/NIHNIAID | D54: Allison.Gervasio@serco-na.com | E54: Corporate Services | F54: Technology | G54: Wave 1B | H54: Migrate | I54: Sync Started-connected
A55: NIH NIAID-Clever Nelly Analysis | B55: https://serco.sharepoint.com/sites/NIHNIAID-CleverNellyAnalysis | C55: https://serconagcch.sharepoint.us/sites/NIHNIAID | D55: Allison.Gervasio@serco-na.com | E55: Corporate Services | F55: Technology | G55: Wave 1B | H55: Migrate | I55: Sync Started-connected
A56: NIH NIAID-PM | B56: https://serco.sharepoint.com/sites/NIHNIAID-PM | C56: https://serconagcch.sharepoint.us/sites/NIHNIAID | D56: Allison.Gervasio@serco-na.com | E56: Corporate Services | F56: Technology | G56: Wave 1B | H56: Migrate | I56: Sync Started-connected
A57: NIH NIAID-Succession Planning | B57: https://serco.sharepoint.com/sites/NIHNIAID-SuccessionPlanning | C57: https://serconagcch.sharepoint.us/sites/NIHNIAID | D57: Allison.Gervasio@serco-na.com | E57: Corporate Services | F57: Technology | G57: Wave 1B | H57: Migrate | I57: Sync Started-connected
A58: PNT - Independent Review Team | B58: https://serco.sharepoint.com/sites/PNT-IndependentReviewTeam | C58: https://serconagcch.sharepoint.us/sites/PNT-IndependentReviewTeam | D58: Till.Schanz@serco-na.com | E58: Corporate Services | F58: Technology | G58: Wave 1B | H58: Migrate | I58: Sync Started
A59: AF PNT (JSSMO) Leads | B59: https://serco.sharepoint.com/sites/PNTJSSMOLeads | C59: https://serconagcch.sharepoint.us/sites/PNTJSSMOLeads | D59: Till.Schanz@serco-na.com | E59: Corporate Services | F59: Technology | G59: Wave 1B | H59: Migrate | I59: Sync Started
A60: PNT PO Strategic Planning | B60: https://serco.sharepoint.com/sites/PNTPOStrategicPlanning | C60: https://serconagcch.sharepoint.us/sites/PNTPOStrategicPlanning | D60: Till.Schanz@serco-na.com | E60: Corporate Services | F60: Technology | G60: Wave 1B | H60: Migrate | I60: Sync Started
A61: PNT Proposal 2025 | B61: https://serco.sharepoint.com/sites/PNTProposal2025 | C61: https://serconagcch.sharepoint.us/sites/PNTProposal2025 | D61: Till.Schanz@serco-na.com | E61: Corporate Services | F61: Technology | G61: Wave 1B | H61: Migrate | I61: Sync Started
A62: R-EGI Phase III (Serco) | B62: https://serco.sharepoint.com/sites/R-EGIPhaseIIISerco | C62: https://serconagcch.sharepoint.us/sites/R-EGIPhaseIIISerco | D62: Jason.Rusco@serco-na.com | E62: Corporate Services | F62: Technology | G62: Wave 1B | H62: Migrate | I62: Sync Started
A63: R-EGI Phase III (Serco)-R-EGI Leadership Briefings (controlled access) | B63: https://serco.sharepoint.com/sites/R-EGIPhaseIIISerco-R-EGILeadershipBriefingscontrolledaccess | D63: Jason.Rusco@serco-na.com | E63: Corporate Services | F63: Technology | G63: Wave 1B | H63: Migrate
A64: WBB-COP Organizational Development | B64: https://serco.sharepoint.com/sites/SA-M365Team-WBB-COPOD | C64: https://serconagcch.sharepoint.us/sites/WBB-COPOrganizationalDevelopment | D64: Allison.Gervasio@serco-na.com | E64: Corporate Services | F64: Technology | G64: Wave 1B | H64: Migrate | I64: Sync Started
A65: WBB Org Design-USASAC org design study | B65: https://serco.sharepoint.com/sites/SA-M365Team-WBB-OrgDesign-USASACorgdesignstudy | D65: Michael.J.Harris@serco-na.com | E65: Corporate Services | F65: Technology | G65: Wave 1B | H65: Migrate | I65: Migrated in Wave 1 - WBB Org Design
A66: Beacon | B66: https://serco.sharepoint.com/sites/SA-WBB-Beacon | D66: Allison.Gervasio@serco-na.com | E66: Corporate Services | F66: Technology | G66: Wave 1B | H66: Migrate
A67: SECWAR Acq Reform Team | B67: https://serco.sharepoint.com/sites/SECWARAcqReformTeam | C67: https://serconagcch.sharepoint.us/sites/SECWARAcqReformTeam | D67: Timothy.Ablay@serco-na.com | E67: Corporate Services | F67: Technology | G67: Wave 1B | H67: Migrate | I67: Sync Started
A68: SERCO Airworthiness Team | B68: https://serco.sharepoint.com/sites/SERCOAirworthinessTeam | C68: https://serconagcch.sharepoint.us/sites/SERCOAirworthinessTeam | D68: Mark.Wilson@serco-na.com | E68: Corporate Services | F68: Technology | G68: Wave 1B | H68: Migrate | I68: Sync Started | J68: https://gov.teams.microsoft.us/l/team/19%3Agcch%3A5b0526e975a748debd9231e2ddab8b70%40thread.tacv2/conversations?groupId=59010a5f-cd41-429a-9cf5-006a8ffdf72a&tenantId=fb1f5cc5-be84-4881-b037-2d641aea97fd
A69: Agile Impact Army Team-Campaign Planning | B69: https://serco.sharepoint.com/sites/SercoArmyMarket-CampaignPlanning | D69: Michael.Bentley@serco-na.com | E69: Corporate Services | F69: Technology | G69: Wave 1B | H69: Migrate | I69: Migrated in Wave 1
A70: Serco Source Selection Training-ISSJ-III | B70: https://serco.sharepoint.com/sites/SercoSourceSelectionTraining-ISSJ-III | D70: Raymond.Wier@serco-na.com | E70: Corporate Services | F70: Technology | G70: Wave 1B | H70: Migrate | I70: Migrated in Wave 1 | J70: https://gov.teams.microsoft.us/l/channel/19%3Agcch%3A012988c267564e9c91ed2d8836cd0fec%40thread.tacv2/ISSJ-III?groupId=a2e56443-3a3b-4170-b549-3d4bb7c5a55b&tenantId=fb1f5cc5-be84-4881-b037-2d641aea97fd&ngc=true
A71: SercoVets Leadership Team | B71: https://serco.sharepoint.com/sites/SercoVetsLeadershipTeam | C71: https://serconagcch.sharepoint.us/sites/SercoVetsLeadershipTeam | D71: Vasilios.Pappas@serco-na.com | E71: Corporate Services | F71: Technology | G71: Wave 1B | H71: Migrate | I71: Sync Started
A72: Agile Impact Team-PDRI Innovative Thinking | B72: https://serco.sharepoint.com/sites/serco-wbb-competency-PDRIInnovativeThinking | D72: Christopher.Pritchet@serco-na.com | E72: Corporate Services | F72: Technology | G72: Wave 1B | H72: Migrate | I72: Migrated in Wave 1
A73: SOCOM AT&L Support (Serco Direct Contract)-OCI Plan | B73: https://serco.sharepoint.com/sites/SOCOMSupportSercoDirectContract-OCIPlan | D73: Raymond.Wier@serco-na.com | E73: Corporate Services | F73: Technology | G73: Wave 1B | H73: Migrate | I73: Migrated in Wave 1 - SOCOM AT&L Support (Serco Direct Contract) | J73: https://gov.teams.microsoft.us/l/channel/19%3Agcch%3Aa3c3932b648e4119b01d4ba52a61e2e4%40thread.tacv2/OCI%20Plan?groupId=8bf46d4c-65f4-4923-86d7-81a8f3e924ca&tenantId=fb1f5cc5-be84-4881-b037-2d641aea97fd&ngc=true
A74: SOCOM AT&L Support (Serco Direct Contract)-PM and Contracting | B74: https://serco.sharepoint.com/sites/SOCOMSupportSercoDirectContract-PMandContracting | D74: Raymond.Wier@serco-na.com | E74: Corporate Services | F74: Technology | G74: Wave 1B | H74: Migrate | I74: Migrated in Wave 1 - SOCOM AT&L Support (Serco Direct Contract) | J74: https://gov.teams.microsoft.us/l/channel/19%3Agcch%3A8728118ef5174ee0aaf93c8b32110d71%40thread.tacv2/PM%20and%20Contracting?groupId=8bf46d4c-65f4-4923-86d7-81a8f3e924ca&tenantId=fb1f5cc5-be84-4881-b037-2d641aea97fd&ngc=true
A75: SOCOM AT&L Support (Serco Direct Contract)-TO 02 - RSAS PEO RW Support | B75: https://serco.sharepoint.com/sites/SOCOMSupportSercoDirectContract-TO02-PEORWSupport | D75: Raymond.Wier@serco-na.com | E75: Corporate Services | F75: Technology | G75: Wave 1B | H75: Migrate | I75: Migrated in Wave 1 - SOCOM AT&L Support (Serco Direct Contract) | J75: https://gov.teams.microsoft.us/l/channel/19%3Agcch%3A7a32f1b9857f428d867b864cca1f13ee%40thread.tacv2/TO%2002%20-%20RSAS%20PEO%20RW%20Support?groupId=8bf46d4c-65f4-4923-86d7-81a8f3e924ca&tenantId=fb1f5cc5-be84-4881-b037-2d641aea97fd&ngc=true
A76: SOCOM AT&L Support (Serco Direct Contract)-TO 06 - HWW | B76: https://serco.sharepoint.com/sites/SOCOMSupportSercoDirectContract-TO06-HWW | D76: Raymond.Wier@serco-na.com | E76: Corporate Services | F76: Technology | G76: Wave 1B | H76: Migrate | I76: Migrated in Wave 1 - SOCOM AT&L Support (Serco Direct Contract) | J76: https://gov.teams.microsoft.us/l/channel/19%3Agcch%3A1c13821ef26646afb91714d2700d3cce%40thread.tacv2/TO%2006%20-%20HWW?groupId=8bf46d4c-65f4-4923-86d7-81a8f3e924ca&tenantId=fb1f5cc5-be84-4881-b037-2d641aea97fd&ngc=true
A77: SOCOM AT&L Support (Serco Direct Contract)-TO 09 - PEO-M PM Mentoring | B77: https://serco.sharepoint.com/sites/SOCOMSupportSercoDirectContract-TO09-PEO-MPMMentoring | D77: Raymond.Wier@serco-na.com | E77: Corporate Services | F77: Technology | G77: Wave 1B | H77: Migrate | I77: Migrated in Wave 1 - SOCOM AT&L Support (Serco Direct Contract) | J77: https://gov.teams.microsoft.us/l/channel/19%3Agcch%3Ac18023ce099b419eb0c80f68a55377e5%40thread.tacv2/TO%2009%20-%20PEO-M%20PM%20Mentoring?groupId=8bf46d4c-65f4-4923-86d7-81a8f3e924ca&tenantId=fb1f5cc5-be84-4881-b037-2d641aea97fd&ngc=true
A78: SOCOM AT&L Support (Serco Direct Contract)-TO 10 - PEO FW A2E Acq Planning | B78: https://serco.sharepoint.com/sites/SOCOMSupportSercoDirectContract-TO10-PEOFWA2EAcqPlanning | D78: Raymond.Wier@serco-na.com | E78: Corporate Services | F78: Technology | G78: Wave 1B | H78: Migrate | I78: Migrated in Wave 1 - SOCOM AT&L Support (Serco Direct Contract) | J78: https://gov.teams.microsoft.us/l/channel/19%3Agcch%3A9288ac5cf6dd418498893d27d1181415%40thread.tacv2/TO%2010%20-%20PEO%20FW%20A2E%20Acq%20Planning?groupId=8bf46d4c-65f4-4923-86d7-81a8f3e924ca&tenantId=fb1f5cc5-be84-4881-b037-2d641aea97fd&ngc=true
A79: SOCOM AT&L Support (Serco Direct Contract)-TO 05 - GLSS Support | B79: https://serco.sharepoint.com/sites/SOCOMSupportSercoDirectContract-TOOX-GLSSSupport | D79: Raymond.Wier@serco-na.com | E79: Corporate Services | F79: Technology | G79: Wave 1B | H79: Migrate | I79: Migrated in Wave 1 - SOCOM AT&L Support (Serco Direct Contract) | J79: https://gov.teams.microsoft.us/l/channel/19%3Agcch%3Aa976e0f31f1f4b4f9f2ba6fefb892954%40thread.tacv2/TO%2005%20-%20GLSS%20Support?groupId=8bf46d4c-65f4-4923-86d7-81a8f3e924ca&tenantId=fb1f5cc5-be84-4881-b037-2d641aea97fd&ngc=true
A80: SOCOM AT&L Support (Serco Direct Contract)-TO 04 - ISS-J | B80: https://serco.sharepoint.com/sites/SOCOMSupportSercoDirectContract-TOXX-ISSJ | D80: Raymond.Wier@serco-na.com | E80: Corporate Services | F80: Technology | G80: Wave 1B | H80: Migrate | I80: Migrated in Wave 1 - SOCOM AT&L Support (Serco Direct Contract) | J80: https://gov.teams.microsoft.us/l/channel/19%3Agcch%3A2286671f781046e3a16bcd8e81b96f96%40thread.tacv2/TO%2004%20-%20ISS-J?groupId=8bf46d4c-65f4-4923-86d7-81a8f3e924ca&tenantId=fb1f5cc5-be84-4881-b037-2d641aea97fd&ngc=true
A81: SOCOM AT&L Support (Serco Direct Contract)-TO 07 - Loggerhead Support | B81: https://serco.sharepoint.com/sites/SOCOMSupportSercoDirectContract-TOXX-MMDSSupport | D81: Raymond.Wier@serco-na.com | E81: Corporate Services | F81: Technology | G81: Wave 1B | H81: Migrate | I81: Migrated in Wave 1 - SOCOM AT&L Support (Serco Direct Contract) | J81: https://gov.teams.microsoft.us/l/channel/19%3Agcch%3Acb4cae2b588245b08c0e231f2d9b405d%40thread.tacv2/TO%2011%20PEO%20Maritime%20Sppt%20Follow-On?groupId=8bf46d4c-65f4-4923-86d7-81a8f3e924ca&tenantId=fb1f5cc5-be84-4881-b037-2d641aea97fd&ngc=true
A82: SOCOM AT&L Support (Serco Direct Contract)-TO 08 - PEO FW Support | B82: https://serco.sharepoint.com/sites/SOCOMSupportSercoDirectContract-TOXX-PEOFWSupport | D82: Raymond.Wier@serco-na.com | E82: Corporate Services | F82: Technology | G82: Wave 1B | H82: Migrate | I82: Migrated in Wave 1 - SOCOM AT&L Support (Serco Direct Contract) | J82: https://gov.teams.microsoft.us/l/channel/19%3Agcch%3A95810efeb04e47ada1c7c28ee1cb9085%40thread.tacv2/TO%2008%20-%20PEO%20FW%20Support?groupId=8bf46d4c-65f4-4923-86d7-81a8f3e924ca&tenantId=fb1f5cc5-be84-4881-b037-2d641aea97fd&ngc=true
A83: SOCOM AT&L Support (Serco Direct Contract)-TO 03 - SOFGSD | B83: https://serco.sharepoint.com/sites/SOCOMSupportSercoDirectContract-TOXX-SOFGSD | D83: Raymond.Wier@serco-na.com | E83: Corporate Services | F83: Technology | G83: Wave 1B | H83: Migrate | I83: Migrated in Wave 1 - SOCOM AT&L Support (Serco Direct Contract) | J83: https://gov.teams.microsoft.us/l/channel/19%3Agcch%3Af76fc85a14b24a0695607f778313ce53%40thread.tacv2/TO%2003%20-%20SOFGSD?groupId=8bf46d4c-65f4-4923-86d7-81a8f3e924ca&tenantId=fb1f5cc5-be84-4881-b037-2d641aea97fd&ngc=true
A84: Tech Trakr | B84: https://serco.sharepoint.com/sites/TechTrakr | C84: https://serconagcch.sharepoint.us/sites/TechTrakr | D84: Brian.Townsend@serco-na.com | E84: Corporate Services | F84: Technology | G84: Wave 1B | H84: Migrate | I84: Sync Started
A85: TRR Test | B85: https://serco.sharepoint.com/sites/TRRTest | C85: https://serconagcch.sharepoint.us/sites/TRRTest | D85: Taryn.Trimble@serco-na.com | E85: Corporate Services | F85: Technology | G85: Wave 1B | H85: Migrate | I85: Sync Started
A86: USASAC Team | B86: https://serco.sharepoint.com/sites/USASACTeam | C86: https://serconagcch.sharepoint.us/sites/USASACTeam | D86: Michael.J.Harris@serco-na.com | E86: Corporate Services | F86: Technology | G86: Wave 1B | H86: Migrate | I86: Sync Started
A87: USSF Training Red Team | B87: https://serco.sharepoint.com/sites/USSFTrainingRedTeam | C87: https://serconagcch.sharepoint.us/sites/USSFTrainingRedTeam | D87: Raymond.Wier@serco-na.com | E87: Corporate Services | F87: Technology | G87: Wave 1B | H87: Migrate | I87: Sync Started
A88: USSOCOM Support (St. Michaels)-MCS COP IRT | B88: https://serco.sharepoint.com/sites/USSOCOMSupport-MCSCOPIRT | D88: Raymond.Wier@serco-na.com | E88: Corporate Services | F88: Technology | G88: Wave 1B | H88: Migrate | I88: Migrated in Wave 1 - USSOCOM Support (St. Michaels) | J88: https://gov.teams.microsoft.us/l/channel/19%3Agcch%3Ad4ffe95cc2c14058b92547ce920346ac%40thread.tacv2/MCS%20COP%20IRT?groupId=c568772c-0d47-4e0b-b1f1-256b85d1f7a3&tenantId=fb1f5cc5-be84-4881-b037-2d641aea97fd&ngc=true
A89: WBB_INT_DAI | B89: https://serco.sharepoint.com/sites/WBB_INT_DAI | D89: Brian.Marshall@serco-na.com | E89: Corporate Services | F89: #N/A | G89: Wave 1B | H89: Migrate | I89: EXISTS IN TARGET. Target Team created in 2022, has no owners
A90: ASG_BD Team-SAF AQH Space Force | B90: https://serco.sharepoint.com/sites/wbb-bu_agile_staff_bd-SAFAQHSpaceForce | D90: Raymond.Wier@serco-na.com | E90: Corporate Services | F90: Technology | G90: Wave 1B | H90: Migrate | I90: Migrated in Wave 1 - ASG_BD Team (Agile Impact_BD)
A91: WBB Org Design-F35 JPO ORG DESIGN STUDY | B91: https://serco.sharepoint.com/sites/WBBOrgDesign-F35JPOAVIONICSORGDESIGNSTUDY | D91: Michael.J.Harris@serco-na.com | E91: Corporate Services | F91: Technology | G91: Wave 1B | H91: Migrate | I91: Migrated in Wave 1 - WBB Org Design
A92: WBB Org Design-PM AMSA Organizational Design Study | B92: https://serco.sharepoint.com/sites/WBBOrgDesign-PMAMSAOrganizationalDesignStudy | D92: Jay.Voorhees@serco-na.com | E92: Corporate Services | F92: Technology | G92: Wave 1B | H92: Migrate | I92: Migrated in Wave 1 - WBB Org Design
A93: WBB Org Design-SE_V ORG Design | B93: https://serco.sharepoint.com/sites/WBBOrgDesign-SE_VORGDesign | D93: Michael.J.Harris@serco-na.com | E93: Corporate Services | F93: Technology | G93: Wave 1B | H93: Migrate | I93: Migrated in Wave 1 - WBB Org Design

Sheet Sheet2
A2: Nicholas.Abate@serco-na.com
A3: Nassebeh.StJohn@serco-na.com
A4: Timothy.Ablay@serco-na.com
A5: Jincy.Abraham@serco.ae
A6: Richard.Adleson@serco-na.com
A7: AdminM365AuditReport@serco.onmicrosoft.com
A8: AFSFMarketTeam@serco.onmicrosoft.com
A9: AFSFMarketTeam@serco.onmicrosoft.com
A10: Francisco.Aguilar@serco-na.com
A11: Kellie.Aguilera@serco-na.com
A12: rahern@serco-na.com
A13: Humdan.Ahmed@serco-na.com
... A1126: Raymond.Wier@serco-na.com

Sheet Permissions
A1: SiteUrl | B1: SiteTitle | C1: Source | D1: UserDisplay | E1: UserEmail | F1: Agile1B | G1: UserMapped | H1: ActiveUsers
A2: https://serco.sharepoint.com/sites/aaaa | B2: AAAA | C2: SiteUsers | D2: AAAA Members | E2: aaaa@serco.onmicrosoft.com | F2: Migrate | G2: =_xlfn.XLOOKUP(E2,[1]QuestALL!$B:$B,[1]QuestALL!$E:$E) -> #N/A | H2: =_xlfn.XLOOKUP(E2,'[2]exportUsers_2026-4-16'!$C:$C,'[2]exportUsers_2026-4-16'!$D:$D) -> #N/A
A3: https://serco.sharepoint.com/sites/aaaa | B3: AAAA | C3: SiteUsers | D3: AAAA Owners | E3: aaaa@serco.onmicrosoft.com | F3: Migrate | G3: =_xlfn.XLOOKUP(E3,[1]QuestALL!$B:$B,[1]QuestALL!$E:$E) -> #N/A | H3: =_xlfn.XLOOKUP(E3,'[2]exportUsers_2026-4-16'!$C:$C,'[2]exportUsers_2026-4-16'!$D:$D) -> #N/A
A4: https://serco.sharepoint.com/sites/aaaa | B4: AAAA | C4: SiteUsers | D4: AdminM365AuditReport | E4: AdminM365AuditReport@serco.onmicrosoft.com | F4: Migrate | G4: =_xlfn.XLOOKUP(E4,[1]QuestALL!$B:$B,[1]QuestALL!$E:$E) -> #N/A | H4: =_xlfn.XLOOKUP(E4,'[2]exportUsers_2026-4-16'!$C:$C,'[2]exportUsers_2026-4-16'!$D:$D) -> #N/A
A5: https://serco.sharepoint.com/sites/aaaa | B5: AAAA | C5: SiteUsers | D5: Bartholomew, Robert - Cloud Admin (Serco NA) | F5: Migrate | G5: =_xlfn.XLOOKUP(E5,[1]QuestALL!$B:$B,[1]QuestALL!$E:$E) -> 0 | H5: #N/A
A6: https://serco.sharepoint.com/sites/aaaa | B6: AAAA | C6: SiteUsers | D6: Everyone | F6: Migrate | G6: =_xlfn.XLOOKUP(E6,[1]QuestALL!$B:$B,[1]QuestALL!$E:$E) -> 0 | H6: #N/A
A7: https://serco.sharepoint.com/sites/aaaa | B7: AAAA | C7: SiteUsers | D7: Everyone except external users | F7: Migrate | G7: =_xlfn.XLOOKUP(E7,[1]QuestALL!$B:$B,[1]QuestALL!$E:$E) -> 0 | H7: #N/A
A8: https://serco.sharepoint.com/sites/aaaa | B8: AAAA | C8: SiteUsers | D8: Harris, Michael, J (Serco NA US) | E8: Michael.J.Harris@serco-na.com | F8: Migrate | G8: =_xlfn.XLOOKUP(E8,[1]QuestALL!$B:$B,[1]QuestALL!$E:$E) -> Migrated | H8: =_xlfn.XLOOKUP(E8,'[2]exportUsers_2026-4-16'!$C:$C,'[2]exportUsers_2026-4-16'!$D:$D) -> Member
A9: https://serco.sharepoint.com/sites/aaaa | B9: AAAA | C9: SiteUsers | D9: NT Service\spsearch | F9: Migrate | G9: =_xlfn.XLOOKUP(E9,[1]QuestALL!$B:$B,[1]QuestALL!$E:$E) -> 0 | H9: #N/A
A10: https://serco.sharepoint.com/sites/aaaa | B10: AAAA | C10: SiteUsers | D10: o-jtinsley | E10: o-jtinsley@serco.onmicrosoft.com | F10: Migrate | G10: =_xlfn.XLOOKUP(E10,[1]QuestALL!$B:$B,[1]QuestALL!$E:$E) -> #N/A | H10: =_xlfn.XLOOKUP(E10,'[2]exportUsers_2026-4-16'!$C:$C,'[2]exportUsers_2026-4-16'!$D:$D) -> #N/A
A11: https://serco.sharepoint.com/sites/aaaa | B11: AAAA | C11: SiteUsers | D11: o-jturner | E11: o-jturner@serco.onmicrosoft.com | F11: Migrate | G11: =_xlfn.XLOOKUP(E11,[1]QuestALL!$B:$B,[1]QuestALL!$E:$E) -> #N/A | H11: =_xlfn.XLOOKUP(E11,'[2]exportUsers_2026-4-16'!$C:$C,'[2]exportUsers_2026-4-16'!$D:$D) -> #N/A
A12: https://serco.sharepoint.com/sites/aaaa | B12: AAAA | C12: SiteUsers | D12: o-tlarese | E12: o-tlarese@serco.onmicrosoft.com | F12: Migrate | G12: =_xlfn.XLOOKUP(E12,[1]QuestALL!$B:$B,[1]QuestALL!$E:$E) -> #N/A | H12: =_xlfn.XLOOKUP(E12,'[2]exportUsers_2026-4-16'!$C:$C,'[2]exportUsers_2026-4-16'!$D:$D) -> #N/A
A13: https://serco.sharepoint.com/sites/aaaa | B13: AAAA | C13: SiteUsers | D13: SharePoint App | F13: Migrate | G13: =_xlfn.XLOOKUP(E13,[1]QuestALL!$B:$B,[1]QuestALL!$E:$E) -> 0 | H13: #N/A
A14: https://serco.sharepoint.com/sites/aaaa | B14: AAAA | C14: SiteUsers | D14: SR-SVC-SPO-Serco-CSL-Mig | E14: SR-SVC-SPO-Serco-CSL-Mig@serco.onmicrosoft.com | F14: Migrate | G14: =_xlfn.XLOOKUP(E14,[1]QuestALL!$B:$B,[1]QuestALL!$E:$E) -> #N/A | H14: =_xlfn.XLOOKUP(E14,'[2]exportUsers_2026-4-16'!$C:$C,'[2]exportUsers_2026-4-16'!$D:$D) -> #N/A
A15: https://serco.sharepoint.com/sites/aaaa | B15: AAAA | C15: SiteUsers | D15: System Account | F15: Migrate | G15: =_xlfn.XLOOKUP(E15,[1]QuestALL!$B:$B,[1]QuestALL!$E:$E) -> 0 | H15: #N/A
A16: https://serco.sharepoint.com/sites/aaaaplanning | B16: AAAAPlanning | C16: SiteUsers | D16: AAAAPlanning Members | E16: aaaaplanning@serco.onmicrosoft.com | F16: Migrate | G16: =_xlfn.XLOOKUP(E16,[1]QuestALL!$B:$B,[1]QuestALL!$E:$E) -> #N/A | H16: =_xlfn.XLOOKUP(E16,'[2]exportUsers_2026-4-16'!$C:$C,'[2]exportUsers_2026-4-16'!$D:$D) -> #N/A
A17: https://serco.sharepoint.com/sites/aaaaplanning | B17: AAAAPlanning | C17: SiteUsers | D17: AAAAPlanning Owners | E17: aaaaplanning@serco.onmicrosoft.com | F17: Migrate | G17: =_xlfn.XLOOKUP(E17,[1]QuestALL!$B:$B,[1]QuestALL!$E:$E) -> #N/A | H17: =_xlfn.XLOOKUP(E17,'[2]exportUsers_2026-4-16'!$C:$C,'[2]exportUsers_2026-4-16'!$D:$D) -> #N/A
A18: https://serco.sharepoint.com/sites/aaaaplanning | B18: AAAAPlanning | C18: SiteUsers | D18: AdminM365AuditReport | E18: AdminM365AuditReport@serco.onmicrosoft.com | F18: Migrate | G18: =_xlfn.XLOOKUP(E18,[1]QuestALL!$B:$B,[1]QuestALL!$E:$E) -> #N/A | H18: =_xlfn.XLOOKUP(E18,'[2]exportUsers_2026-4-16'!$C:$C,'[2]exportUsers_2026-4-16'!$D:$D) -> #N/A
A19: https://serco.sharepoint.com/sites/aaaaplanning | B19: AAAAPlanning | C19: SiteUsers | D19: Bartholomew, Robert - Cloud Admin (Serco NA) | F19: Migrate | G19: =_xlfn.XLOOKUP(E19,[1]QuestALL!$B:$B,[1]QuestALL!$E:$E) -> 0 | H19: #N/A
A20: https://serco.sharepoint.com/sites/aaaaplanning | B20: AAAAPlanning | C20: SiteUsers | D20: Everyone | F20: Migrate | G20: =_xlfn.XLOOKUP(E20,[1]QuestALL!$B:$B,[1]QuestALL!$E:$E) -> 0 | H20: #N/A
A21: https://serco.sharepoint.com/sites/aaaaplanning | B21: AAAAPlanning | C21: SiteUsers | D21: Everyone except external users | F21: Migrate | G21: =_xlfn.XLOOKUP(E21,[1]QuestALL!$B:$B,[1]QuestALL!$E:$E) -> 0 | H21: #N/A
A22: https://serco.sharepoint.com/sites/aaaaplanning | B22: AAAAPlanning | C22: SiteUsers | D22: NT Service\spsearch | F22: Migrate | G22: =_xlfn.XLOOKUP(E22,[1]QuestALL!$B:$B,[1]QuestALL!$E:$E) -> 0 | H22: #N/A
A23: https://serco.sharepoint.com/sites/aaaaplanning | B23: AAAAPlanning | C23: SiteUsers | D23: o-jtinsley | E23: o-jtinsley@serco.onmicrosoft.com | F23: Migrate | G23: =_xlfn.XLOOKUP(E23,[1]QuestALL!$B:$B,[1]QuestALL!$E:$E) -> #N/A | H23: =_xlfn.XLOOKUP(E23,'[2]exportUsers_2026-4-16'!$C:$C,'[2]exportUsers_2026-4-16'!$D:$D) -> #N/A
A24: https://serco.sharepoint.com/sites/aaaaplanning | B24: AAAAPlanning | C24: SiteUsers | D24: o-jturner | E24: o-jturner@serco.onmicrosoft.com | F24: Migrate | G24: =_xlfn.XLOOKUP(E24,[1]QuestALL!$B:$B,[1]QuestALL!$E:$E) -> #N/A | H24: =_xlfn.XLOOKUP(E24,'[2]exportUsers_2026-4-16'!$C:$C,'[2]exportUsers_2026-4-16'!$D:$D) -> #N/A
A25: https://serco.sharepoint.com/sites/aaaaplanning | B25: AAAAPlanning | C25: SiteUsers | D25: o-tlarese | E25: o-tlarese@serco.onmicrosoft.com | F25: Migrate | G25: =_xlfn.XLOOKUP(E25,[1]QuestALL!$B:$B,[1]QuestALL!$E:$E) -> #N/A | H25: =_xlfn.XLOOKUP(E25,'[2]exportUsers_2026-4-16'!$C:$C,'[2]exportUsers_2026-4-16'!$D:$D) -> #N/A
A26: https://serco.sharepoint.com/sites/aaaaplanning | B26: AAAAPlanning | C26: SiteUsers | D26: SharePoint App | F26: Migrate | G26: =_xlfn.XLOOKUP(E26,[1]QuestALL!$B:$B,[1]QuestALL!$E:$E) -> 0 | H26: #N/A
A27: https://serco.sharepoint.com/sites/aaaaplanning | B27: AAAAPlanning | C27: SiteUsers | D27: SR-SVC-SPO-Serco-CSL-Mig | E27: SR-SVC-SPO-Serco-CSL-Mig@serco.onmicrosoft.com | F27: Migrate | G27: =_xlfn.XLOOKUP(E27,[1]QuestALL!$B:$B,[1]QuestALL!$E:$E) -> #N/A | H27: =_xlfn.XLOOKUP(E27,'[2]exportUsers_2026-4-16'!$C:$C,'[2]exportUsers_2026-4-16'!$D:$D) -> #N/A
A28: https://serco.sharepoint.com/sites/aaaaplanning | B28: AAAAPlanning | C28: SiteUsers | D28: System Account | F28: Migrate | G28: =_xlfn.XLOOKUP(E28,[1]QuestALL!$B:$B,[1]QuestALL!$E:$E) -> 0 | H28: #N/A
A29: https://serco.sharepoint.com/sites/AFSFMarketTeam | B29: Acquisition Management (AQM) | C29: SiteUsers | D29: Abate, Nicholas (Serco NA) | E29: Nicholas.Abate@serco-na.com | F29: Migrate | G29: =_xlfn.XLOOKUP(E29,[1]QuestALL!$B:$B,[1]QuestALL!$E:$E) -> #N/A | H29: =_xlfn.XLOOKUP(E29,'[2]exportUsers_2026-4-16'!$C:$C,'[2]exportUsers_2026-4-16'!$D:$D) -> #N/A
A30: https://serco.sharepoint.com/sites/AFSFMarketTeam | B30: Acquisition Management (AQM) | C30: SiteUsers | D30: Abdeljaber, Jennifer, J (Serco NA) | E30: Nassebeh.StJohn@serco-na.com | F30: Migrate | G30: =_xlfn.XLOOKUP(E30,[1]QuestALL!$B:$B,[1]QuestALL!$E:$E) -> #N/A | H30: =_xlfn.XLOOKUP(E30,'[2]exportUsers_2026-4-16'!$C:$C,'[2]exportUsers_2026-4-16'!$D:$D) -> #N/A
A31: https://serco.sharepoint.com/sites/AFSFMarketTeam | B31: Acquisition Management (AQM) | C31: SiteUsers | D31: Ablay, Timothy (Serco NA US) | E31: Timothy.Ablay@serco-na.com | F31: Migrate | G31: =_xlfn.XLOOKUP(E31,[1]QuestALL!$B:$B,[1]QuestALL!$E:$E) -> Migrated | H31: =_xlfn.XLOOKUP(E31,'[2]exportUsers_2026-4-16'!$C:$C,'[2]exportUsers_2026-4-16'!$D:$D) -> Member
A32: https://serco.sharepoint.com/sites/AFSFMarketTeam | B32: Acquisition Management (AQM) | C32: SiteUsers | D32: Abraham, Jincy (Serco ME) | E32: Jincy.Abraham@serco.ae | F32: Migrate | G32: =_xlfn.XLOOKUP(E32,[1]QuestALL!$B:$B,[1]QuestALL!$E:$E) -> #N/A | H32: =_xlfn.XLOOKUP(E32,'[2]exportUsers_2026-4-16'!$C:$C,'[2]exportUsers_2026-4-16'!$D:$D) -> #N/A
A33: https://serco.sharepoint.com/sites/AFSFMarketTeam | B33: Acquisition Management (AQM) | C33: SiteUsers | D33: Adleson, Richard, B (Serco NA US) | E33: Richard.Adleson@serco-na.com | F33: Migrate | G33: =_xlfn.XLOOKUP(E33,[1]QuestALL!$B:$B,[1]QuestALL!$E:$E) -> #N/A | H33: =_xlfn.XLOOKUP(E33,'[2]exportUsers_2026-4-16'!$C:$C,'[2]exportUsers_2026-4-16'!$D:$D) -> #N/A
A34: https://serco.sharepoint.com/sites/AFSFMarketTeam | B34: Acquisition Management (AQM) | C34: SiteUsers | D34: AdminM365AuditReport | E34: AdminM365AuditReport@serco.onmicrosoft.com | F34: Migrate | G34: =_xlfn.XLOOKUP(E34,[1]QuestALL!$B:$B,[1]QuestALL!$E:$E) -> #N/A | H34: =_xlfn.XLOOKUP(E34,'[2]exportUsers_2026-4-16'!$C:$C,'[2]exportUsers_2026-4-16'!$D:$D) -> #N/A
A35: https://serco.sharepoint.com/sites/AFSFMarketTeam | B35: Acquisition Management (AQM) | C35: SiteUsers | D35: AF/SF Market Team Members | E35: AFSFMarketTeam@serco.onmicrosoft.com | F35: Migrate | G35: =_xlfn.XLOOKUP(E35,[1]QuestALL!$B:$B,[1]QuestALL!$E:$E) -> #N/A | H35: =_xlfn.XLOOKUP(E35,'[2]exportUsers_2026-4-16'!$C:$C,'[2]exportUsers_2026-4-16'!$D:$D) -> #N/A
A36: https://serco.sharepoint.com/sites/AFSFMarketTeam | B36: Acquisition Management (AQM) | C36: SiteUsers | D36: AF/SF Market Team Owners | E36: AFSFMarketTeam@serco.onmicrosoft.com | F36: Migrate | G36: =_xlfn.XLOOKUP(E36,[1]QuestALL!$B:$B,[1]QuestALL!$E:$E) -> #N/A | H36: =_xlfn.XLOOKUP(E36,'[2]exportUsers_2026-4-16'!$C:$C,'[2]exportUsers_2026-4-16'!$D:$D) -> #N/A
A37: https://serco.sharepoint.com/sites/AFSFMarketTeam | B37: Acquisition Management (AQM) | C37: SiteUsers | D37: Aguilar, Francisco (Serco NA US) | E37: Francisco.Aguilar@serco-na.com | F37: Migrate | G37: =_xlfn.XLOOKUP(E37,[1]QuestALL!$B:$B,[1]QuestALL!$E:$E) -> #N/A | H37: =_xlfn.XLOOKUP(E37,'[2]exportUsers_2026-4-16'!$C:$C,'[2]exportUsers_2026-4-16'!$D:$D) -> Member
A38: https://serco.sharepoint.com/sites/AFSFMarketTeam | B38: Acquisition Management (AQM) | C38: SiteUsers | D38: Aguilera, Kellie (Serco NA US) | E38: Kellie.Aguilera@serco-na.com | F38: Migrate | G38: =_xlfn.XLOOKUP(E38,[1]QuestALL!$B:$B,[1]QuestALL!$E:$E) -> #N/A | H38: =_xlfn.XLOOKUP(E38,'[2]exportUsers_2026-4-16'!$C:$C,'[2]exportUsers_2026-4-16'!$D:$D) -> #N/A
A39: https://serco.sharepoint.com/sites/AFSFMarketTeam | B39: Acquisition Management (AQM) | C39: SiteUsers | D39: Ahern, Robert, E (Serco NA US) | E39: rahern@serco-na.com | F39: Migrate | G39: =_xlfn.XLOOKUP(E39,[1]QuestALL!$B:$B,[1]QuestALL!$E:$E) -> Mapped | H39: =_xlfn.XLOOKUP(E39,'[2]exportUsers_2026-4-16'!$C:$C,'[2]exportUsers_2026-4-16'!$D:$D) -> Member
A40: https://serco.sharepoint.com/sites/AFSFMarketTeam | B40: Acquisition Management (AQM) | C40: SiteUsers | D40: Ahmed, Humdan, J (Serco NA US) | E40: Humdan.Ahmed@serco-na.com | F40: Migrate | G40: =_xlfn.XLOOKUP(E40,[1]QuestALL!$B:$B,[1]QuestALL!$E:$E) -> Mapped | H40: =_xlfn.XLOOKUP(E40,'[2]exportUsers_2026-4-16'!$C:$C,'[2]exportUsers_2026-4-16'!$D:$D) -> Member
... A45: https://serco.sharepoint.com/sites/AFSFMarketTeam | B45: Acquisition Management (AQM) | C45: SiteUsers | D45: Allen, David, N (Serco NA) | E45: David.N.Allen@serco-na.com | F45: Migrate | G45: =_xlfn.XLOOKUP(E45,[1]QuestALL!$B:$B,[1]QuestALL!$E:$E) -> Mapped | H45: =_xlfn.XLOOKUP(E45,'[2]exportUsers_2026-4-16'!$C:$C,'[2]exportUsers_2026-4-16'!$D:$D) -> Member
A46: https://serco.sharepoint.com/sites/AFSFMarketTeam | B46: Acquisition Management (AQM) | C46: SiteUsers | D46: All Users (windows) | F46: Migrate | G46: =_xlfn.XLOOKUP(E46,[1]QuestALL!$B:$B,[1]QuestALL!$E:$E) -> 0 | H46: =_xlfn.XLOOKUP(E46,'[2]exportUsers_2026-4-16'!$C:$C,'[2]exportUsers_2026-4-16'!$D:$D) -> #N/A
A47: https://serco.sharepoint.com/sites/AFSFMarketTeam | B47: Acquisition Management (AQM) | C47: SiteUsers | D47: Alston, Saad, A (Serco NA US) | E47: Saad.Alston@serco-na.com | F47: Migrate | G47: =_xlfn.XLOOKUP(E47,[1]QuestALL!$B:$B,[1]QuestALL!$E:$E) -> #N/A | H47: =_xlfn.XLOOKUP(E47,'[2]exportUsers_2026-4-16'!$C:$C,'[2]exportUsers_2026-4-16'!$D:$D) -> #N/A
A48: https://serco.sharepoint.com/sites/AFSFMarketTeam | B48: Acquisition Management (AQM) | C48: SiteUsers | D48: Altwies, Meighan, K (Serco NA US) | E48: Meighan.Altwies@serco-na.com | F48: Migrate | G48: =_xlfn.XLOOKUP(E48,[1]QuestALL!$B:$B,[1]QuestALL!$E:$E) -> Mapped | H48: =_xlfn.XLOOKUP(E48,'[2]exportUsers_2026-4-16'!$C:$C,'[2]exportUsers_2026-4-16'!$D:$D) -> Member
A49: https://serco.sharepoint.com/sites/AFSFMarketTeam | B49: Acquisition Management (AQM) | C49: SiteUsers | D49: Alwahab, Hussein (Serco NA US) | E49: Hussein.Alwahab@serco-na.com | F49: Migrate | G49: =_xlfn.XLOOKUP(E49,[1]QuestALL!$B:$B,[1]QuestALL!$E:$E) -> #N/A | H49: =_xlfn.XLOOKUP(E49,'[2]exportUsers_2026-4-16'!$C:$C,'[2]exportUsers_2026-4-16'!$D:$D) -> #N/A
A50: https://serco.sharepoint.com/sites/AFSFMarketTeam | B50: Acquisition Management (AQM) | C50: SiteUsers | D50: Amalraj, Vanessa (Serco ASPAC) | E50: Vanessa.Amalraj@serco-ap.com | F50: Migrate | G50: =_xlfn.XLOOKUP(E50,[1]QuestALL!$B:$B,[1]QuestALL!$E:$E) -> #N/A | H50: =_xlfn.XLOOKUP(E50,'[2]exportUsers_2026-4-16'!$C:$C,'[2]exportUsers_2026-4-16'!$D:$D) -> #N/A
A51: https://serco.sharepoint.com/sites/AFSFMarketTeam | B51: Acquisition Management (AQM) | C51: SiteUsers | D51: Amato, Vincent (Serco NA) | E51: Vincent.Amato@serco-na.com | F51: Migrate | G51: =_xlfn.XLOOKUP(E51,[1]QuestALL!$B:$B,[1]QuestALL!$E:$E) -> Migrated | H51: =_xlfn.XLOOKUP(E51,'[2]exportUsers_2026-4-16'!$C:$C,'[2]exportUsers_2026-4-16'!$D:$D) -> Member
A52: https://serco.sharepoint.com/sites/AFSFMarketTeam | B52: Acquisition Management (AQM) | C52: SiteUsers | D52: Ambrosio, Leonard (Serco NA US) | E52: Leonard.Ambrosio@serco-na.com | F52: Migrate | G52: =_xlfn.XLOOKUP(E52,[1]QuestALL!$B:$B,[1]QuestALL!$E:$E) -> #N/A | H52: =_xlfn.XLOOKUP(E52,'[2]exportUsers_2026-4-16'!$C:$C,'[2]exportUsers_2026-4-16'!$D:$D) -> #N/A
A53: https://serco.sharepoint.com/sites/AFSFMarketTeam | B53: Acquisition Management (AQM) | C53: SiteUsers | D53: Ammerman, Ann, E (Serco NA US) | E53: Ann.Ammerman@serco-na.com | F53: Migrate | G53: =_xlfn.XLOOKUP(E53,[1]QuestALL!$B:$B,[1]QuestALL!$E:$E) -> #N/A | H53: =_xlfn.XLOOKUP(E53,'[2]exportUsers_2026-4-16'!$C:$C,'[2]exportUsers_2026-4-16'!$D:$D) -> #N/A
A54: https://serco.sharepoint.com/sites/AFSFMarketTeam | B54: Acquisition Management (AQM) | C54: SiteUsers | D54: Amode, Sheriff (Serco ME) | E54: Sheriff.Amode@serco.ae | F54: Migrate | G54: =_xlfn.XLOOKUP(E54,[1]QuestALL!$B:$B,[1]QuestALL!$E:$E) -> #N/A | H54: =_xlfn.XLOOKUP(E54,'[2]exportUsers_2026-4-16'!$C:$C,'[2]exportUsers_2026-4-16'!$D:$D) -> #N/A
A55: https://serco.sharepoint.com/sites/AFSFMarketTeam | B55: Acquisition Management (AQM) | C55: SiteUsers | D55: Andersen, Dana, J (Serco NA US) | E55: Dana.Andersen@serco-na.com | F55: Migrate | G55: =_xlfn.XLOOKUP(E55,[1]QuestALL!$B:$B,[1]QuestALL!$E:$E) -> Mapped | H55: =_xlfn.XLOOKUP(E55,'[2]exportUsers_2026-4-16'!$C:$C,'[2]exportUsers_2026-4-16'!$D:$D) -> Member
A56: https://serco.sharepoint.com/sites/AFSFMarketTeam | B56: Acquisition Management (AQM) | C56: SiteUsers | D56: Anderson, David, W (Serco NA US) | E56: David.Anderson@serco-na.com | F56: Migrate | G56: =_xlfn.XLOOKUP(E56,[1]QuestALL!$B:$B,[1]QuestALL!$E:$E) -> #N/A | H56: =_xlfn.XLOOKUP(E56,'[2]exportUsers_2026-4-16'!$C:$C,'[2]exportUsers_2026-4-16'!$D:$D) -> #N/A
A57: https://serco.sharepoint.com/sites/AFSFMarketTeam | B57: Acquisition Management (AQM) | C57: SiteUsers | D57: Anderson, Easton, R (Serco NA US) | E57: Easton.Anderson@serco-na.com | F57: Migrate | G57: =_xlfn.XLOOKUP(E57,[1]QuestALL!$B:$B,[1]QuestALL!$E:$E) -> #N/A | H57: =_xlfn.XLOOKUP(E57,'[2]exportUsers_2026-4-16'!$C:$C,'[2]exportUsers_2026-4-16'!$D:$D) -> #N/A
A58: https://serco.sharepoint.com/sites/AFSFMarketTeam | B58: Acquisition Management (AQM) | C58: SiteUsers | D58: Anderson, Shawn (Serco ASPAC) | E58: Shawn.Anderson@serco-ap.com | F58: Migrate | G58: =_xlfn.XLOOKUP(E58,[1]QuestALL!$B:$B,[1]QuestALL!$E:$E) -> #N/A | H58: =_xlfn.XLOOKUP(E58,'[2]exportUsers_2026-4-16'!$C:$C,'[2]exportUsers_2026-4-16'!$D:$D) -> #N/A
... A84: https://serco.sharepoint.com/sites/AFSFMarketTeam | B84: Acquisition Management (AQM) | C84: SiteUsers | D84: Barron, Daniel (Serco ASPAC) | E84: Daniel.Barron@serco-ap.com | F84: Migrate | G84: =_xlfn.XLOOKUP(E84,[1]QuestALL!$B:$B,[1]QuestALL!$E:$E) -> #N/A | H84: =_xlfn.XLOOKUP(E84,'[2]exportUsers_2026-4-16'!$C:$C,'[2]exportUsers_2026-4-16'!$D:$D) -> #N/A
A85: https://serco.sharepoint.com/sites/AFSFMarketTeam | B85: Acquisition Management (AQM) | C85: SiteUsers | D85: Bartholomew, Robert - Cloud Admin (Serco NA) | F85: Migrate | G85: =_xlfn.XLOOKUP(E85,[1]QuestALL!$B:$B,[1]QuestALL!$E:$E) -> 0 | H85: =_xlfn.XLOOKUP(E85,'[2]exportUsers_2026-4-16'!$C:$C,'[2]exportUsers_2026-4-16'!$D:$D) -> #N/A
A86: https://serco.sharepoint.com/sites/AFSFMarketTeam | B86: Acquisition Management (AQM) | C86: SiteUsers | D86: Bartley, Danielle (Serco NA) | E86: Danielle.Bartley@serco-na.com | F86: Migrate | G86: =_xlfn.XLOOKUP(E86,[1]QuestALL!$B:$B,[1]QuestALL!$E:$E) -> #N/A | H86: =_xlfn.XLOOKUP(E86,'[2]exportUsers_2026-4-16'!$C:$C,'[2]exportUsers_2026-4-16'!$D:$D) -> Member
A87: https://serco.sharepoint.com/sites/AFSFMarketTeam | B87: Acquisition Management (AQM) | C87: SiteUsers | D87: Barton, Mike, L (Serco NA) | E87: Michael.Barton@serco-na.com | F87: Migrate | G87: =_xlfn.XLOOKUP(E87,[1]QuestALL!$B:$B,[1]QuestALL!$E:$E) -> Mapped | H87: =_xlfn.XLOOKUP(E87,'[2]exportUsers_2026-4-16'!$C:$C,'[2]exportUsers_2026-4-16'!$D:$D) -> Member
A88: https://serco.sharepoint.com/sites/AFSFMarketTeam | B88: Acquisition Management (AQM) | C88: SiteUsers | D88: Bassely, Shery (Serco NA US) | E88: Shery.Bassely@serco-na.com | F88: Migrate | G88: =_xlfn.XLOOKUP(E88,[1]QuestALL!$B:$B,[1]QuestALL!$E:$E) -> #N/A | H88: =_xlfn.XLOOKUP(E88,'[2]exportUsers_2026-4-16'!$C:$C,'[2]exportUsers_2026-4-16'!$D:$D) -> #N/A
A89: https://serco.sharepoint.com/sites/AFSFMarketTeam | B89: Acquisition Management (AQM) | C89: SiteUsers | D89: Batista, Alejandro (Serco NA US) | E89: Alejandro.Batista@serco-na.com | F89: Migrate | G89: =_xlfn.XLOOKUP(E89,[1]QuestALL!$B:$B,[1]QuestALL!$E:$E) -> #N/A | H89: =_xlfn.XLOOKUP(E89,'[2]exportUsers_2026-4-16'!$C:$C,'[2]exportUsers_2026-4-16'!$D:$D) -> Member
A90: https://serco.sharepoint.com/sites/AFSFMarketTeam | B90: Acquisition Management (AQM) | C90: SiteUsers | D90: Bauer, Vanessa, K (Serco NA US) | E90: Vanessa.Bauer@serco-na.com | F90: Migrate | G90: =_xlfn.XLOOKUP(E90,[1]QuestALL!$B:$B,[1]QuestALL!$E:$E) -> Migrated | H90: =_xlfn.XLOOKUP(E90,'[2]exportUsers_2026-4-16'!$C:$C,'[2]exportUsers_2026-4-16'!$D:$D) -> Member
A91: https://serco.sharepoint.com/sites/AFSFMarketTeam | B91: Acquisition Management (AQM) | C91: SiteUsers | D91: Baumler, Sabrina, E (Serco NA US) | E91: Sabrina.Baumler@serco-na.com | F91: Migrate | G91: =_xlfn.XLOOKUP(E91,[1]QuestALL!$B:$B,[1]QuestALL!$E:$E) -> #N/A | H91: =_xlfn.XLOOKUP(E91,'[2]exportUsers_2026-4-16'!$C:$C,'[2]exportUsers_2026-4-16'!$D:$D) -> Member
A92: https://serco.sharepoint.com/sites/AFSFMarketTeam | B92: Acquisition Management (AQM) | C92: SiteUsers | D92: Beales, Brian, O (Serco NA) | E92: Brian.Beales@serco-na.com | F92: Migrate | G92: =_xlfn.XLOOKUP(E92,[1]QuestALL!$B:$B,[1]QuestALL!$E:$E) -> Migrated | H92: =_xlfn.XLOOKUP(E92,'[2]exportUsers_2026-4-16'!$C:$C,'[2]exportUsers_2026-4-16'!$D:$D) -> Member
A93: https://serco.sharepoint.com/sites/AFSFMarketTeam | B93: Acquisition Management (AQM) | C93: SiteUsers | D93: Bednarcik, Ray, S (Serco NA US) | E93: Raymond.Bednarcik@serco-na.com | F93: Migrate | G93: =_xlfn.XLOOKUP(E93,[1]QuestALL!$B:$B,[1]QuestALL!$E:$E) -> #N/A | H93: =_xlfn.XLOOKUP(E93,'[2]exportUsers_2026-4-16'!$C:$C,'[2]exportUsers_2026-4-16'!$D:$D) -> #N/A
A94: https://serco.sharepoint.com/sites/AFSFMarketTeam | B94: Acquisition Management (AQM) | C94: SiteUsers | D94: Bekisz, Kevin (Serco ASPAC) | E94: Kevin.Bekisz@serco-ap.com | F94: Migrate | G94: =_xlfn.XLOOKUP(E94,[1]QuestALL!$B:$B,[1]QuestALL!$E:$E) -> #N/A | H94: =_xlfn.XLOOKUP(E94,'[2]exportUsers_2026-4-16'!$C:$C,'[2]exportUsers_2026-4-16'!$D:$D) -> #N/A
A95: https://serco.sharepoint.com/sites/AFSFMarketTeam | B95: Acquisition Management (AQM) | C95: SiteUsers | D95: Bell, Amber, D (Serco NA) | E95: Amber.Bell@serco-na.com | F95: Migrate | G95: =_xlfn.XLOOKUP(E95,[1]QuestALL!$B:$B,[1]QuestALL!$E:$E) -> #N/A | H95: =_xlfn.XLOOKUP(E95,'[2]exportUsers_2026-4-16'!$C:$C,'[2]exportUsers_2026-4-16'!$D:$D) -> Member
A96: https://serco.sharepoint.com/sites/AFSFMarketTeam | B96: Acquisition Management (AQM) | C96: SiteUsers | D96: Bell, Edwin, M (Serco NA) | E96: Edwin.Bell@serco-na.com | F96: Migrate | G96: =_xlfn.XLOOKUP(E96,[1]QuestALL!$B:$B,[1]QuestALL!$E:$E) -> #N/A | H96: =_xlfn.XLOOKUP(E96,'[2]exportUsers_2026-4-16'!$C:$C,'[2]exportUsers_2026-4-16'!$D:$D) -> Member
A97: https://serco.sharepoint.com/sites/AFSFMarketTeam | B97: Acquisition Management (AQM) | C97: SiteUsers | D97: Bennett, Mark, A (Serco NA US) | E97: Mark.Bennett@serco-na.com | F97: Migrate | G97: =_xlfn.XLOOKUP(E97,[1]QuestALL!$B:$B,[1]QuestALL!$E:$E) -> #N/A | H97: =_xlfn.XLOOKUP(E97,'[2]exportUsers_2026-4-16'!$C:$C,'[2]exportUsers_2026-4-16'!$D:$D) -> #N/A
... A303: https://serco.sharepoint.com/sites/AFSFMarketTeam | B303: Acquisition Management (AQM) | C303: SiteUsers | D303: Eveleigh, Karl (Group) | E303: Karl.Eveleigh@serco.com | F303: Migrate | G303: =_xlfn.XLOOKUP(E303,[1]QuestALL!$B:$B,[1]QuestALL!$E:$E) -> #N/A | H303: =_xlfn.XLOOKUP(E303,'[2]exportUsers_2026-4-16'!$C:$C,'[2]exportUsers_2026-4-16'!$D:$D) -> #N/A
A304: https://serco.sharepoint.com/sites/AFSFMarketTeam | B304: Acquisition Management (AQM) | C304: SiteUsers | D304: Everyone | F304: Migrate | G304: =_xlfn.XLOOKUP(E304,[1]QuestALL!$B:$B,[1]QuestALL!$E:$E) -> #N/A | H304: =_xlfn.XLOOKUP(E304,'[2]exportUsers_2026-4-16'!$C:$C,'[2]exportUsers_2026-4-16'!$D:$D) -> #N/A
A305: https://serco.sharepoint.com/sites/AFSFMarketTeam | B305: Acquisition Management (AQM) | C305: SiteUsers | D305: Everyone except external users | F305: Migrate | G305: =_xlfn.XLOOKUP(E305,[1]QuestALL!$B:$B,[1]QuestALL!$E:$E) -> #N/A | H305: =_xlfn.XLOOKUP(E305,'[2]exportUsers_2026-4-16'!$C:$C,'[2]exportUsers_2026-4-16'!$D:$D) -> #N/A
A306: https://serco.sharepoint.com/sites/AFSFMarketTeam | B306: Acquisition Management (AQM) | C306: SiteUsers | D306: Ewane, Kome - CTR | E306: Kome.Ewane@serco-na.com | F306: Migrate | G306: =_xlfn.XLOOKUP(E306,[1]QuestALL!$B:$B,[1]QuestALL!$E:$E) -> #N/A | H306: =_xlfn.XLOOKUP(E306,'[2]exportUsers_2026-4-16'!$C:$C,'[2]exportUsers_2026-4-16'!$D:$D) -> Member
A307: https://serco.sharepoint.com/sites/AFSFMarketTeam | B307: Acquisition Management (AQM) | C307: SiteUsers | D307: Ezinwa, Collins | E307: Collins.Ezinwa@serco.com | F307: Migrate | G307: =_xlfn.XLOOKUP(E307,[1]QuestALL!$B:$B,[1]QuestALL!$E:$E) -> #N/A | H307: =_xlfn.XLOOKUP(E307,'[2]exportUsers_2026-4-16'!$C:$C,'[2]exportUsers_2026-4-16'!$D:$D) -> #N/A
A308: https://serco.sharepoint.com/sites/AFSFMarketTeam | B308: Acquisition Management (AQM) | C308: SiteUsers | D308: Fagan, Bentley, D (Serco NA) | E308: Bentley.Fagan@serco-na.com | F308: Migrate | G308: =_xlfn.XLOOKUP(E308,[1]QuestALL!$B:$B,[1]QuestALL!$E:$E) -> #N/A | H308: =_xlfn.XLOOKUP(E308,'[2]exportUsers_2026-4-16'!$C:$C,'[2]exportUsers_2026-4-16'!$D:$D) -> #N/A
A309: https://serco.sharepoint.com/sites/AFSFMarketTeam | B309: Acquisition Management (AQM) | C309: SiteUsers | D309: Faison, Celeste, G (Serco NA) | E309: cfaison@serco-na.com | F309: Migrate | G309: =_xlfn.XLOOKUP(E309,[1]QuestALL!$B:$B,[1]QuestALL!$E:$E) -> #N/A | H309: =_xlfn.XLOOKUP(E309,'[2]exportUsers_2026-4-16'!$C:$C,'[2]exportUsers_2026-4-16'!$D:$D) -> #N/A
A310: https://serco.sharepoint.com/sites/AFSFMarketTeam | B310: Acquisition Management (AQM) | C310: SiteUsers | D310: Falzone, Joe, E (Serco NA) | E310: Joe.Falzone@serco-na.com | F310: Migrate | G310: =_xlfn.XLOOKUP(E310,[1]QuestALL!$B:$B,[1]QuestALL!$E:$E) -> Migrated | H310: =_xlfn.XLOOKUP(E310,'[2]exportUsers_2026-4-16'!$C:$C,'[2]exportUsers_2026-4-16'!$D:$D) -> Member
A311: https://serco.sharepoint.com/sites/AFSFMarketTeam | B311: Acquisition Management (AQM) | C311: SiteUsers | D311: Farley, Blake, C (Serco NA US) | E311: Blake.Farley@serco-na.com | F311: Migrate | G311: =_xlfn.XLOOKUP(E311,[1]QuestALL!$B:$B,[1]QuestALL!$E:$E) -> Migrated | H311: =_xlfn.XLOOKUP(E311,'[2]exportUsers_2026-4-16'!$C:$C,'[2]exportUsers_2026-4-16'!$D:$D) -> Member
A312: https://serco.sharepoint.com/sites/AFSFMarketTeam | B312: Acquisition Management (AQM) | C312: SiteUsers | D312: Farley, Randal, D (Serco NA US) | E312: Randal.Farley@serco-na.com | F312: Migrate | G312: =_xlfn.XLOOKUP(E312,[1]QuestALL!$B:$B,[1]QuestALL!$E:$E) -> #N/A | H312: =_xlfn.XLOOKUP(E312,'[2]exportUsers_2026-4-16'!$C:$C,'[2]exportUsers_2026-4-16'!$D:$D) -> #N/A
A313: https://serco.sharepoint.com/sites/AFSFMarketTeam | B313: Acquisition Management (AQM) | C313: SiteUsers | D313: Farotte-Kruchas, Rick, E (Serco NA US) | E313: Richard.Farotte@serco-na.com | F313: Migrate | G313: =_xlfn.XLOOKUP(E313,[1]QuestALL!$B:$B,[1]QuestALL!$E:$E) -> #N/A | H313: =_xlfn.XLOOKUP(E313,'[2]exportUsers_2026-4-16'!$C:$C,'[2]exportUsers_2026-4-16'!$D:$D) -> #N/A
A314: https://serco.sharepoint.com/sites/AFSFMarketTeam | B314: Acquisition Management (AQM) | C314: SiteUsers | D314: Federkeil, Jeremy, K (Serco NA US) | E314: Jeremy.Federkeil@serco-na.com | F314: Migrate | G314: =_xlfn.XLOOKUP(E314,[1]QuestALL!$B:$B,[1]QuestALL!$E:$E) -> #N/A | H314: =_xlfn.XLOOKUP(E314,'[2]exportUsers_2026-4-16'!$C:$C,'[2]exportUsers_2026-4-16'!$D:$D) -> #N/A
A315: https://serco.sharepoint.com/sites/AFSFMarketTeam | B315: Acquisition Management (AQM) | C315: SiteUsers | D315: Fells, Lisa, G (Serco NA) | E315: Lisa.Fells@serco-na.com | F315: Migrate | G315: =_xlfn.XLOOKUP(E315,[1]QuestALL!$B:$B,[1]QuestALL!$E:$E) -> #N/A | H315: =_xlfn.XLOOKUP(E315,'[2]exportUsers_2026-4-16'!$C:$C,'[2]exportUsers_2026-4-16'!$D:$D) -> #N/A
A316: https://serco.sharepoint.com/sites/AFSFMarketTeam | B316: Acquisition Management (AQM) | C316: SiteUsers | D316: Fenton, Joshua | E316: joshua.fenton@serco.com | F316: Migrate | G316: =_xlfn.XLOOKUP(E316,[1]QuestALL!$B:$B,[1]QuestALL!$E:$E) -> #N/A | H316: =_xlfn.XLOOKUP(E316,'[2]exportUsers_2026-4-16'!$C:$C,'[2]exportUsers_2026-4-16'!$D:$D) -> #N/A
A317: https://serco.sharepoint.com/sites/AFSFMarketTeam | B317: Acquisition Management (AQM) | C317: SiteUsers | D317: Fidler, Paul, P (Serco NA US) | E317: Paul.Fidler@serco-na.com | F317: Migrate | G317: =_xlfn.XLOOKUP(E317,[1]QuestALL!$B:$B,[1]QuestALL!$E:$E) -> #N/A | H317: =_xlfn.XLOOKUP(E317,'[2]exportUsers_2026-4-16'!$C:$C,'[2]exportUsers_2026-4-16'!$D:$D) -> #N/A
... A701: https://serco.sharepoint.com/sites/AFSFMarketTeam | B701: Acquisition Management (AQM) | C701: SiteUsers | D701: Nouledo, Koffi, Z (Serco NA US) | E701: Koffi.Nouledo@serco-na.com | F701: Migrate | G701: =_xlfn.XLOOKUP(E701,[1]QuestALL!$B:$B,[1]QuestALL!$E:$E) -> #N/A | H701: =_xlfn.XLOOKUP(E701,'[2]exportUsers_2026-4-16'!$C:$C,'[2]exportUsers_2026-4-16'!$D:$D) -> #N/A
A702: https://serco.sharepoint.com/sites/AFSFMarketTeam | B702: Acquisition Management (AQM) | C702: SiteUsers | D702: NT AUTHORITY\LOCAL SERVICE | F702: Migrate | G702: =_xlfn.XLOOKUP(E702,[1]QuestALL!$B:$B,[1]QuestALL!$E:$E) -> #N/A | H702: =_xlfn.XLOOKUP(E702,'[2]exportUsers_2026-4-16'!$C:$C,'[2]exportUsers_2026-4-16'!$D:$D) -> #N/A
A703: https://serco.sharepoint.com/sites/AFSFMarketTeam | B703: Acquisition Management (AQM) | C703: SiteUsers | D703: NT Service\spsearch | F703: Migrate | G703: =_xlfn.XLOOKUP(E703,[1]QuestALL!$B:$B,[1]QuestALL!$E:$E) -> #N/A | H703: =_xlfn.XLOOKUP(E703,'[2]exportUsers_2026-4-16'!$C:$C,'[2]exportUsers_2026-4-16'!$D:$D) -> #N/A
A704: https://serco.sharepoint.com/sites/AFSFMarketTeam | B704: Acquisition Management (AQM) | C704: SiteUsers | D704: Nylander-Freeman, Elisa, J (Serco NA US) | E704: Elisa.NylanderFreema@serco-na.com | F704: Migrate | G704: =_xlfn.XLOOKUP(E704,[1]QuestALL!$B:$B,[1]QuestALL!$E:$E) -> #N/A | H704: =_xlfn.XLOOKUP(E704,'[2]exportUsers_2026-4-16'!$C:$C,'[2]exportUsers_2026-4-16'!$D:$D) -> #N/A
A705: https://serco.sharepoint.com/sites/AFSFMarketTeam | B705: Acquisition Management (AQM) | C705: SiteUsers | D705: Oakes, Dave | E705: dave_oakes@serco.com | F705: Migrate | G705: =_xlfn.XLOOKUP(E705,[1]QuestALL!$B:$B,[1]QuestALL!$E:$E) -> #N/A | H705: =_xlfn.XLOOKUP(E705,'[2]exportUsers_2026-4-16'!$C:$C,'[2]exportUsers_2026-4-16'!$D:$D) -> #N/A
A706: https://serco.sharepoint.com/sites/AFSFMarketTeam | B706: Acquisition Management (AQM) | C706: SiteUsers | D706: Ober, Tom (Serco NA US) | E706: Thomas.Ober@serco-na.com | F706: Migrate | G706: =_xlfn.XLOOKUP(E706,[1]QuestALL!$B:$B,[1]QuestALL!$E:$E) -> Migrated | H706: =_xlfn.XLOOKUP(E706,'[2]exportUsers_2026-4-16'!$C:$C,'[2]exportUsers_2026-4-16'!$D:$D) -> Member
A707: https://serco.sharepoint.com/sites/AFSFMarketTeam | B707: Acquisition Management (AQM) | C707: SiteUsers | D707: Obiofuma, Judith, N (Serco NA US) | E707: Judith.Obiofuma@serco-na.com | F707: Migrate | G707: =_xlfn.XLOOKUP(E707,[1]QuestALL!$B:$B,[1]QuestALL!$E:$E) -> #N/A | H707: =_xlfn.XLOOKUP(E707,'[2]exportUsers_2026-4-16'!$C:$C,'[2]exportUsers_2026-4-16'!$D:$D) -> Member
A708: https://serco.sharepoint.com/sites/AFSFMarketTeam | B708: Acquisition Management (AQM) | C708: SiteUsers | D708: o-bsabir | E708: o-bsabir@serco-na.com | F708: Migrate | G708: =_xlfn.XLOOKUP(E708,[1]QuestALL!$B:$B,[1]QuestALL!$E:$E) -> #N/A | H708: =_xlfn.XLOOKUP(E708,'[2]exportUsers_2026-4-16'!$C:$C,'[2]exportUsers_2026-4-16'!$D:$D) -> Member
A709: https://serco.sharepoint.com/sites/AFSFMarketTeam | B709: Acquisition Management (AQM) | C709: SiteUsers | D709: Ochoa, Anna, M (Serco NA US) | E709: Anna.Ochoa@serco-na.com | F709: Migrate | G709: =_xlfn.XLOOKUP(E709,[1]QuestALL!$B:$B,[1]QuestALL!$E:$E) -> #N/A | H709: =_xlfn.XLOOKUP(E709,'[2]exportUsers_2026-4-16'!$C:$C,'[2]exportUsers_2026-4-16'!$D:$D) -> #N/A
A710: https://serco.sharepoint.com/sites/AFSFMarketTeam | B710: Acquisition Management (AQM) | C710: SiteUsers | D710: o-fkruk | E710: o-fkruk@serco-na.com | F710: Migrate | G710: =_xlfn.XLOOKUP(E710,[1]QuestALL!$B:$B,[1]QuestALL!$E:$E) -> #N/A | H710: =_xlfn.XLOOKUP(E710,'[2]exportUsers_2026-4-16'!$C:$C,'[2]exportUsers_2026-4-16'!$D:$D) -> #N/A
A711: https://serco.sharepoint.com/sites/AFSFMarketTeam | B711: Acquisition Management (AQM) | C711: SiteUsers | D711: o-jtinsley | E711: o-jtinsley@serco.onmicrosoft.com | F711: Migrate | G711: =_xlfn.XLOOKUP(E711,[1]QuestALL!$B:$B,[1]QuestALL!$E:$E) -> #N/A | H711: =_xlfn.XLOOKUP(E711,'[2]exportUsers_2026-4-16'!$C:$C,'[2]exportUsers_2026-4-16'!$D:$D) -> #N/A
A712: https://serco.sharepoint.com/sites/AFSFMarketTeam | B712: Acquisition Management (AQM) | C712: SiteUsers | D712: o-jturner | E712: o-jturner@serco.onmicrosoft.com | F712: Migrate | G712: =_xlfn.XLOOKUP(E712,[1]QuestALL!$B:$B,[1]QuestALL!$E:$E) -> #N/A | H712: =_xlfn.XLOOKUP(E712,'[2]exportUsers_2026-4-16'!$C:$C,'[2]exportUsers_2026-4-16'!$D:$D) -> #N/A
A713: https://serco.sharepoint.com/sites/AFSFMarketTeam | B713: Acquisition Management (AQM) | C713: SiteUsers | D713: Oldham, Thomas, L (Serco NA) | E713: Thomas.Oldham@serco-na.com | F713: Migrate | G713: =_xlfn.XLOOKUP(E713,[1]QuestALL!$B:$B,[1]QuestALL!$E:$E) -> #N/A | H713: =_xlfn.XLOOKUP(E713,'[2]exportUsers_2026-4-16'!$C:$C,'[2]exportUsers_2026-4-16'!$D:$D) -> Member
A714: https://serco.sharepoint.com/sites/AFSFMarketTeam | B714: Acquisition Management (AQM) | C714: SiteUsers | D714: Olson, Miles, C (Serco NA US) | E714: Miles.Olson@serco-na.com | F714: Migrate | G714: =_xlfn.XLOOKUP(E714,[1]QuestALL!$B:$B,[1]QuestALL!$E:$E) -> Migrated | H714: =_xlfn.XLOOKUP(E714,'[2]exportUsers_2026-4-16'!$C:$C,'[2]exportUsers_2026-4-16'!$D:$D) -> Member
A715: https://serco.sharepoint.com/sites/AFSFMarketTeam | B715: Acquisition Management (AQM) | C715: SiteUsers | D715: O'Mahony, Donald (Serco NA US) | E715: Donald.O'Mahony@serco-na.com | F715: Migrate | G715: =_xlfn.XLOOKUP(E715,[1]QuestALL!$B:$B,[1]QuestALL!$E:$E) -> #N/A | H715: =_xlfn.XLOOKUP(E715,'[2]exportUsers_2026-4-16'!$C:$C,'[2]exportUsers_2026-4-16'!$D:$D) -> #N/A
... A852: https://serco.sharepoint.com/sites/AFSFMarketTeam | B852: Acquisition Management (AQM) | C852: SiteUsers | D852: Shands-Shields, Asia, C (Serco NA US) | E852: Asia.ShandsShields@serco-na.com | F852: Migrate | G852: =_xlfn.XLOOKUP(E852,[1]QuestALL!$B:$B,[1]QuestALL!$E:$E) -> #N/A | H852: =_xlfn.XLOOKUP(E852,'[2]exportUsers_2026-4-16'!$C:$C,'[2]exportUsers_2026-4-16'!$D:$D) -> #N/A
A853: https://serco.sharepoint.com/sites/AFSFMarketTeam | B853: Acquisition Management (AQM) | C853: SiteUsers | D853: SharePoint App | F853: Migrate | G853: =_xlfn.XLOOKUP(E853,[1]QuestALL!$B:$B,[1]QuestALL!$E:$E) -> #N/A | H853: =_xlfn.XLOOKUP(E853,'[2]exportUsers_2026-4-16'!$C:$C,'[2]exportUsers_2026-4-16'!$D:$D) -> #N/A
...

Sheet AFSFMarketTeam
A1: https://serco.sharepoint.com/sites/AFSFMarketTeam
A2: Francisco.Aguilar@serco-na.com | B2: =_xlfn.XLOOKUP(A2,'[3]SAM ACCT LIST'!$B:$B,'[3]SAM ACCT LIST'!$F:$F) -> Francisco.Aguilar@serco-na.us | C2: =_xlfn.XLOOKUP(A2,Permissions!E:E,Permissions!D:D) -> Aguilar, Francisco (Serco NA US)
A3: Tanvir.Ahmed@serco-na.com | B3: =_xlfn.XLOOKUP(A3,'[3]SAM ACCT LIST'!$B:$B,'[3]SAM ACCT LIST'!$F:$F) -> Tanvir.Ahmed@serco-na.us | C3: =_xlfn.XLOOKUP(A3,Permissions!E:E,Permissions!D:D) -> Ahmed, Tanvir, N (Serco NA)
A4: Lucille.Arguijo@serco-na.com | B4: =_xlfn.XLOOKUP(A4,'[3]SAM ACCT LIST'!$B:$B,'[3]SAM ACCT LIST'!$F:$F) -> Lucille.Arguijo@serco-na.us | C4: =_xlfn.XLOOKUP(A4,Permissions!E:E,Permissions!D:D) -> Arguijo, Lucille (Serco NA US)
A5: Sarah.Arthurs@serco-na.com | B5: =_xlfn.XLOOKUP(A5,'[3]SAM ACCT LIST'!$B:$B,'[3]SAM ACCT LIST'!$F:$F) -> Sarah.Arthurs@serco-na.us | C5: =_xlfn.XLOOKUP(A5,Permissions!E:E,Permissions!D:D) -> Arthurs, Sarah (Serco NA)
A6: Ishmael.Asah@serco-na.com | B6: =_xlfn.XLOOKUP(A6,'[3]SAM ACCT LIST'!$B:$B,'[3]SAM ACCT LIST'!$F:$F) -> Ishmael.Asah@serco-na.us | C6: =_xlfn.XLOOKUP(A6,Permissions!E:E,Permissions!D:D) -> Asah, Ishmael (Serco NA US)
A7: Zoya.Augustus@serco-na.com | B7: =_xlfn.XLOOKUP(A7,'[3]SAM ACCT LIST'!$B:$B,'[3]SAM ACCT LIST'!$F:$F) -> Zoya.Augustus@serco-na.us | C7: =_xlfn.XLOOKUP(A7,Permissions!E:E,Permissions!D:D) -> Augustus, Zoya (Serco NA US)
A8: Mel.Austin@serco-na.com | B8: =_xlfn.XLOOKUP(A8,'[3]SAM ACCT LIST'!$B:$B,'[3]SAM ACCT LIST'!$F:$F) -> Mel.Austin@serco-na.us | C8: =_xlfn.XLOOKUP(A8,Permissions!E:E,Permissions!D:D) -> Austin, Mel, C (Serco NA US)
A9: Danielle.Bartley@serco-na.com | B9: =_xlfn.XLOOKUP(A9,'[3]SAM ACCT LIST'!$B:$B,'[3]SAM ACCT LIST'!$F:$F) -> Danielle.Bartley@serco-na.us | C9: =_xlfn.XLOOKUP(A9,Permissions!E:E,Permissions!D:D) -> Bartley, Danielle (Serco NA)
A10: Alejandro.Batista@serco-na.com | B10: =_xlfn.XLOOKUP(A10,'[3]SAM ACCT LIST'!$B:$B,'[3]SAM ACCT LIST'!$F:$F) -> Alejandro.Batista@serco-na.us | C10: =_xlfn.XLOOKUP(A10,Permissions!E:E,Permissions!D:D) -> Batista, Alejandro (Serco NA US)
A11: Sabrina.Baumler@serco-na.com | B11: =_xlfn.XLOOKUP(A11,'[3]SAM ACCT LIST'!$B:$B,'[3]SAM ACCT LIST'!$F:$F) -> Sabrina.Baumler@serco-na.us | C11: =_xlfn.XLOOKUP(A11,Permissions!E:E,Permissions!D:D) -> Baumler, Sabrina, E (Serco NA US)
A12: Amber.Bell@serco-na.com | B12: =_xlfn.XLOOKUP(A12,'[3]SAM ACCT LIST'!$B:$B,'[3]SAM ACCT LIST'!$F:$F) -> Amber.Bell@serco-na.us | C12: =_xlfn.XLOOKUP(A12,Permissions!E:E,Permissions!D:D) -> Bell, Amber, D (Serco NA)
A13: Edwin.Bell@serco-na.com | B13: =_xlfn.XLOOKUP(A13,'[3]SAM ACCT LIST'!$B:$B,'[3]SAM ACCT LIST'!$F:$F) -> Edwin.Bell@serco-na.us | C13: =_xlfn.XLOOKUP(A13,Permissions!E:E,Permissions!D:D) -> Bell, Edwin, M (Serco NA)
... A146: Kameron.Zepeda@serco-na.com | B146: =_xlfn.XLOOKUP(A146,'[3]SAM ACCT LIST'!$B:$B,'[3]SAM ACCT LIST'!$F:$F) -> Kameron.Zepeda@serco-na.us | C146: =_xlfn.XLOOKUP(A146,Permissions!E:E,Permissions!D:D) -> Zepeda, Kam, N (Serco NA US)

Sheet WBB
A1: UserEmail | B1: WBB
A2: Francisco.Aguilar@serco-na.com | B2: =_xlfn.XLOOKUP(A2,AFSFMarketTeam!A:A,AFSFMarketTeam!B:B) -> Francisco.Aguilar@serco-na.us
A3: Laeeqa.Ahmad@serco-na.com | B3: =_xlfn.XLOOKUP(A3,AFSFMarketTeam!A:A,AFSFMarketTeam!B:B) -> #N/A
A4: Eric.Anderson@serco-na.com | B4: =_xlfn.XLOOKUP(A4,AFSFMarketTeam!A:A,AFSFMarketTeam!B:B) -> #N/A
A5: Anthony.Androsky@serco-na.com | B5: =_xlfn.XLOOKUP(A5,AFSFMarketTeam!A:A,AFSFMarketTeam!B:B) -> #N/A
A6: John.Arriza@serco-na.com | B6: =_xlfn.XLOOKUP(A6,AFSFMarketTeam!A:A,AFSFMarketTeam!B:B) -> #N/A
A7: Justice.Bailey@serco-na.com | B7: =_xlfn.XLOOKUP(A7,AFSFMarketTeam!A:A,AFSFMarketTeam!B:B) -> #N/A
A8: Phillip.Baker@serco-na.com | B8: =_xlfn.XLOOKUP(A8,AFSFMarketTeam!A:A,AFSFMarketTeam!B:B) -> #N/A
A9: Velincia.Baker@serco-na.com | B9: =_xlfn.XLOOKUP(A9,AFSFMarketTeam!A:A,AFSFMarketTeam!B:B) -> #N/A
A10: Sarah.Ballard@serco-na.com | B10: =_xlfn.XLOOKUP(A10,AFSFMarketTeam!A:A,AFSFMarketTeam!B:B) -> #N/A
A11: Veronica.Banton@serco-na.com | B11: =_xlfn.XLOOKUP(A11,AFSFMarketTeam!A:A,AFSFMarketTeam!B:B) -> #N/A
A12: Robert.Barber@serco-na.com | B12: =_xlfn.XLOOKUP(A12,AFSFMarketTeam!A:A,AFSFMarketTeam!B:B) -> #N/A
A13: Amber.Bell@serco-na.com | B13: =_xlfn.XLOOKUP(A13,AFSFMarketTeam!A:A,AFSFMarketTeam!B:B) -> Amber.Bell@serco-na.us
... A188: Casey.Zerkle@serco-na.com | B188: =_xlfn.XLOOKUP(A188,AFSFMarketTeam!A:A,AFSFMarketTeam!B:B) -> #N/A

Sheet UserAnalysis
A1: ActiveUsers | B1: Member
A3: Row Labels | B3: Count of SiteUrl
A4: Aaron.Runion@serco-na.com | B4: 1
A5: Aaron.Webb@serco-na.com | B5: 1
A6: Abroadger.Lipardo@serco-na.com | B6: 1
A7: Achim.Prosser@serco-na.com | B7: 1
A8: Adam.Blankenship@serco-na.com | B8: 14
A9: Adam.Heathman@serco-na.com | B9: 1
A10: Adam.Rosnick@serco-na.com | B10: 1
A11: Adam.Taylor@serco-na.com | B11: 1
A12: Adrienne.Kempton@serco-na.com | B12: 1
A13: ahunter@serco-na.com | B13: 3
A14: Alan.Cruz@serco-na.com | B14: 4
A15: Alan.Lipzin@serco-na.com | B15: 1
... A1014: Grand Total | B1014: 2213

Sheet SiteAnalysis
A1: UserMapped | B1: #N/A
B3: Column Labels
B4: Member | D4: #N/A | F4: Total Count of ActiveUsers | G4: Total Count of UserEmail
A5: Row Labels | B5: Count of ActiveUsers | C5: Count of UserEmail | D5: Count of ActiveUsers | E5: Count of UserEmail
A6: https://serco.sharepoint.com/sites/aaaa | D6: 13 | E6: 7 | F6: 13 | G6: 7
A7: https://serco.sharepoint.com/sites/aaaaplanning | D7: 12 | E7: 7 | F7: 12 | G7: 7
A8: https://serco.sharepoint.com/sites/AFSFMarketTeam | B8: 150 | C8: 150 | D8: 547 | E8: 540 | F8: 697 | G8: 690
A9: https://serco.sharepoint.com/sites/AFSFMarketTeam-AUiXBriefing | D9: 7 | E9: 1 | F9: 7 | G9: 1
A10: https://serco.sharepoint.com/sites/AFSFMarketTeam-RS3PMPNTPSSVP31231 | D10: 7 | E10: 1 | F10: 7 | G10: 1
A11: https://serco.sharepoint.com/sites/AFSFMarketTeam-Training | D11: 7 | E11: 1 | F11: 7 | G11: 1
A12: https://serco.sharepoint.com/sites/AFSFMarketTeam-USSFTraining | D12: 8 | E12: 2 | F12: 8 | G12: 2
A13: https://serco.sharepoint.com/sites/AFWROSpecialProjects | B13: 1 | C13: 1 | D13: 36 | E13: 28 | F13: 37 | G13: 29
A14: https://serco.sharepoint.com/sites/AFWROSpecialProjects-HBGSpecialProjects2 | D14: 14 | E14: 8 | F14: 14 | G14: 8
A15: https://serco.sharepoint.com/sites/AFWROSpecialProjects-programatics | D15: 9 | E15: 3 | F15: 9 | G15: 3
A16: https://serco.sharepoint.com/sites/ahfrm | D16: 15 | E16: 9 | F16: 15 | G16: 9
A17: https://serco.sharepoint.com/sites/AHFRMDTICKICKOFF-AHFRMDTICManagementChannel | D17: 20 | E17: 14 | F17: 20 | G17: 14
A18: https://serco.sharepoint.com/sites/AHFRMManufacturingEmails | D18: 11 | E18: 5 | F18: 11 | G18: 5
A19: https://serco.sharepoint.com/sites/AmeriCorpsWorkforceAnalysis | D19: 21 | E19: 15 | F19: 21 | G19: 15
A20: https://serco.sharepoint.com/sites/AngeloFiles | D20: 13 | E20: 7 | F20: 13 | G20: 7
A21: https://serco.sharepoint.com/sites/ArmedOverwatch | D21: 23 | E21: 17 | F21: 23 | G21: 17
A22: https://serco.sharepoint.com/sites/ArmyCONOPSTeam | B22: 1 | C22: 1 | D22: 67 | E22: 60 | F22: 68 | G22: 61
A23: https://serco.sharepoint.com/sites/armyteam | D23: 15 | E23: 9 | F23: 15 | G23: 9
A24: https://serco.sharepoint.com/sites/AUSAGroup | B24: 1 | C24: 1 | D24: 34 | E24: 27 | F24: 35 | G24: 28
A25: https://serco.sharepoint.com/sites/B-52DTICIACTeam | D25: 31 | E25: 24 | F25: 31 | G25: 24
A26: https://serco.sharepoint.com/sites/B-52LegacyTSPWS | D26: 17 | E26: 11 | F26: 17 | G26: 11
A27: https://serco.sharepoint.com/sites/B-52NucCertCollaboration | D27: 20 | E27: 14 | F27: 20 | G27: 14
A28: https://serco.sharepoint.com/sites/B-52TS | D28: 19 | E28: 13 | F28: 19 | G28: 13
A29: https://serco.sharepoint.com/sites/CBPRFI | D29: 9 | E29: 3 | F29: 9 | G29: 3
A30: https://serco.sharepoint.com/sites/ConsultancyArmyMarket-ArmyAviationConcept2040-PACOM | D30: 7 | E30: 1 | F30: 7 | G30: 1
A31: https://serco.sharepoint.com/sites/ConsultancyArmyMarket-ArmyAviationConcept2040-PACOM2 | D31: 9 | E31: 3 | F31: 9 | G31: 3
A32: https://serco.sharepoint.com/sites/ConsultancyArmyMarket-FTNovoselUASIndustryDayandAVCOEIndustryDay | D32: 9 | E32: 3 | F32: 9 | G32: 3
A33: https://serco.sharepoint.com/sites/DAFRCO24-C-0007 | D33: 17 | E33: 11 | F33: 17 | G33: 11
A34: https://serco.sharepoint.com/sites/DAFRCOBridge | D34: 11 | E34: 4 | F34: 11 | G34: 4
A35: https://serco.sharepoint.com/sites/DefenseExportabilityFeatures-Bell | D35: 17 | E35: 11 | F35: 17 | G35: 11
A36: https://serco.sharepoint.com/sites/DHSFPSAcquisition32094 | D36: 15 | E36: 9 | F36: 15 | G36: 9
A37: https://serco.sharepoint.com/sites/DigitalEnterprise-EWAACDEConsortium | D37: 12 | E37: 5 | F37: 12 | G37: 5
A38: https://serco.sharepoint.com/sites/DTICIACMAC-PoolOne | B38: 2 | C38: 2 | D38: 12 | E38: 6 | F38: 14 | G38: 8
A39: https://serco.sharepoint.com/sites/DTICIACMAC-PoolOne-IACMAC2673448SCMW | D39: 8 | E39: 2 | F39: 8 | G39: 2
A40: https://serco.sharepoint.com/sites/DTICIACMAC-PoolOne-MECSIP | D40: 8 | E40: 2 | F40: 8 | G40: 2
A41: https://serco.sharepoint.com/sites/DTICTO1Group | D41: 13 | E41: 7 | F41: 13 | G41: 7
A42: https://serco.sharepoint.com/sites/EglinWideAgileAcquisitionContractEWAAC | B42: 2 | C42: 2 | D42: 62 | E42: 55 | F42: 64 | G42: 57
A43: https://serco.sharepoint.com/sites/F-35FMKBS | D43: 11 | E43: 5 | F43: 11 | G43: 5
A44: https://serco.sharepoint.com/sites/F-35LogisticsKBS | D44: 11 | E44: 5 | F44: 11 | G44: 5
A45: https://serco.sharepoint.com/sites/F-35TeamSite | D45: 16 | E45: 11 | F45: 16 | G45: 11
A46: https://serco.sharepoint.com/sites/FDICIFWMS | B46: 2 | C46: 2 | D46: 18 | E46: 12 | F46: 20 | G46: 14
A47: https://serco.sharepoint.com/sites/FDICIFWMS-ProjectTeam | D47: 10 | E47: 4 | F47: 10 | G47: 4
A48: https://serco.sharepoint.com/sites/FEMACIDBid | B48: 2 | C48: 2 | D48: 10 | E48: 4 | F48: 12 | G48: 6
A49: https://serco.sharepoint.com/sites/GraphicsHub | D49: 9 | E49: 3 | F49: 9 | G49: 3
A50: https://serco.sharepoint.com/sites/ICERealPropertyManagementSystemOMProposal | D50: 9 | E50: 3 | F50: 9 | G50: 3
A51: https://serco.sharepoint.com/sites/JSSMOPNTPO-WrightPattersonClientSiteTeam | D51: 12 | E51: 6 | F51: 12 | G51: 6
A52: https://serco.sharepoint.com/sites/KC-135AW | D52: 11 | E52: 5 | F52: 11 | G52: 5
A53: https://serco.sharepoint.com/sites/KC-135EngineeringSupport | D53: 13 | E53: 7 | F53: 13 | G53: 7
A54: https://serco.sharepoint.com/sites/MDAThreatSystemsEngineering-ThreatProductsandServices | D54: 9 | E54: 3 | F54: 9 | G54: 3
A55: https://serco.sharepoint.com/sites/MTUASAcqSupport-Working | D55: 19 | E55: 12 | F55: 19 | G55: 12
A56: https://serco.sharepoint.com/sites/N81FCombatSystemSustainment | B56: 5 | C56: 5 | D56: 135 | E56: 129 | F56: 140 | G56: 134
A57: https://serco.sharepoint.com/sites/NavigatingBusinessWebinarSeries | D57: 18 | E57: 12 | F57: 18 | G57: 12
A58: https://serco.sharepoint.com/sites/NIHNIAID | D58: 13 | E58: 7 | F58: 13 | G58: 7
A59: https://serco.sharepoint.com/sites/NIHNIAID-CleverNellyAnalysis | D59: 10 | E59: 4 | F59: 10 | G59: 4
A60: https://serco.sharepoint.com/sites/NIHNIAID-PM | D60: 11 | E60: 5 | F60: 11 | G60: 5
A61: https://serco.sharepoint.com/sites/NIHNIAID-SuccessionPlanning | D61: 8 | E61: 2 | F61: 8 | G61: 2
A62: https://serco.sharepoint.com/sites/PNT-IndependentReviewTeam | D62: 10 | E62: 4 | F62: 10 | G62: 4
A63: https://serco.sharepoint.com/sites/PNTJSSMOLeads | D63: 15 | E63: 9 | F63: 15 | G63: 9
A64: https://serco.sharepoint.com/sites/PNTPOStrategicPlanning | D64: 11 | E64: 5 | F64: 11 | G64: 5
A65: https://serco.sharepoint.com/sites/PNTProposal2025 | D65: 9 | E65: 3 | F65: 9 | G65: 3
A66: https://serco.sharepoint.com/sites/R-EGIPhaseIIISerco | B66: 1 | C66: 1 | D66: 27 | E66: 21 | F66: 28 | G66: 22
A67: https://serco.sharepoint.com/sites/R-EGIPhaseIIISerco-R-EGILeadershipBriefingscontrolledaccess | D67: 18 | E67: 12 | F67: 18 | G67: 12
A68: https://serco.sharepoint.com/sites/SA-M365Team-WBB-COPOD | D68: 48 | E68: 42 | F68: 48 | G68: 42
A69: https://serco.sharepoint.com/sites/SA-M365Team-WBB-OrgDesign-USASACorgdesignstudy | D69: 15 | E69: 9 | F69: 15 | G69: 9
A70: https://serco.sharepoint.com/sites/SA-WBB-Beacon | B70: 199 | C70: 199 | D70: 1178 | E70: 1169 | F70: 1377 | G70: 1368
A71: https://serco.sharepoint.com/sites/SECWARAcqReformTeam | D71: 11 | E71: 5 | F71: 11 | G71: 5
A72: https://serco.sharepoint.com/sites/SERCOAirworthinessTeam | D72: 10 | E72: 4 | F72: 10 | G72: 4
A73: https://serco.sharepoint.com/sites/SercoArmyMarket-CampaignPlanning | D73: 19 | E73: 13 | F73: 19 | G73: 13
A74: https://serco.sharepoint.com/sites/SercoSourceSelectionTraining-ISSJ-III | D74: 8 | E74: 2 | F74: 8 | G74: 2
A75: https://serco.sharepoint.com/sites/SercoVetsLeadershipTeam | B75: 3 | C75: 3 | D75: 36 | E75: 28 | F75: 39 | G75: 31
A76: https://serco.sharepoint.com/sites/serco-wbb-competency-PDRIInnovativeThinking | D76: 7 | E76: 1 | F76: 7 | G76: 1
A77: https://serco.sharepoint.com/sites/SOCOMSupportSercoDirectContract-OCIPlan | D77: 8 | E77: 2 | F77: 8 | G77: 2
A78: https://serco.sharepoint.com/sites/SOCOMSupportSercoDirectContract-PMandContracting | D78: 10 | E78: 4 | F78: 10 | G78: 4
A79: https://serco.sharepoint.com/sites/SOCOMSupportSercoDirectContract-TO02-PEORWSupport | D79: 8 | E79: 2 | F79: 8 | G79: 2
A80: https://serco.sharepoint.com/sites/SOCOMSupportSercoDirectContract-TO06-HWW | D80: 8 | E80: 2 | F80: 8 | G80: 2
A81: https://serco.sharepoint.com/sites/SOCOMSupportSercoDirectContract-TO09-PEO-MPMMentoring | D81: 7 | E81: 1 | F81: 7 | G81: 1
A82: https://serco.sharepoint.com/sites/SOCOMSupportSercoDirectContract-TO10-PEOFWA2EAcqPlanning | D82: 7 | E82: 1 | F82: 7 | G82: 1
A83: https://serco.sharepoint.com/sites/SOCOMSupportSercoDirectContract-TOOX-GLSSSupport | D83: 11 | E83: 5 | F83: 11 | G83: 5
A84: https://serco.sharepoint.com/sites/SOCOMSupportSercoDirectContract-TOXX-ISSJ | D84: 8 | E84: 2 | F84: 8 | G84: 2
A85: https://serco.sharepoint.com/sites/SOCOMSupportSercoDirectContract-TOXX-MMDSSupport | D85: 11 | E85: 5 | F85: 11 | G85: 5
A86: https://serco.sharepoint.com/sites/SOCOMSupportSercoDirectContract-TOXX-PEOFWSupport | D86: 9 | E86: 4 | F86: 9 | G86: 4
A87: https://serco.sharepoint.com/sites/SOCOMSupportSercoDirectContract-TOXX-SOFGSD | D87: 8 | E87: 2 | F87: 8 | G87: 2
... A97: https://serco.sharepoint.com/sites/WBBOrgDesign-SE_VORGDesign | D97: 15 | E97: 9 | F97: 15 | G97: 9
A98: Grand Total | B98: 369 | C98: 369 | D98: 3167 | E98: 2603 | F98: 3536 | G98: 2972

Sheet AdditionalUsers
A1: UserEmail
A2: Francisco.Aguilar@serco-na.com
A3: Tanvir.Ahmed@serco-na.com
A4: Richard.Antorietto@serco-na.com
A5: Lucille.Arguijo@serco-na.com
A6: Sarah.Arthurs@serco-na.com
A7: Ishmael.Asah@serco-na.com
A8: Zoya.Augustus@serco-na.com
A9: Mel.Austin@serco-na.com
A10: Danielle.Bartley@serco-na.com
A11: Alejandro.Batista@serco-na.com
A12: Sabrina.Baumler@serco-na.com
... A350: Ronald.Rodriguez@serco-na.com

Sheet AdditionalUsersMinusBigSites
A1: Commercial UPN | B1: GCCH UPN | C1: Notes
A2: Levern.Keels@serco-na.com | B2: Levern.Keels@serco-na.us
A3: Ken.Long@serco-na.com | B3: Ken.Long@serco-na.us
A4: Dianna.Savage@serco-na.com | B4: Dianna.Savage@serco-na.us | C4: no longer exists
A5: Paulette.Terrell@serco-na.com | B5: Paulette.Terrell@serco-na.us
A6: Andy.AguilarSiguenza@serco-na.com | B6: Andy.AguilarSiguenza@serco-na.us
A7: David.Masini@serco-na.com | B7: David.Masini@serco-na.us
A8: Maura.Connolly@serco-na.com | B8: Maura.Connolly@serco-na.us
A9: Bryan.Miller@serco-na.com | B9: Bryan.Miller@serco-na.us
A10: Gabriel.Gentry@serco-na.com | B10: Gabriel.Gentry@serco-na.us
A11: Yolande.Parahoo-Doug@serco-na.com | B11: Yolande.Parahoo-Doug@serco-na.us
A12: Regina.Seetoo@serco-na.com | B12: Regina.Seetoo@serco-na.us
A13: Lorenzo.White@serco-na.com | B13: Lorenzo.White@serco-na.us | C13: moved in wave 1
A14: Ronald.Rodriguez@serco-na.com | B14: Ronald.Rodriguez@serco-na.us
